Workbook
Name JK_8: #REF!
Name JKRow14: #REF!
Name JKRow13: #REF!
Name City_3: #REF!
Name JK_EMPTY: #REF!
Name JKRow8: #REF!
Name City_4: #REF!
Name JKRow9: #REF!
Name JK_2: #REF!
Name JK_7: #REF!
Name JKRow5: #REF!
Name JK_4: #REF!
Name City_5: #REF!
Name JKRow12: #REF!
Name JKRow10: #REF!
Name JK_3: #REF!
Name JKRow7: #REF!
Name JKRow6: #REF!
Name JK_6: #REF!
Name JK_5: #REF!
Name JK_10: #REF!
Name City_2: #REF!
Name JK_9: #REF!
Name RegionList: #REF!
Name City_1: #REF!
Name JKRow11: #REF!
Name JK_11: #REF!
Name JK_1: #REF!

Sheet Стоп-лист
A2: Организации и продукции, запрещенные к размещению по ФЗ «О рекламе» от 13.03.2006 г. № 38-ФЗ
A3: 1 | B3: Организации и продукции, запрещенные к размещению по ФЗ «О рекламе» от 13.03.2006 г. № 38-ФЗ
A4: 2 | B4: Ритуальные услуги
A5: 3 | B5: Религиозные организации
A6: 6 | B6: Юридические услуги по получению отсрочек от воинской службы
A7: 7 | B7: Коллекторские организации
A8: 8 | B8: Интим-услуги
A9: 9 | B9: Народные целители
A10: 10 | B10: Финансовые пирамиды/криптовалюты
A11: Сфера развлечения
A12: 11 | B12: ночные клубы
A13: 12 | B13: букмекеры
A14: 13 | B14: лотереи
A15: 14 | B15: стриптиз-клубы
A16: Сфера товары
A17: 16 | B17: эротические товары
A18: 17 | B18: электронные сигареты,кальян
A19: 18 | B19: алкогольная продукция, лекарственные средства, биологически активные добавки
A20: 19 | B20: табак, табачная продукция, табачные изделий, никотинсодержащая продукция

Sheet Стоп-лист застройщики
A2: Регион | B2: Город | C2: ЖК | D2: Разрешено застройщикам
A3: =IFERROR(__xludf.DUMMYFUNCTION("SORT(UNIQUE(CHOOSECOLS(FILTER('Основной эфир'!B3:I1149,LEN('Основной эфир'!I3:I1149)>0),1,2,5)))"),"Московская область") -> Московская область | B3: =IFERROR(__xludf.DUMMYFUNCTION("""COMPUTED_VALUE"""),"Внуково") -> Внуково | C3: =IFERROR(__xludf.DUMMYFUNCTION("""COMPUTED_VALUE"""),"А") -> А | D3: нет
A4: =IFERROR(__xludf.DUMMYFUNCTION("""COMPUTED_VALUE"""),"Московская область") -> Московская область | B4: =IFERROR(__xludf.DUMMYFUNCTION("""COMPUTED_VALUE"""),"Красногорск") -> Красногорск | C4: =IFERROR(__xludf.DUMMYFUNCTION("""COMPUTED_VALUE"""),"Б") -> Б | D4: нет
A5: =IFERROR(__xludf.DUMMYFUNCTION("""COMPUTED_VALUE"""),"Московская область") -> Московская область | B5: =IFERROR(__xludf.DUMMYFUNCTION("""COMPUTED_VALUE"""),"Мисайлово") -> Мисайлово | C5: =IFERROR(__xludf.DUMMYFUNCTION("""COMPUTED_VALUE"""),"Б") -> Б | D5: нет
A6: =IFERROR(__xludf.DUMMYFUNCTION("""COMPUTED_VALUE"""),"Московская область") -> Московская область | B6: =IFERROR(__xludf.DUMMYFUNCTION("""COMPUTED_VALUE"""),"Одинцово") -> Одинцово | C6: =IFERROR(__xludf.DUMMYFUNCTION("""COMPUTED_VALUE"""),"А") -> А | D6: нет
A7: =IFERROR(__xludf.DUMMYFUNCTION("""COMPUTED_VALUE"""),"Московская область") -> Московская область | B7: =IFERROR(__xludf.DUMMYFUNCTION("""COMPUTED_VALUE"""),"Одинцово") -> Одинцово | C7: =IFERROR(__xludf.DUMMYFUNCTION("""COMPUTED_VALUE"""),"Б") -> Б | D7: да
A8: =IFERROR(__xludf.DUMMYFUNCTION("""COMPUTED_VALUE"""),"Московская область") -> Московская область | B8: =IFERROR(__xludf.DUMMYFUNCTION("""COMPUTED_VALUE"""),"Путилково") -> Путилково | C8: =IFERROR(__xludf.DUMMYFUNCTION("""COMPUTED_VALUE"""),"А") -> А | D8: да
A9: =IFERROR(__xludf.DUMMYFUNCTION("""COMPUTED_VALUE"""),"Московская область") -> Московская область | B9: =IFERROR(__xludf.DUMMYFUNCTION("""COMPUTED_VALUE"""),"Щербинка") -> Щербинка | C9: =IFERROR(__xludf.DUMMYFUNCTION("""COMPUTED_VALUE"""),"Б") -> Б | D9: да
A10: =IFERROR(__xludf.DUMMYFUNCTION("""COMPUTED_VALUE"""),"Нижегородская область") -> Нижегородская область | B10: =IFERROR(__xludf.DUMMYFUNCTION("""COMPUTED_VALUE"""),"Нижний Новгород") -> Нижний Новгород | C10: =IFERROR(__xludf.DUMMYFUNCTION("""COMPUTED_VALUE"""),"Б") -> Б | D10: нет
A11: =IFERROR(__xludf.DUMMYFUNCTION("""COMPUTED_VALUE"""),"Оренбургская область") -> Оренбургская область | B11: =IFERROR(__xludf.DUMMYFUNCTION("""COMPUTED_VALUE"""),"Оренбург") -> Оренбург | C11: =IFERROR(__xludf.DUMMYFUNCTION("""COMPUTED_VALUE"""),"А") -> А | D11: нет
A12: =IFERROR(__xludf.DUMMYFUNCTION("""COMPUTED_VALUE"""),"Оренбургская область") -> Оренбургская область | B12: =IFERROR(__xludf.DUMMYFUNCTION("""COMPUTED_VALUE"""),"Оренбург") -> Оренбург | C12: =IFERROR(__xludf.DUMMYFUNCTION("""COMPUTED_VALUE"""),"Б") -> Б | D12: нет
A13: =IFERROR(__xludf.DUMMYFUNCTION("""COMPUTED_VALUE"""),"Республика Башкортостан") -> Республика Башкортостан | B13: =IFERROR(__xludf.DUMMYFUNCTION("""COMPUTED_VALUE"""),"Нефтекамск") -> Нефтекамск | C13: =IFERROR(__xludf.DUMMYFUNCTION("""COMPUTED_VALUE"""),"Б") -> Б | D13: нет
A14: =IFERROR(__xludf.DUMMYFUNCTION("""COMPUTED_VALUE"""),"Республика Башкортостан") -> Республика Башкортостан | B14: =IFERROR(__xludf.DUMMYFUNCTION("""COMPUTED_VALUE"""),"Октябрьский") -> Октябрьский | C14: =IFERROR(__xludf.DUMMYFUNCTION("""COMPUTED_VALUE"""),"Б") -> Б | D14: нет
A15: =IFERROR(__xludf.DUMMYFUNCTION("""COMPUTED_VALUE"""),"Республика Башкортостан") -> Республика Башкортостан | B15: =IFERROR(__xludf.DUMMYFUNCTION("""COMPUTED_VALUE"""),"Стерлитамак") -> Стерлитамак | C15: =IFERROR(__xludf.DUMMYFUNCTION("""COMPUTED_VALUE"""),"А") -> А | D15: нет
A16: =IFERROR(__xludf.DUMMYFUNCTION("""COMPUTED_VALUE"""),"Республика Башкортостан") -> Республика Башкортостан | B16: =IFERROR(__xludf.DUMMYFUNCTION("""COMPUTED_VALUE"""),"Уфа") -> Уфа | C16: =IFERROR(__xludf.DUMMYFUNCTION("""COMPUTED_VALUE"""),"А") -> А | D16: нет
A17: =IFERROR(__xludf.DUMMYFUNCTION("""COMPUTED_VALUE"""),"Республика Башкортостан") -> Республика Башкортостан | B17: =IFERROR(__xludf.DUMMYFUNCTION("""COMPUTED_VALUE"""),"Уфа") -> Уфа | C17: =IFERROR(__xludf.DUMMYFUNCTION("""COMPUTED_VALUE"""),"Б") -> Б | D17: нет
A18: =IFERROR(__xludf.DUMMYFUNCTION("""COMPUTED_VALUE"""),"Республика Татарстан") -> Республика Татарстан | B18: =IFERROR(__xludf.DUMMYFUNCTION("""COMPUTED_VALUE"""),"Казань") -> Казань | C18: =IFERROR(__xludf.DUMMYFUNCTION("""COMPUTED_VALUE"""),"А") -> А | D18: нет
A19: =IFERROR(__xludf.DUMMYFUNCTION("""COMPUTED_VALUE"""),"Республика Татарстан") -> Республика Татарстан | B19: =IFERROR(__xludf.DUMMYFUNCTION("""COMPUTED_VALUE"""),"Казань") -> Казань | C19: =IFERROR(__xludf.DUMMYFUNCTION("""COMPUTED_VALUE"""),"Б") -> Б | D19: да
A20: =IFERROR(__xludf.DUMMYFUNCTION("""COMPUTED_VALUE"""),"Республика Татарстан") -> Республика Татарстан | B20: =IFERROR(__xludf.DUMMYFUNCTION("""COMPUTED_VALUE"""),"Усады") -> Усады | C20: =IFERROR(__xludf.DUMMYFUNCTION("""COMPUTED_VALUE"""),"Б") -> Б | D20: нет
D21: нет
D22: да
D23: да
D24: да
D25: да
D26: да
D27: да
D28: да
D29: да
D30: да
D31: да
D32: нет
... D357: да

Sheet СВОД АП
C1: СВОД Умных экранов по городам
A2: Регион | B2: Город | C2: Количество пакетов | D2: Карта ЖК | E2: Количество ЖК | F2: Количество домов | G2: Количество жильцов | H2: Всего экранов | I2: Цена за размещение на 1 экране/месяц руб. без НДС для Федерального и крупного бизнеса | J2: Цена за размещение на 1 экране/месяц руб. в т.ч НДС 22% для Федерального и крупного бизнеса | K2: Стоимость размещения в 1 доме/1 месяц, руб. без НДС для Федерального и крупного бизнеса | L2: Стоимость размещения в 1 доме/1 месяц, руб. в т.ч.НДС 22% для Федерального и крупного бизнеса | M2: ФО/скрин с камеры
A3: Республика Башкортостан | B3: Уфа | C3: =IFERROR(__xludf.DUMMYFUNCTION("COUNTUNIQUEIFS('Основной эфир'!E$3:E1004, 'Основной эфир'!C$3:C1004, B3, 'Основной эфир'!E$3:E1004, ""<>"") "),10.0) -> 10 | E3: =IFERROR(__xludf.DUMMYFUNCTION("COUNTUNIQUEIFS('Основной эфир'!I$3:I1004, 'Основной эфир'!C$3:C1004, B3, 'Основной эфир'!I$3:I1004, ""<>"") "),122.0) -> 122 | F3: =IFERROR(__xludf.DUMMYFUNCTION("COUNTUNIQUEIFS('Основной эфир'!J$3:J1004, 'Основной эфир'!C$3:C1004, B3, 'Основной эфир'!J$3:J1004, ""<>"") "),176.0) -> 176 | G3: =SUMIFS('Основной эфир'!$P$3:$P$1149,'Основной эфир'!$C$3:$C$1149,B3) -> 142724.4 | H3: =SUMIFS('Основной эфир'!$Q$3:$Q$1149,'Основной эфир'!$C$3:$C$1149,B3) -> 634 | I3: {=IFERROR(INDEX('Основной эфир'!$AI$3:$AI$1149,MATCH(B3,'Основной эфир'!$C$3:$C$1149,0)),"")} -> 3278.6885 | J3: {=IFERROR(INDEX('Основной эфир'!$AJ$3:$AJ$1149,MATCH(B3,'Основной эфир'!$C$3:$C$1149,0)),"")} -> 4000 | K3: =SUMIFS('Основной эфир'!$AK$3:$AK$1149,'Основной эфир'!$C$3:$C$1149,B3) -> 2078688.5 | L3: =SUMIFS('Основной эфир'!$AL$3:$AL$1149,'Основной эфир'!$C$3:$C$1149,B3) -> 2536000 | M3: 1
A4: Республика Башкортостан | B4: Стерлитамак | C4: =IFERROR(__xludf.DUMMYFUNCTION("COUNTUNIQUEIFS('Основной эфир'!E$3:E1004, 'Основной эфир'!C$3:C1004, B4, 'Основной эфир'!E$3:E1004, ""<>"") "),1.0) -> 1 | E4: =IFERROR(__xludf.DUMMYFUNCTION("COUNTUNIQUEIFS('Основной эфир'!I$3:I1004, 'Основной эфир'!C$3:C1004, B4, 'Основной эфир'!I$3:I1004, ""<>"") "),5.0) -> 5 | F4: =IFERROR(__xludf.DUMMYFUNCTION("COUNTUNIQUEIFS('Основной эфир'!J$3:J1004, 'Основной эфир'!C$3:C1004, B4, 'Основной эфир'!J$3:J1004, ""<>"") "),5.0) -> 5 | G4: =SUMIFS('Основной эфир'!$P$3:$P$1149,'Основной эфир'!$C$3:$C$1149,B4) -> 4690 | H4: =SUMIFS('Основной эфир'!$Q$3:$Q$1149,'Основной эфир'!$C$3:$C$1149,B4) -> 34 | I4: {=IFERROR(INDEX('Основной эфир'!$AI$3:$AI$1149,MATCH(B4,'Основной эфир'!$C$3:$C$1149,0)),"")} -> 3278.6885 | J4: {=IFERROR(INDEX('Основной эфир'!$AJ$3:$AJ$1149,MATCH(B4,'Основной эфир'!$C$3:$C$1149,0)),"")} -> 4000 | K4: =SUMIFS('Основной эфир'!$AK$3:$AK$1149,'Основной эфир'!$C$3:$C$1149,B4) -> 111475.41 | L4: =SUMIFS('Основной эфир'!$AL$3:$AL$1149,'Основной эфир'!$C$3:$C$1149,B4) -> 136000 | M4: 1
A5: Республика Башкортостан | B5: Нефтекамск | C5: =IFERROR(__xludf.DUMMYFUNCTION("COUNTUNIQUEIFS('Основной эфир'!E$3:E1004, 'Основной эфир'!C$3:C1004, B5, 'Основной эфир'!E$3:E1004, ""<>"") "),1.0) -> 1 | E5: =IFERROR(__xludf.DUMMYFUNCTION("COUNTUNIQUEIFS('Основной эфир'!I$3:I1004, 'Основной эфир'!C$3:C1004, B5, 'Основной эфир'!I$3:I1004, ""<>"") "),2.0) -> 2 | F5: =IFERROR(__xludf.DUMMYFUNCTION("COUNTUNIQUEIFS('Основной эфир'!J$3:J1004, 'Основной эфир'!C$3:C1004, B5, 'Основной эфир'!J$3:J1004, ""<>"") "),3.0) -> 3 | G5: =SUMIFS('Основной эфир'!$P$3:$P$1149,'Основной эфир'!$C$3:$C$1149,B5) -> 1968.4 | H5: =SUMIFS('Основной эфир'!$Q$3:$Q$1149,'Основной эфир'!$C$3:$C$1149,B5) -> 10 | I5: {=IFERROR(INDEX('Основной эфир'!$AI$3:$AI$1149,MATCH(B5,'Основной эфир'!$C$3:$C$1149,0)),"")} -> 3278.6885 | J5: {=IFERROR(INDEX('Основной эфир'!$AJ$3:$AJ$1149,MATCH(B5,'Основной эфир'!$C$3:$C$1149,0)),"")} -> 4000 | K5: =SUMIFS('Основной эфир'!$AK$3:$AK$1149,'Основной эфир'!$C$3:$C$1149,B5) -> 32786.885 | L5: =SUMIFS('Основной эфир'!$AL$3:$AL$1149,'Основной эфир'!$C$3:$C$1149,B5) -> 40000 | M5: 1
A6: Республика Башкортостан | B6: Октябрьский | C6: =IFERROR(__xludf.DUMMYFUNCTION("COUNTUNIQUEIFS('Основной эфир'!E$3:E1004, 'Основной эфир'!C$3:C1004, B6, 'Основной эфир'!E$3:E1004, ""<>"") "),1.0) -> 1 | E6: =IFERROR(__xludf.DUMMYFUNCTION("COUNTUNIQUEIFS('Основной эфир'!I$3:I1004, 'Основной эфир'!C$3:C1004, B6, 'Основной эфир'!I$3:I1004, ""<>"") "),1.0) -> 1 | F6: =IFERROR(__xludf.DUMMYFUNCTION("COUNTUNIQUEIFS('Основной эфир'!J$3:J1004, 'Основной эфир'!C$3:C1004, B6, 'Основной эфир'!J$3:J1004, ""<>"") "),1.0) -> 1 | G6: =SUMIFS('Основной эфир'!$P$3:$P$1149,'Основной эфир'!$C$3:$C$1149,B6) -> 658 | H6: =SUMIFS('Основной эфир'!$Q$3:$Q$1149,'Основной эфир'!$C$3:$C$1149,B6) -> 5 | I6: {=IFERROR(INDEX('Основной эфир'!$AI$3:$AI$1149,MATCH(B6,'Основной эфир'!$C$3:$C$1149,0)),"")} -> 3278.6885 | J6: {=IFERROR(INDEX('Основной эфир'!$AJ$3:$AJ$1149,MATCH(B6,'Основной эфир'!$C$3:$C$1149,0)),"")} -> 4000 | K6: =SUMIFS('Основной эфир'!$AK$3:$AK$1149,'Основной эфир'!$C$3:$C$1149,B6) -> 16393.443 | L6: =SUMIFS('Основной эфир'!$AL$3:$AL$1149,'Основной эфир'!$C$3:$C$1149,B6) -> 20000 | M6: 1
A7: Оренбургская область | B7: Оренбург | C7: =IFERROR(__xludf.DUMMYFUNCTION("COUNTUNIQUEIFS('Основной эфир'!E$3:E1004, 'Основной эфир'!C$3:C1004, B7, 'Основной эфир'!E$3:E1004, ""<>"") "),6.0) -> 6 | E7: =IFERROR(__xludf.DUMMYFUNCTION("COUNTUNIQUEIFS('Основной эфир'!I$3:I1004, 'Основной эфир'!C$3:C1004, B7, 'Основной эфир'!I$3:I1004, ""<>"") "),49.0) -> 49 | F7: =IFERROR(__xludf.DUMMYFUNCTION("COUNTUNIQUEIFS('Основной эфир'!J$3:J1004, 'Основной эфир'!C$3:C1004, B7, 'Основной эфир'!J$3:J1004, ""<>"") "),108.0) -> 108 | G7: =SUMIFS('Основной эфир'!$P$3:$P$1149,'Основной эфир'!$C$3:$C$1149,B7) -> 94802.4 | H7: =SUMIFS('Основной эфир'!$Q$3:$Q$1149,'Основной эфир'!$C$3:$C$1149,B7) -> 507 | I7: {=IFERROR(INDEX('Основной эфир'!$AI$3:$AI$1149,MATCH(B7,'Основной эфир'!$C$3:$C$1149,0)),"")} -> 3278.6885 | J7: {=IFERROR(INDEX('Основной эфир'!$AJ$3:$AJ$1149,MATCH(B7,'Основной эфир'!$C$3:$C$1149,0)),"")} -> 4000 | K7: =SUMIFS('Основной эфир'!$AK$3:$AK$1149,'Основной эфир'!$C$3:$C$1149,B7) -> 1662295.1 | L7: =SUMIFS('Основной эфир'!$AL$3:$AL$1149,'Основной эфир'!$C$3:$C$1149,B7) -> 2028000 | M7: 1
A8: Нижегородская область | B8: Нижний Новгород | C8: =IFERROR(__xludf.DUMMYFUNCTION("COUNTUNIQUEIFS('Основной эфир'!E$3:E1004, 'Основной эфир'!C$3:C1004, B8, 'Основной эфир'!E$3:E1004, ""<>"") "),7.0) -> 7 | E8: =IFERROR(__xludf.DUMMYFUNCTION("COUNTUNIQUEIFS('Основной эфир'!I$3:I1004, 'Основной эфир'!C$3:C1004, B8, 'Основной эфир'!I$3:I1004, ""<>"") "),71.0) -> 71 | F8: =IFERROR(__xludf.DUMMYFUNCTION("COUNTUNIQUEIFS('Основной эфир'!J$3:J1004, 'Основной эфир'!C$3:C1004, B8, 'Основной эфир'!J$3:J1004, ""<>"") "),112.0) -> 112 | G8: =SUMIFS('Основной эфир'!$P$3:$P$1149,'Основной эфир'!$C$3:$C$1149,B8) -> 54975.2 | H8: =SUMIFS('Основной эфир'!$Q$3:$Q$1149,'Основной эфир'!$C$3:$C$1149,B8) -> 400 | I8: {=IFERROR(INDEX('Основной эфир'!$AI$3:$AI$1149,MATCH(B8,'Основной эфир'!$C$3:$C$1149,0)),"")} -> 3278.6885 | J8: {=IFERROR(INDEX('Основной эфир'!$AJ$3:$AJ$1149,MATCH(B8,'Основной эфир'!$C$3:$C$1149,0)),"")} -> 4000 | K8: =SUMIFS('Основной эфир'!$AK$3:$AK$1149,'Основной эфир'!$C$3:$C$1149,B8) -> 1311475.4 | L8: =SUMIFS('Основной эфир'!$AL$3:$AL$1149,'Основной эфир'!$C$3:$C$1149,B8) -> 1600000 | M8: 1
A9: Республика Татарстан | B9: Казань | C9: =IFERROR(__xludf.DUMMYFUNCTION("COUNTUNIQUEIFS('Основной эфир'!E$3:E1004, 'Основной эфир'!C$3:C1004, B9, 'Основной эфир'!E$3:E1004, ""<>"") "),10.0) -> 10 | E9: =IFERROR(__xludf.DUMMYFUNCTION("COUNTUNIQUEIFS('Основной эфир'!I$3:I1004, 'Основной эфир'!C$3:C1004, B9, 'Основной эфир'!I$3:I1004, ""<>"") "),84.0) -> 84 | F9: =IFERROR(__xludf.DUMMYFUNCTION("COUNTUNIQUEIFS('Основной эфир'!J$3:J1004, 'Основной эфир'!C$3:C1004, B9, 'Основной эфир'!J$3:J1004, ""<>"") "),138.0) -> 138 | G9: =SUMIFS('Основной эфир'!$P$3:$P$1149,'Основной эфир'!$C$3:$C$1149,B9) -> 77268.8 | H9: =SUMIFS('Основной эфир'!$Q$3:$Q$1149,'Основной эфир'!$C$3:$C$1149,B9) -> 506 | I9: {=IFERROR(INDEX('Основной эфир'!$AI$3:$AI$1149,MATCH(B9,'Основной эфир'!$C$3:$C$1149,0)),"")} -> 3278.6885 | J9: {=IFERROR(INDEX('Основной эфир'!$AJ$3:$AJ$1149,MATCH(B9,'Основной эфир'!$C$3:$C$1149,0)),"")} -> 4000 | K9: =SUMIFS('Основной эфир'!$AK$3:$AK$1149,'Основной эфир'!$C$3:$C$1149,B9) -> 1659016.4 | L9: =SUMIFS('Основной эфир'!$AL$3:$AL$1149,'Основной эфир'!$C$3:$C$1149,B9) -> 2024000 | M9: 1
A10: Республика Татарстан | B10: Усады | C10: =IFERROR(__xludf.DUMMYFUNCTION("COUNTUNIQUEIFS('Основной эфир'!E$3:E1004, 'Основной эфир'!C$3:C1004, B10, 'Основной эфир'!E$3:E1004, ""<>"") "),1.0) -> 1 | E10: =IFERROR(__xludf.DUMMYFUNCTION("COUNTUNIQUEIFS('Основной эфир'!I$3:I1004, 'Основной эфир'!C$3:C1004, B10, 'Основной эфир'!I$3:I1004, ""<>"") "),1.0) -> 1 | F10: =IFERROR(__xludf.DUMMYFUNCTION("COUNTUNIQUEIFS('Основной эфир'!J$3:J1004, 'Основной эфир'!C$3:C1004, B10, 'Основной эфир'!J$3:J1004, ""<>"") "),7.0) -> 7 | G10: =SUMIFS('Основной эфир'!$P$3:$P$1149,'Основной эфир'!$C$3:$C$1149,B10) -> 2993.2 | H10: =SUMIFS('Основной эфир'!$Q$3:$Q$1149,'Основной эфир'!$C$3:$C$1149,B10) -> 12 | I10: {=IFERROR(INDEX('Основной эфир'!$AI$3:$AI$1149,MATCH(B10,'Основной эфир'!$C$3:$C$1149,0)),"")} -> 3278.6885 | J10: {=IFERROR(INDEX('Основной эфир'!$AJ$3:$AJ$1149,MATCH(B10,'Основной эфир'!$C$3:$C$1149,0)),"")} -> 4000 | K10: =SUMIFS('Основной эфир'!$AK$3:$AK$1149,'Основной эфир'!$C$3:$C$1149,B10) -> 39344.262 | L10: =SUMIFS('Основной эфир'!$AL$3:$AL$1149,'Основной эфир'!$C$3:$C$1149,B10) -> 48000 | M10: 1
A11: Московская область | B11: Путилково | C11: =IFERROR(__xludf.DUMMYFUNCTION("COUNTUNIQUEIFS('Основной эфир'!E$3:E1004, 'Основной эфир'!C$3:C1004, B11, 'Основной эфир'!E$3:E1004, ""<>"") "),1.0) -> 1 | E11: =IFERROR(__xludf.DUMMYFUNCTION("COUNTUNIQUEIFS('Основной эфир'!I$3:I1004, 'Основной эфир'!C$3:C1004, B11, 'Основной эфир'!I$3:I1004, ""<>"") "),4.0) -> 4 | F11: =IFERROR(__xludf.DUMMYFUNCTION("COUNTUNIQUEIFS('Основной эфир'!J$3:J1004, 'Основной эфир'!C$3:C1004, B11, 'Основной эфир'!J$3:J1004, ""<>"") "),11.0) -> 11 | G11: =SUMIFS('Основной эфир'!$P$3:$P$1149,'Основной эфир'!$C$3:$C$1149,B11) -> 11765.6 | H11: =SUMIFS('Основной эфир'!$Q$3:$Q$1149,'Основной эфир'!$C$3:$C$1149,B11) -> 48 | I11: {=IFERROR(INDEX('Основной эфир'!$AI$3:$AI$1149,MATCH(B11,'Основной эфир'!$C$3:$C$1149,0)),"")} -> 3278.6885 | J11: {=IFERROR(INDEX('Основной эфир'!$AJ$3:$AJ$1149,MATCH(B11,'Основной эфир'!$C$3:$C$1149,0)),"")} -> 4000 | K11: =SUMIFS('Основной эфир'!$AK$3:$AK$1149,'Основной эфир'!$C$3:$C$1149,B11) -> 157377.05 | L11: =SUMIFS('Основной эфир'!$AL$3:$AL$1149,'Основной эфир'!$C$3:$C$1149,B11) -> 192000 | M11: 1
A12: Московская область | B12: Одинцово | C12: =IFERROR(__xludf.DUMMYFUNCTION("COUNTUNIQUEIFS('Основной эфир'!E$3:E1004, 'Основной эфир'!C$3:C1004, B12, 'Основной эфир'!E$3:E1004, ""<>"") "),1.0) -> 1 | E12: =IFERROR(__xludf.DUMMYFUNCTION("COUNTUNIQUEIFS('Основной эфир'!I$3:I1004, 'Основной эфир'!C$3:C1004, B12, 'Основной эфир'!I$3:I1004, ""<>"") "),9.0) -> 9 | F12: =IFERROR(__xludf.DUMMYFUNCTION("COUNTUNIQUEIFS('Основной эфир'!J$3:J1004, 'Основной эфир'!C$3:C1004, B12, 'Основной эфир'!J$3:J1004, ""<>"") "),17.0) -> 17 | G12: =SUMIFS('Основной эфир'!$P$3:$P$1149,'Основной эфир'!$C$3:$C$1149,B12) -> 19171.6 | H12: =SUMIFS('Основной эфир'!$Q$3:$Q$1149,'Основной эфир'!$C$3:$C$1149,B12) -> 82 | I12: {=IFERROR(INDEX('Основной эфир'!$AI$3:$AI$1149,MATCH(B12,'Основной эфир'!$C$3:$C$1149,0)),"")} -> 3278.6885 | J12: {=IFERROR(INDEX('Основной эфир'!$AJ$3:$AJ$1149,MATCH(B12,'Основной эфир'!$C$3:$C$1149,0)),"")} -> 4000 | K12: =SUMIFS('Основной эфир'!$AK$3:$AK$1149,'Основной эфир'!$C$3:$C$1149,B12) -> 268852.46 | L12: =SUMIFS('Основной эфир'!$AL$3:$AL$1149,'Основной эфир'!$C$3:$C$1149,B12) -> 328000 | M12: 1
A13: Московская область | B13: Красногорск | C13: =IFERROR(__xludf.DUMMYFUNCTION("COUNTUNIQUEIFS('Основной эфир'!E$3:E1004, 'Основной эфир'!C$3:C1004, B13, 'Основной эфир'!E$3:E1004, ""<>"") "),1.0) -> 1 | E13: =IFERROR(__xludf.DUMMYFUNCTION("COUNTUNIQUEIFS('Основной эфир'!I$3:I1004, 'Основной эфир'!C$3:C1004, B13, 'Основной эфир'!I$3:I1004, ""<>"") "),3.0) -> 3 | F13: =IFERROR(__xludf.DUMMYFUNCTION("COUNTUNIQUEIFS('Основной эфир'!J$3:J1004, 'Основной эфир'!C$3:C1004, B13, 'Основной эфир'!J$3:J1004, ""<>"") "),5.0) -> 5 | G13: =SUMIFS('Основной эфир'!$P$3:$P$1149,'Основной эфир'!$C$3:$C$1149,B13) -> 12521.6 | H13: =SUMIFS('Основной эфир'!$Q$3:$Q$1149,'Основной эфир'!$C$3:$C$1149,B13) -> 28 | I13: {=IFERROR(INDEX('Основной эфир'!$AI$3:$AI$1149,MATCH(B13,'Основной эфир'!$C$3:$C$1149,0)),"")} -> 3278.6885 | J13: {=IFERROR(INDEX('Основной эфир'!$AJ$3:$AJ$1149,MATCH(B13,'Основной эфир'!$C$3:$C$1149,0)),"")} -> 4000 | K13: =SUMIFS('Основной эфир'!$AK$3:$AK$1149,'Основной эфир'!$C$3:$C$1149,B13) -> 91803.279 | L13: =SUMIFS('Основной эфир'!$AL$3:$AL$1149,'Основной эфир'!$C$3:$C$1149,B13) -> 112000 | M13: 1
A14: Московская область | B14: Мисайлово | C14: =IFERROR(__xludf.DUMMYFUNCTION("COUNTUNIQUEIFS('Основной эфир'!E$3:E1004, 'Основной эфир'!C$3:C1004, B14, 'Основной эфир'!E$3:E1004, ""<>"") "),1.0) -> 1 | E14: =IFERROR(__xludf.DUMMYFUNCTION("COUNTUNIQUEIFS('Основной эфир'!I$3:I1004, 'Основной эфир'!C$3:C1004, B14, 'Основной эфир'!I$3:I1004, ""<>"") "),9.0) -> 9 | F14: =IFERROR(__xludf.DUMMYFUNCTION("COUNTUNIQUEIFS('Основной эфир'!J$3:J1004, 'Основной эфир'!C$3:C1004, B14, 'Основной эфир'!J$3:J1004, ""<>"") "),28.0) -> 28 | G14: =SUMIFS('Основной эфир'!$P$3:$P$1149,'Основной эфир'!$C$3:$C$1149,B14) -> 27244 | H14: =SUMIFS('Основной эфир'!$Q$3:$Q$1149,'Основной эфир'!$C$3:$C$1149,B14) -> 84 | I14: {=IFERROR(INDEX('Основной эфир'!$AI$3:$AI$1149,MATCH(B14,'Основной эфир'!$C$3:$C$1149,0)),"")} -> 3278.6885 | J14: {=IFERROR(INDEX('Основной эфир'!$AJ$3:$AJ$1149,MATCH(B14,'Основной эфир'!$C$3:$C$1149,0)),"")} -> 4000 | K14: =SUMIFS('Основной эфир'!$AK$3:$AK$1149,'Основной эфир'!$C$3:$C$1149,B14) -> 275409.84 | L14: =SUMIFS('Основной эфир'!$AL$3:$AL$1149,'Основной эфир'!$C$3:$C$1149,B14) -> 336000 | M14: 1
A15: Московская область | B15: Внуково | C15: =IFERROR(__xludf.DUMMYFUNCTION("COUNTUNIQUEIFS('Основной эфир'!E$3:E1004, 'Основной эфир'!C$3:C1004, B15, 'Основной эфир'!E$3:E1004, ""<>"") "),1.0) -> 1 | E15: =IFERROR(__xludf.DUMMYFUNCTION("COUNTUNIQUEIFS('Основной эфир'!I$3:I1004, 'Основной эфир'!C$3:C1004, B15, 'Основной эфир'!I$3:I1004, ""<>"") "),4.0) -> 4 | F15: =IFERROR(__xludf.DUMMYFUNCTION("COUNTUNIQUEIFS('Основной эфир'!J$3:J1004, 'Основной эфир'!C$3:C1004, B15, 'Основной эфир'!J$3:J1004, ""<>"") "),16.0) -> 16 | G15: =SUMIFS('Основной эфир'!$P$3:$P$1149,'Основной эфир'!$C$3:$C$1149,B15) -> 9240 | H15: =SUMIFS('Основной эфир'!$Q$3:$Q$1149,'Основной эфир'!$C$3:$C$1149,B15) -> 29 | I15: {=IFERROR(INDEX('Основной эфир'!$AI$3:$AI$1149,MATCH(B15,'Основной эфир'!$C$3:$C$1149,0)),"")} -> 3278.6885 | J15: {=IFERROR(INDEX('Основной эфир'!$AJ$3:$AJ$1149,MATCH(B15,'Основной эфир'!$C$3:$C$1149,0)),"")} -> 4000 | K15: =SUMIFS('Основной эфир'!$AK$3:$AK$1149,'Основной эфир'!$C$3:$C$1149,B15) -> 95081.967 | L15: =SUMIFS('Основной эфир'!$AL$3:$AL$1149,'Основной эфир'!$C$3:$C$1149,B15) -> 116000 | M15: 1
A16: Московская область | B16: Щербинка | C16: =IFERROR(__xludf.DUMMYFUNCTION("COUNTUNIQUEIFS('Основной эфир'!E$3:E1004, 'Основной эфир'!C$3:C1004, B16, 'Основной эфир'!E$3:E1004, ""<>"") "),1.0) -> 1 | E16: =IFERROR(__xludf.DUMMYFUNCTION("COUNTUNIQUEIFS('Основной эфир'!I$3:I1004, 'Основной эфир'!C$3:C1004, B16, 'Основной эфир'!I$3:I1004, ""<>"") "),13.0) -> 13 | F16: =IFERROR(__xludf.DUMMYFUNCTION("COUNTUNIQUEIFS('Основной эфир'!J$3:J1004, 'Основной эфир'!C$3:C1004, B16, 'Основной эфир'!J$3:J1004, ""<>"") "),26.0) -> 26 | G16: =SUMIFS('Основной эфир'!$P$3:$P$1149,'Основной эфир'!$C$3:$C$1149,B16) -> 33625.2 | H16: =SUMIFS('Основной эфир'!$Q$3:$Q$1149,'Основной эфир'!$C$3:$C$1149,B16) -> 102 | I16: {=IFERROR(INDEX('Основной эфир'!$AI$3:$AI$1149,MATCH(B16,'Основной эфир'!$C$3:$C$1149,0)),"")} -> 3278.6885 | J16: {=IFERROR(INDEX('Основной эфир'!$AJ$3:$AJ$1149,MATCH(B16,'Основной эфир'!$C$3:$C$1149,0)),"")} -> 4000 | K16: =SUMIFS('Основной эфир'!$AK$3:$AK$1149,'Основной эфир'!$C$3:$C$1149,B16) -> 334426.23 | L16: =SUMIFS('Основной эфир'!$AL$3:$AL$1149,'Основной эфир'!$C$3:$C$1149,B16) -> 408000 | M16: 1
A17: Всего | B17: =COUNTA(B3:B16) -> 14 | C17: =IFERROR(__xludf.DUMMYFUNCTION("COUNTUNIQUEIFS('Основной эфир'!E$3:E1004, 'Основной эфир'!C$3:C1004, B17, 'Основной эфир'!E$3:E1004, ""<>"") "),0.0) -> 0 | E17: =SUM(E3:E16) -> 377 | F17: =SUM(F3:F16) -> 653 | H17: =SUM(H3:H16) -> 2481 | K17: =SUM(K3:K16) -> 8134426.2 | L17: =SUM(L3:L16) -> 9924000

Sheet Основной эфир
D1: Прайс на размещение рекламного ролика
A2: GID | B2: Регион | C2: Город | D2: Район | E2: Название пакета | F2: Категория ЖК | G2: Дата застройки экранов | H2: Класс жилья | I2: Наименование ЖК | J2: Адрес | K2: Коррдинаты (широта, долгота) | M2: Год сдачи дома | N2: Этажность | O2: Количество квартир | P2: Количество жильцов | Q2: Всего экранов | R2: Число экранов в холле | S2: Всего холлов в доме | T2: Число экранов в лифте | U2: Всего лифтов в доме | V2: Тип экрана | W2: Способ показа | X2: Формат | Y2: Хронометраж (сек) | Z2: Блок | AA2: Кол-во показов в сутки/1 экран (сек) | AB2: Период/дней | AC2: Кол-во показов в ЖК/период | AD2: Частота контакта рекламы c 1 жителем (Frequency) | AE2: Количество контактов с рекламой (OTS) | AF2: Стоимость 1000 контактов (CPT) с НДС для Федерального и крупного бизнеса | AG2: ФО/скрин с камеры | AH2: Фото | AI2: Цена за размещение на 1 экране/месяц руб. без НДС | AJ2: Цена за размещение на 1 экране/месяц руб. в т.ч НДС 22% | AK2: Стоимость размещения в 1 доме/1 месяц, руб. без НДС | AL2: Стоимость размещения в 1 доме/1 месяц, руб. в т.ч.НДС 22%
A3: U1 | B3: Республика Башкортостан | C3: Уфа | D3: Ленинский | E3: Проспект | F3: А | G3: 45839 | H3: Бизнес | I3: ЖК Видинеевский | J3: улица Пархоменко, 156Б | K3: 54.743697 | L3: 55.969246 | M3: 2021 | N3: 14 | O3: 412 | P3: =O3*2.8 -> 1153.6 | Q3: 2 | R3: 1 | S3: 3 | T3: 1 | U3: 6 | V3: Горизонтальный 4*3 | W3: Digital (без звука) | X3: видеоролик | Y3: 10 | Z3: 150 | AA3: 576 | AB3: 31 | AC3: =Q3*AA3*AB3 -> 35712 | AD3: =AE3/P3 -> 5.1942222 | AE3: =((P3*2.6*R3/S3/2)*30/Z3+(P3*2.6*T3/U3)*N3*2/Z3)*AB3 -> 5992.0548 | AF3: =AL3/AE3*1000 -> 1335.1013 | AG3: 1 | AH3: https://ibb.co/1S8hzvX | AI3: =AJ3/1.22 -> 3278.6885 | AJ3: 4000 | AK3: =AI3*Q3 -> 6557.377 | AL3: =AK3*1.22 -> 8000
A4: U1 | B4: Республика Башкортостан | C4: Уфа | D4: Ленинский | E4: Проспект | F4: А | G4: 45839 | H4: Бизнес | I4: ЖК Видинеевский | J4: улица Пархоменко, 156В | K4: 54.744659 | L4: 55.969713 | M4: 2019 | N4: 26 | O4: 232 | P4: =O4*2.8 -> 649.6 | Q4: 2 | R4: 1 | S4: 1 | T4: 1 | U4: 3 | V4: Горизонтальный 4*3 | W4: Digital (без звука) | X4: видеоролик | Y4: 10 | Z4: 150 | AA4: 576 | AB4: 31 | AC4: =Q4*AA4*AB4 -> 35712 | AD4: =AE4/P4 -> 17.373778 | AE4: =((P4*2.6*R4/S4/2)*30/Z4+(P4*2.6*T4/U4)*N4*2/Z4)*AB4 -> 11286.006 | AF4: =AL4/AE4*1000 -> 708.84243 | AG4: 1 | AH4: https://ibb.co/1pfqR3G | AI4: =AJ4/1.22 -> 3278.6885 | AJ4: 4000 | AK4: =AI4*Q4 -> 6557.377 | AL4: =AK4*1.22 -> 8000
A5: U1 | B5: Республика Башкортостан | C5: Уфа | D5: Ленинский | E5: Проспект | F5: А | G5: 45839 | H5: Бизнес | I5: ЖК Видинеевский | J5: улица Пархоменко, 156Г | K5: 54.744939 | L5: 55.970603 | M5: 2023 | N5: 25 | O5: 173 | P5: =O5*2.8 -> 484.4 | Q5: 1 | R5: 0 | S5: 1 | T5: 1 | U5: 3 | V5: Горизонтальный 4*3 | W5: Digital (без звука) | X5: видеоролик | Y5: 10 | Z5: 150 | AA5: 576 | AB5: 31 | AC5: =Q5*AA5*AB5 -> 17856 | AD5: =AE5/P5 -> 8.9555556 | AE5: =((P5*2.6*R5/S5/2)*30/Z5+(P5*2.6*T5/U5)*N5*2/Z5)*AB5 -> 4338.0711 | AF5: =AL5/AE5*1000 -> 922.06879 | AG5: 1 | AI5: =AJ5/1.22 -> 3278.6885 | AJ5: 4000 | AK5: =AI5*Q5 -> 3278.6885 | AL5: =AK5*1.22 -> 4000
A6: U1 | B6: Республика Башкортостан | C6: Уфа | D6: Ленинский | E6: Проспект | F6: А | G6: 45839 | H6: Бизнес | I6: ЖК Видинеевский | J6: лица Пархоменко, 156Е | K6: 54.744482 | L6: 55.972408 | M6: 2025 | N6: 26 | O6: 233 | P6: =O6*2.8 -> 652.4 | Q6: 3 | R6: 0 | S6: 1 | T6: 3 | U6: 3 | V6: Горизонтальный 4*3 | W6: Digital (без звука) | X6: видеоролик | Y6: 10 | Z6: 150 | AA6: 576 | AB6: 31 | AC6: =Q6*AA6*AB6 -> 53568 | AD6: =AE6/P6 -> 27.941333 | AE6: =((P6*2.6*R6/S6/2)*30/Z6+(P6*2.6*T6/U6)*N6*2/Z6)*AB6 -> 18228.926 | AF6: =AL6/AE6*1000 -> 658.29441 | AG6: 1 | AI6: =AJ6/1.22 -> 3278.6885 | AJ6: 4000 | AK6: =AI6*Q6 -> 9836.0656 | AL6: =AK6*1.22 -> 12000
A7: U1 | B7: Республика Башкортостан | C7: Уфа | D7: Ленинский | E7: Проспект | F7: А | G7: 45839 | H7: Бизнес | I7: ЖК Видинеевский | J7: улица Пархоменко, 156Ж | K7: 54.743999 | L7: 55.972094 | M7: 2024 | N7: 15 | O7: 289 | P7: =O7*2.8 -> 809.2 | Q7: 4 | R7: 2 | S7: 1 | T7: 2 | U7: 4 | V7: Горизонтальный 4*3 | W7: Digital (без звука) | X7: видеоролик | Y7: 10 | Z7: 150 | AA7: 576 | AB7: 31 | AC7: =Q7*AA7*AB7 -> 71424 | AD7: =AE7/P7 -> 24.18 | AE7: =((P7*2.6*R7/S7/2)*30/Z7+(P7*2.6*T7/U7)*N7*2/Z7)*AB7 -> 19566.456 | AF7: =AL7/AE7*1000 -> 817.72601 | AG7: 1 | AI7: =AJ7/1.22 -> 3278.6885 | AJ7: 4000 | AK7: =AI7*Q7 -> 13114.754 | AL7: =AK7*1.22 -> 16000
A8: U2 | B8: Республика Башкортостан | C8: Уфа | D8: Кировский | E8: Зеленая Роща 2 | F8: Б | G8: 45985 | H8: Комфорт | I8: ЖК Южный | J8: улица Генерала Рыленко, 8 | K8: 54.695476 | L8: 55.989638 | M8: 2021 | N8: 28 | O8: 301 | P8: =O8*2.8 -> 842.8 | Q8: 3 | R8: 1 | S8: 1 | T8: 2 | U8: 4 | V8: Горизонтальный 4*3 | W8: Digital (без звука) | X8: видеоролик | Y8: 10 | Z8: 150 | AA8: 576 | AB8: 31 | AC8: =Q8*AA8*AB8 -> 53568 | AD8: =AE8/P8 -> 23.105333 | AE8: =((P8*2.6*R8/S8/2)*30/Z8+(P8*2.6*T8/U8)*N8*2/Z8)*AB8 -> 19473.175 | AF8: =AL8/AE8*1000 -> 616.23233 | AG8: 1 | AI8: =AJ8/1.22 -> 3278.6885 | AJ8: 4000 | AK8: =AI8*Q8 -> 9836.0656 | AL8: =AK8*1.22 -> 12000
A9: U3 | B9: Республика Башкортостан | C9: Уфа | D9: Кировский | E9: Центр | F9: А | G9: 45950 | H9: Бизнес | I9: ЖК Выбор первых | J9: улица Айская, 61 | K9: 54.727375 | L9: 55.976172 | M9: 2024 | N9: 10 | O9: 329 | P9: =O9*2.8 -> 921.2 | Q9: 5 | R9: 0 | S9: 5 | T9: 5 | U9: 5 | V9: Горизонтальный 4*3 | W9: Digital (без звука) | X9: видеоролик | Y9: 10 | Z9: 150 | AA9: 576 | AB9: 31 | AC9: =Q9*AA9*AB9 -> 89280 | AD9: =AE9/P9 -> 10.746667 | AE9: =((P9*2.6*R9/S9/2)*30/Z9+(P9*2.6*T9/U9)*N9*2/Z9)*AB9 -> 9899.8293 | AF9: =AL9/AE9*1000 -> 2020.2368 | AG9: 1 | AI9: =AJ9/1.22 -> 3278.6885 | AJ9: 4000 | AK9: =AI9*Q9 -> 16393.443 | AL9: =AK9*1.22 -> 20000
A10: U4 | B10: Республика Башкортостан | C10: Уфа | D10: Калининский | E10: Инорс_Сипайлово | F10: Б | G10: 45961 | H10: Стандарт | I10: ЖК Акварель | J10: улица Лётчика Кобелева, 1 | K10: 54.778409 | L10: 56.137887 | M10: 2023 | N10: 19 | O10: 102 | P10: =O10*2.8 -> 285.6 | Q10: 1 | R10: 1 | S10: 8 | T10: 0 | U10: 16 | V10: Горизонтальный 4*3 | W10: Digital (без звука) | X10: видеоролик | Y10: 10 | Z10: 150 | AA10: 576 | AB10: 31 | AC10: =Q10*AA10*AB10 -> 17856 | AD10: =AE10/P10 -> 1.0075 | AE10: =((P10*2.6*R10/S10/2)*30/Z10+(P10*2.6*T10/U10)*N10*2/Z10)*AB10 -> 287.742 | AF10: =AL10/AE10*1000 -> 13901.342 | AG10: 1 | AI10: =AJ10/1.22 -> 3278.6885 | AJ10: 4000 | AK10: =AI10*Q10 -> 3278.6885 | AL10: =AK10*1.22 -> 4000
A11: U4 | B11: Республика Башкортостан | C11: Уфа | D11: Калининский | E11: Инорс_Сипайлово | F11: Б | G11: 45961 | H11: Стандарт | I11: ЖК Акварель | J11: улица Лётчика Кобелева, 3/3 | K11: 54.778180 | L11: 56.134411 | M11: 2018 | N11: 27 | O11: 338 | P11: =O11*2.8 -> 946.4 | Q11: 1 | R11: 1 | S11: 1 | T11: 0 | U11: 3 | V11: Горизонтальный 4*3 | W11: Digital (без звука) | X11: видеоролик | Y11: 10 | Z11: 150 | AA11: 576 | AB11: 31 | AC11: =Q11*AA11*AB11 -> 17856 | AD11: =AE11/P11 -> 8.06 | AE11: =((P11*2.6*R11/S11/2)*30/Z11+(P11*2.6*T11/U11)*N11*2/Z11)*AB11 -> 7627.984 | AF11: =AL11/AE11*1000 -> 524.38495 | AG11: 1 | AI11: =AJ11/1.22 -> 3278.6885 | AJ11: 4000 | AK11: =AI11*Q11 -> 3278.6885 | AL11: =AK11*1.22 -> 4000
A12: U4 | B12: Республика Башкортостан | C12: Уфа | D12: Калининский | E12: Инорс_Сипайлово | F12: Б | G12: 45961 | H12: Стандарт | I12: ЖК Акварель | J12: улица Ферина, 33 | K12: 54.777126 | L12: 56.132030 | M12: 2017 | N12: 18 | O12: 187 | P12: =O12*2.8 -> 523.6 | Q12: 2 | R12: 0 | S12: 2 | T12: 2 | U12: 4 | V12: Вертикальный 4*3 | W12: Digital (без звука) | X12: видеоролик | Y12: 10 | Z12: 150 | AA12: 576 | AB12: 31 | AC12: =Q12*AA12*AB12 -> 35712 | AD12: =AE12/P12 -> 9.672 | AE12: =((P12*2.6*R12/S12/2)*30/Z12+(P12*2.6*T12/U12)*N12*2/Z12)*AB12 -> 5064.2592 | AF12: =AL12/AE12*1000 -> 1579.698 | AG12: 1 | AI12: =AJ12/1.22 -> 3278.6885 | AJ12: 4000 | AK12: =AI12*Q12 -> 6557.377 | AL12: =AK12*1.22 -> 8000
A13: U5 | B13: Республика Башкортостан | C13: Уфа | D13: Ленинский | E13: Центр | F13: Б | G13: 45961 | H13: Бизнес | I13: ЖК Старый центр | J13: улица Чернышевского, 26 | K13: 54.731545 | L13: 55.928831 | M13: 2023 | N13: 19 | O13: 321 | P13: =O13*2.8 -> 898.8 | Q13: 2 | R13: 2 | S13: 2 | T13: 0 | U13: 4 | V13: Горизонтальный 4*3 | W13: Digital (без звука) | X13: видеоролик | Y13: 10 | Z13: 150 | AA13: 576 | AB13: 31 | AC13: =Q13*AA13*AB13 -> 35712 | AD13: =AE13/P13 -> 8.06 | AE13: =((P13*2.6*R13/S13/2)*30/Z13+(P13*2.6*T13/U13)*N13*2/Z13)*AB13 -> 7244.328 | AF13: =AL13/AE13*1000 -> 1104.3122 | AG13: 1 | AI13: =AJ13/1.22 -> 3278.6885 | AJ13: 4000 | AK13: =AI13*Q13 -> 6557.377 | AL13: =AK13*1.22 -> 8000
A14: U5 | B14: Республика Башкортостан | C14: Уфа | D14: Ленинский | E14: Центр | F14: Б | G14: 45961 | H14: Бизнес | I14: ЖК Старый центр | J14: улица Коммунистическая, 15 | K14: 54.729512 | L14: 55.929083 | M14: 2020 | N14: 15 | O14: 151 | P14: =O14*2.8 -> 422.8 | Q14: 2 | R14: 2 | S14: 2 | T14: 0 | U14: 4 | V14: Горизонтальный 4*3 | W14: Digital (без звука) | X14: видеоролик | Y14: 10 | Z14: 150 | AA14: 576 | AB14: 31 | AC14: =Q14*AA14*AB14 -> 35712 | AD14: =AE14/P14 -> 8.06 | AE14: =((P14*2.6*R14/S14/2)*30/Z14+(P14*2.6*T14/U14)*N14*2/Z14)*AB14 -> 3407.768 | AF14: =AL14/AE14*1000 -> 2347.5777 | AG14: 1 | AI14: =AJ14/1.22 -> 3278.6885 | AJ14: 4000 | AK14: =AI14*Q14 -> 6557.377 | AL14: =AK14*1.22 -> 8000
A15: U5 | B15: Республика Башкортостан | C15: Уфа | D15: Ленинский | E15: Центр | F15: Б | G15: 45961 | H15: Бизнес | I15: ЖК Старый центр | J15: улица Чернышевского, 28 | K15: 54.731326 | L15: 55.929774 | M15: 2012 | N15: 18 | O15: 111 | P15: =O15*2.8 -> 310.8 | Q15: 1 | R15: 1 | S15: 1 | T15: 0 | U15: 2 | V15: Горизонтальный 4*3 | W15: Digital (без звука) | X15: видеоролик | Y15: 10 | Z15: 150 | AA15: 576 | AB15: 31 | AC15: =Q15*AA15*AB15 -> 17856 | AD15: =AE15/P15 -> 8.06 | AE15: =((P15*2.6*R15/S15/2)*30/Z15+(P15*2.6*T15/U15)*N15*2/Z15)*AB15 -> 2505.048 | AF15: =AL15/AE15*1000 -> 1596.7758 | AG15: 1 | AI15: =AJ15/1.22 -> 3278.6885 | AJ15: 4000 | AK15: =AI15*Q15 -> 3278.6885 | AL15: =AK15*1.22 -> 4000
A16: U5 | B16: Республика Башкортостан | C16: Уфа | D16: Ленинский | E16: Центр | F16: Б | G16: 45961 | H16: Бизнес | I16: ЖК Старый центр | J16: улица Коммунистическая, 11/1 | K16: 54.730157 | L16: 55.927978 | M16: 2018 | N16: 27 | O16: 271 | P16: =O16*2.8 -> 758.8 | Q16: 1 | R16: 1 | S16: 1 | T16: 0 | U16: 3 | V16: Горизонтальный 4*3 | W16: Digital (без звука) | X16: видеоролик | Y16: 10 | Z16: 150 | AA16: 576 | AB16: 31 | AC16: =Q16*AA16*AB16 -> 17856 | AD16: =AE16/P16 -> 8.06 | AE16: =((P16*2.6*R16/S16/2)*30/Z16+(P16*2.6*T16/U16)*N16*2/Z16)*AB16 -> 6115.928 | AF16: =AL16/AE16*1000 -> 654.02994 | AG16: 1 | AI16: =AJ16/1.22 -> 3278.6885 | AJ16: 4000 | AK16: =AI16*Q16 -> 3278.6885 | AL16: =AK16*1.22 -> 4000
... A131: U79 | B131: Республика Башкортостан | C131: Уфа | D131: Кировский | E131: Зеленая Роща 2 | F131: А | G131: 46171 | H131: Комфорт | I131: квартал Кузнецовский затон | J131: улица Просвещения, 11/1 | K131: 54.689997 | L131: 55.972204 | M131: 2019 | N131: 11 | O131: 70 | P131: =O131*2.8 -> 196 | Q131: 1 | R131: 0 | S131: 1 | T131: 1 | U131: 1 | V131: Вертикальный 4*3 | W131: Digital (без звука) | X131: видеоролик | Y131: 10 | Z131: 150 | AA131: 576 | AB131: 31 | AC131: =Q131*AA131*AB131 -> 17856 | AD131: =AE131/P131 -> 11.821333 | AE131: =((P131*2.6*R131/S131/2)*30/Z131+(P131*2.6*T131/U131)*N131*2/Z131)*AB131 -> 2316.9813 | AF131: =AL131/AE131*1000 -> 1726.3842 | AG131: 1 | AI131: =AJ131/1.22 -> 3278.6885 | AJ131: 4000 | AK131: =AI131*Q131 -> 3278.6885 | AL131: =AK131*1.22 -> 4000
A132: U79 | B132: Республика Башкортостан | C132: Уфа | D132: Кировский | E132: Зеленая Роща 2 | F132: А | G132: 46244 | H132: Комфорт | I132: квартал Кузнецовский затон | J132: улица Бородинская, 20/1 | K132: 54.686208, 55.984572 | M132: 2023 | N132: 12 | O132: 158 | P132: =O132*2.8 -> 442.4 | Q132: 2 | R132: 0 | S132: 1 | T132: 2 | U132: 2 | V132: Вертикальный 4*3 | W132: Digital (без звука) | X132: видеоролик | Y132: 10 | Z132: 150 | AA132: 576 | AB132: 31 | AC132: =Q132*AA132*AB132 -> 35712 | AD132: =AE132/P132 -> 12.896 | AE132: =((P132*2.6*R132/S132/2)*30/Z132+(P132*2.6*T132/U132)*N132*2/Z132)*AB132 -> 5705.1904 | AF132: =AL132/AE132*1000 -> 1402.2319 | AG132: 1 | AI132: =AJ132/1.22 -> 3278.6885 | AJ132: 4000 | AK132: =AI132*Q132 -> 6557.377 | AL132: =AK132*1.22 -> 8000
A133: U80 | B133: Республика Башкортостан | C133: Уфа | D133: Ленинский | E133: Ленинский 1 Затон_мкрн. 8 Марта | F133: А | G133: 46183 | H133: Стандарт | I133: Квартал Летчиков | J133: улица Летчиков, 16/1 | K133: 54.795296 | L133: 55.867126 | M133: 2014 | N133: 18 | O133: 90 | P133: =O133*2.8 -> 252 | Q133: 2 | R133: 0 | S133: 1 | T133: 2 | U133: 2 | V133: Вертикальный 4*3 | W133: Digital (без звука) | X133: видеоролик | Y133: 10 | Z133: 150 | AA133: 576 | AB133: 31 | AC133: =Q133*AA133*AB133 -> 35712 | AD133: =AE133/P133 -> 19.344 | AE133: =((P133*2.6*R133/S133/2)*30/Z133+(P133*2.6*T133/U133)*N133*2/Z133)*AB133 -> 4874.688 | AF133: =AL133/AE133*1000 -> 1641.1307 | AG133: 1 | AI133: =AJ133/1.22 -> 3278.6885 | AJ133: 4000 | AK133: =AI133*Q133 -> 6557.377 | AL133: =AK133*1.22 -> 8000
A134: U80 | B134: Республика Башкортостан | C134: Уфа | D134: Ленинский | E134: Ленинский 1 Затон_мкрн. 8 Марта | F134: А | G134: 46183 | H134: Стандарт | I134: Квартал Летчиков | J134: улица Летчиков, 18 | K134: 54.79523 | L134: 55.868527 | M134: 2013 | N134: 14 | O134: 154 | P134: =O134*2.8 -> 431.2 | Q134: 3 | R134: 0 | S134: 3 | T134: 3 | U134: 6 | V134: Вертикальный 4*3 | W134: Digital (без звука) | X134: видеоролик | Y134: 10 | Z134: 150 | AA134: 576 | AB134: 31 | AC134: =Q134*AA134*AB134 -> 53568 | AD134: =AE134/P134 -> 7.5226667 | AE134: =((P134*2.6*R134/S134/2)*30/Z134+(P134*2.6*T134/U134)*N134*2/Z134)*AB134 -> 3243.7739 | AF134: =AL134/AE134*1000 -> 3699.3947 | AG134: 1 | AI134: =AJ134/1.22 -> 3278.6885 | AJ134: 4000 | AK134: =AI134*Q134 -> 9836.0656 | AL134: =AK134*1.22 -> 12000
A135: U81 | B135: Республика Башкортостан | C135: Уфа | D135: Октябрьский | E135: Инорс_Сипайлово | F135: А | G135: 46168 | H135: Комфорт | I135: Квартал Олимп | J135: улица Маршала Жукова, 4/4 | K135: 54.765952 | L135: 56.051225 | M135: 2002 | N135: 10 | O135: 150 | P135: =O135*2.8 -> 420 | Q135: 3 | R135: 0 | S135: 3 | T135: 3 | U135: 3 | V135: Вертикальный 4*3 | W135: Digital (без звука) | X135: видеоролик | Y135: 10 | Z135: 150 | AA135: 576 | AB135: 31 | AC135: =Q135*AA135*AB135 -> 53568 | AD135: =AE135/P135 -> 10.746667 | AE135: =((P135*2.6*R135/S135/2)*30/Z135+(P135*2.6*T135/U135)*N135*2/Z135)*AB135 -> 4513.6 | AF135: =AL135/AE135*1000 -> 2658.6317 | AG135: 1 | AI135: =AJ135/1.22 -> 3278.6885 | AJ135: 4000 | AK135: =AI135*Q135 -> 9836.0656 | AL135: =AK135*1.22 -> 12000
A136: U82 | B136: Республика Башкортостан | C136: Уфа | D136: Октябрьский | E136: Инорс_Сипайлово | F136: А | G136: 46196 | H136: Комфорт | I136: Квартал Олимп 2 | J136: улица Маршала Жукова, 4/1 | K136: 54.767256 | L136: 56.053738 | M136: 1995 | N136: 10 | O136: 290 | P136: =O136*2.8 -> 812 | Q136: 8 | R136: 0 | S136: 8 | T136: 8 | U136: 8 | V136: Вертикальный 4*3 | W136: Digital (без звука) | X136: видеоролик | Y136: 10 | Z136: 150 | AA136: 576 | AB136: 31 | AC136: =Q136*AA136*AB136 -> 142848 | AD136: =AE136/P136 -> 10.746667 | AE136: =((P136*2.6*R136/S136/2)*30/Z136+(P136*2.6*T136/U136)*N136*2/Z136)*AB136 -> 8726.2933 | AF136: =AL136/AE136*1000 -> 3667.0782 | AG136: 1 | AI136: =AJ136/1.22 -> 3278.6885 | AJ136: 4000 | AK136: =AI136*Q136 -> 26229.508 | AL136: =AK136*1.22 -> 32000
A137: U83 | B137: Республика Башкортостан | C137: Уфа | D137: Октябрьский | E137: Инорс_Сипайлово | F137: А | G137: 46186 | H137: Комфорт | I137: Квартал Олимп 3 | J137: улица Юрия Гагарина, 10/2 | K137: 54.763763 | L137: 56.050715 | M137: 2001 | N137: 9 | O137: 207 | P137: =O137*2.8 -> 579.6 | Q137: 7 | R137: 0 | S137: 7 | T137: 7 | U137: 7 | V137: Вертикальный 4*3 | W137: Digital (без звука) | X137: видеоролик | Y137: 10 | Z137: 150 | AA137: 576 | AB137: 31 | AC137: =Q137*AA137*AB137 -> 124992 | AD137: =AE137/P137 -> 9.672 | AE137: =((P137*2.6*R137/S137/2)*30/Z137+(P137*2.6*T137/U137)*N137*2/Z137)*AB137 -> 5605.8912 | AF137: =AL137/AE137*1000 -> 4994.7455 | AG137: 1 | AI137: =AJ137/1.22 -> 3278.6885 | AJ137: 4000 | AK137: =AI137*Q137 -> 22950.82 | AL137: =AK137*1.22 -> 28000
A138: U84 | B138: Республика Башкортостан | C138: Уфа | D138: Октябрьский | E138: Инорс_Сипайлово | F138: Б | G138: 46188 | H138: Комфорт | I138: Квартал Маяк | J138: улица Маршала Жукова, 3/2 | K138: 54.766198 | L138: 56.047695 | M138: 2007 | N138: 18 | O138: 80 | P138: =O138*2.8 -> 224 | Q138: 2 | R138: 0 | S138: 1 | T138: 2 | U138: 2 | V138: Вертикальный 4*3 | W138: Digital (без звука) | X138: видеоролик | Y138: 10 | Z138: 150 | AA138: 576 | AB138: 31 | AC138: =Q138*AA138*AB138 -> 35712 | AD138: =AE138/P138 -> 19.344 | AE138: =((P138*2.6*R138/S138/2)*30/Z138+(P138*2.6*T138/U138)*N138*2/Z138)*AB138 -> 4333.056 | AF138: =AL138/AE138*1000 -> 1846.272 | AG138: 1 | AI138: =AJ138/1.22 -> 3278.6885 | AJ138: 4000 | AK138: =AI138*Q138 -> 6557.377 | AL138: =AK138*1.22 -> 8000
A139: U85 | B139: Республика Башкортостан | C139: Уфа | D139: Кировский | E139: Зеленая Роща 2 | F139: Б | G139: 46191 | H139: Комфорт | I139: ЖК Южный 2 | J139: улица Загира Исмагилова, 16/1 | K139: 54.698573 | L139: 55.982071 | M139: 2009 | N139: 9 | O139: 71 | P139: =O139*2.8 -> 198.8 | Q139: 2 | R139: 0 | S139: 2 | T139: 2 | U139: 2 | V139: Вертикальный 4*3 | W139: Digital (без звука) | X139: видеоролик | Y139: 10 | Z139: 150 | AA139: 576 | AB139: 31 | AC139: =Q139*AA139*AB139 -> 35712 | AD139: =AE139/P139 -> 9.672 | AE139: =((P139*2.6*R139/S139/2)*30/Z139+(P139*2.6*T139/U139)*N139*2/Z139)*AB139 -> 1922.7936 | AF139: =AL139/AE139*1000 -> 4160.613 | AG139: 1 | AI139: =AJ139/1.22 -> 3278.6885 | AJ139: 4000 | AK139: =AI139*Q139 -> 6557.377 | AL139: =AK139*1.22 -> 8000
A140: U85 | B140: Республика Башкортостан | C140: Уфа | D140: Кировский | E140: Зеленая Роща 2 | F140: Б | G140: 46191 | H140: Комфорт | I140: ЖК Южный 2 | J140: улица Загира Исмагилова, д. 18 | K140: 54.698718 | L140: 55.980256 | M140: 2012 | N140: 13 | O140: 148 | P140: =O140*2.8 -> 414.4 | Q140: 2 | R140: 0 | S140: 2 | T140: 2 | U140: 4 | V140: Вертикальный 4*3 | W140: Digital (без звука) | X140: видеоролик | Y140: 10 | Z140: 150 | AA140: 576 | AB140: 31 | AC140: =Q140*AA140*AB140 -> 35712 | AD140: =AE140/P140 -> 6.9853333 | AE140: =((P140*2.6*R140/S140/2)*30/Z140+(P140*2.6*T140/U140)*N140*2/Z140)*AB140 -> 2894.7221 | AF140: =AL140/AE140*1000 -> 2763.6504 | AG140: 1 | AI140: =AJ140/1.22 -> 3278.6885 | AJ140: 4000 | AK140: =AI140*Q140 -> 6557.377 | AL140: =AK140*1.22 -> 8000
A141: U86 | B141: Республика Башкортостан | C141: Уфа | D141: Дёмский | E141: Дёмский_мкрн. Цветы Башкирии | F141: А | G141: 46191 | H141: Комфорт | I141: ЖК Яркий Квартал Париж 1 | J141: Яркий бульвар, 10 | K141: 54.695817 | L141: 55.859804 | M141: 2022 | N141: 19 | O141: 204 | P141: =O141*2.8 -> 571.2 | Q141: 3 | R141: 0 | S141: 1 | T141: 3 | U141: 3 | V141: Вертикальный 4*3 | W141: Digital (без звука) | X141: видеоролик | Y141: 10 | Z141: 150 | AA141: 576 | AB141: 31 | AC141: =Q141*AA141*AB141 -> 53568 | AD141: =AE141/P141 -> 20.418667 | AE141: =((P141*2.6*R141/S141/2)*30/Z141+(P141*2.6*T141/U141)*N141*2/Z141)*AB141 -> 11663.142 | AF141: =AL141/AE141*1000 -> 1028.8822 | AG141: 1 | AI141: =AJ141/1.22 -> 3278.6885 | AJ141: 4000 | AK141: =AI141*Q141 -> 9836.0656 | AL141: =AK141*1.22 -> 12000
A142: U87 | B142: Республика Башкортостан | C142: Уфа | D142: Дёмский | E142: Дёмский_мкрн. Цветы Башкирии | F142: А | G142: 46217 | H142: Комфорт | I142: ЖК Яркий Квартал Париж 2 | J142: улица Евгения Столярова, 13 | K142: 54.695185 | L142: 55.857586 | M142: 2025 | N142: 26 | O142: 288 | P142: =O142*2.8 -> 806.4 | Q142: 3 | R142: 0 | S142: 1 | T142: 3 | U142: 4 | V142: Вертикальный 4*3 | W142: Digital (без звука) | X142: видеоролик | Y142: 10 | Z142: 150 | AA142: 576 | AB142: 31 | AC142: =Q142*AA142*AB142 -> 53568 | AD142: =AE142/P142 -> 20.956 | AE142: =((P142*2.6*R142/S142/2)*30/Z142+(P142*2.6*T142/U142)*N142*2/Z142)*AB142 -> 16898.918 | AF142: =AL142/AE142*1000 -> 710.10462 | AG142: 1 | AI142: =AJ142/1.22 -> 3278.6885 | AJ142: 4000 | AK142: =AI142*Q142 -> 9836.0656 | AL142: =AK142*1.22 -> 12000
A143: U88 | B143: Республика Башкортостан | C143: Уфа | D143: Дёмский | E143: Дёмский_мкрн. Цветы Башкирии | F143: А | G143: 46217 | H143: Комфорт | I143: ЖК Яркий Квартал Париж 3 | J143: улица Архитектора Калимуллина, 12 | K143: 54.694867 | L143: 55.859257 | M143: 2025 | N143: 26 | O143: 288 | P143: =O143*2.8 -> 806.4 | Q143: 3 | R143: 0 | S143: 1 | T143: 3 | U143: 4 | V143: Вертикальный 4*3 | W143: Digital (без звука) | X143: видеоролик | Y143: 10 | Z143: 150 | AA143: 576 | AB143: 31 | AC143: =Q143*AA143*AB143 -> 53568 | AD143: =AE143/P143 -> 20.956 | AE143: =((P143*2.6*R143/S143/2)*30/Z143+(P143*2.6*T143/U143)*N143*2/Z143)*AB143 -> 16898.918 | AF143: =AL143/AE143*1000 -> 710.10462 | AG143: 1 | AI143: =AJ143/1.22 -> 3278.6885 | AJ143: 4000 | AK143: =AI143*Q143 -> 9836.0656 | AL143: =AK143*1.22 -> 12000
A144: U89 | B144: Республика Башкортостан | C144: Уфа | D144: Дёмский | E144: Дёмский_мкрн. Цветы Башкирии | F144: А | G144: 46202 | H144: Стандарт | I144: ЖК Новая Дёма | J144: улица Генерала Кусимова, 20 | K144: 54.717392 | L144: 55.842467 | M144: 2025 | N144: 19 | O144: 808 | P144: =O144*2.8 -> 2262.4 | Q144: 8 | R144: 0 | S144: 8 | T144: 8 | U144: 16 | V144: Вертикальный 4*3 | W144: Digital (без звука) | X144: видеоролик | Y144: 10 | Z144: 150 | AA144: 576 | AB144: 31 | AC144: =Q144*AA144*AB144 -> 142848 | AD144: =AE144/P144 -> 10.209333 | AE144: =((P144*2.6*R144/S144/2)*30/Z144+(P144*2.6*T144/U144)*N144*2/Z144)*AB144 -> 23097.596 | AF144: =AL144/AE144*1000 -> 1385.4256 | AG144: 1 | AI144: =AJ144/1.22 -> 3278.6885 | AJ144: 4000 | AK144: =AI144*Q144 -> 26229.508 | AL144: =AK144*1.22 -> 32000
... A181: U120 | B181: Республика Башкортостан | C181: Уфа | D181: Кировский | E181: Зеленая Роща 2 | F181: Б | G181: 46248 | H181: Комфорт | I181: ЖК на Перовской 54 | J181: улица Софьи Перовской, 54 | K181: 54.697172 | L181: 55.992477 | M181: 2010 | N181: 18 | O181: 321 | P181: =O181*2.8 -> 898.8 | Q181: 5 | R181: 0 | S181: 5 | T181: 5 | U181: 10 | V181: Вертикальный 4*3 | W181: Digital (без звука) | X181: видеоролик | Y181: 10 | Z181: 150 | AA181: 576 | AB181: 31 | AC181: =Q181*AA181*AB181 -> 89280 | AD181: =AE181/P181 -> 9.672 | AE181: =((P181*2.6*R181/S181/2)*30/Z181+(P181*2.6*T181/U181)*N181*2/Z181)*AB181 -> 8693.1936 | AF181: =AL181/AE181*1000 -> 2300.6505 | AG181: 1 | AI181: =AJ181/1.22 -> 3278.6885 | AJ181: 4000 | AK181: =AI181*Q181 -> 16393.443 | AL181: =AK181*1.22 -> 20000
A182: U121 | B182: Республика Башкортостан | C182: Уфа | D182: Октябрьский | F182: Б | G182: 46254 | H182: Комфорт | I182: ЖК на Набережной реки Уфы 3/5 | J182: улица Набережная реки Уфы, 3/5 | K182: 54.761940 | L182: 56.052637 | M182: 2000 | N182: 10 | O182: 86 | P182: =O182*2.8 -> 240.8 | Q182: 2 | R182: 0 | S182: 2 | T182: 2 | U182: 2 | V182: Вертикальный 4*3 | W182: Digital (без звука) | X182: видеоролик | Y182: 10 | Z182: 150 | AA182: 576 | AB182: 31 | AC182: =Q182*AA182*AB182 -> 35712 | AD182: =AE182/P182 -> 10.746667 | AE182: =((P182*2.6*R182/S182/2)*30/Z182+(P182*2.6*T182/U182)*N182*2/Z182)*AB182 -> 2587.7973 | AF182: =AL182/AE182*1000 -> 3091.4322 | AG182: 1 | AI182: =AJ182/1.22 -> 3278.6885 | AJ182: 4000 | AK182: =AI182*Q182 -> 6557.377 | AL182: =AK182*1.22 -> 8000
A183: U122 | B183: Республика Башкортостан | C183: Уфа | D183: Первомайский | F183: Б | G183: 46254 | H183: Стандарт | I183: ЖК Мечтателей | J183: улица Рашита Нигмати, 12 | K183: 54.710131 | L183: 55.842665 | M183: 2025 | N183: 12 | O183: 289 | P183: =O183*2.8 -> 809.2 | Q183: 5 | R183: 0 | S183: 5 | T183: 5 | U183: 4 | V183: Вертикальный 4*3 | W183: Digital (без звука) | X183: видеоролик | Y183: 10 | Z183: 150 | AA183: 576 | AB183: 31 | AC183: =Q183*AA183*AB183 -> 89280 | AD183: =AE183/P183 -> 16.12 | AE183: =((P183*2.6*R183/S183/2)*30/Z183+(P183*2.6*T183/U183)*N183*2/Z183)*AB183 -> 13044.304 | AF183: =AL183/AE183*1000 -> 1533.2363 | AG183: 1 | AI183: =AJ183/1.22 -> 3278.6885 | AJ183: 4000 | AK183: =AI183*Q183 -> 16393.443 | AL183: =AK183*1.22 -> 20000
A184: STR1 | B184: Республика Башкортостан | C184: Стерлитамак | D184: ​Западный | E184: продажа городом | F184: А | G184: 45972 | H184: Комфорт | I184: ЖК Браво | J184: улица Интернациональная, 61 | K184: 54.811887 | L184: 56.077233 | M184: 2024 | N184: 10 | O184: 519 | P184: =O184*2.8 -> 1453.2 | Q184: 10 | R184: 5 | S184: 1 | T184: 5 | U184: 7 | V184: Горизонтальный 4*3 | W184: Digital (без звука) | X184: видеоролик | Y184: 10 | Z184: 150 | AA184: 576 | AB184: 31 | AC184: =Q184*AA184*AB184 -> 178560 | AD184: =AE184/P184 -> 47.97619 | AE184: =((P184*2.6*R184/S184/2)*30/Z184+(P184*2.6*T184/U184)*N184*2/Z184)*AB184 -> 69719 | AF184: =AL184/AE184*1000 -> 573.73169 | AG184: 1 | AI184: =AJ184/1.22 -> 3278.6885 | AJ184: 4000 | AK184: =AI184*Q184 -> 32786.885 | AL184: =AK184*1.22 -> 40000
A185: STR2 | B185: Республика Башкортостан | C185: Стерлитамак | D185: ​Западный | E185: продажа городом | F185: А | G185: 46219 | H185: Комфорт | I185: ЖК Браво 2 | J185: улица Интернациональная, 63 | K185: 54.811726 | L185: 56.077790 | M185: 2025 | N185: 17 | O185: 363 | P185: =363*2.8 -> 1016.4 | Q185: 10 | R185: 5 | S185: 5 | T185: 5 | U185: 10 | V185: Горизонтальный 4*3 | W185: Digital (без звука) | X185: видеоролик | Y185: 10 | Z185: 150 | AA185: 576 | AB185: 31 | AC185: =Q185*AA185*AB185 -> 178560 | AD185: =AE185/P185 -> 17.194667 | AE185: =((P185*2.6*R185/S185/2)*30/Z185+(P185*2.6*T185/U185)*N185*2/Z185)*AB185 -> 17476.659 | AF185: =AL185/AE185*1000 -> 2288.767 | AG185: 1 | AI185: =AJ185/1.22 -> 3278.6885 | AJ185: 4000 | AK185: =AI185*Q185 -> 32786.885 | AL185: =AK185*1.22 -> 40000
A186: STR3 | B186: Республика Башкортостан | C186: Стерлитамак | D186: Западный | E186: продажа городом | F186: А | G186: 45951 | H186: Комфорт | I186: ЖК Шиханы | J186: проспект Октября, 99 | K186: 53.629169 | L186: 55.883017 | M186: 2023 | N186: 20 | O186: 439 | P186: =O186*2.8 -> 1229.2 | Q186: 6 | R186: 3 | S186: 1 | T186: 3 | U186: 6 | V186: Горизонтальный 4*3 | W186: Digital (без звука) | X186: видеоролик | Y186: 10 | Z186: 150 | AA186: 576 | AB186: 31 | AC186: =Q186*AA186*AB186 -> 107136 | AD186: =AE186/P186 -> 34.926667 | AE186: =((P186*2.6*R186/S186/2)*30/Z186+(P186*2.6*T186/U186)*N186*2/Z186)*AB186 -> 42931.859 | AF186: =AL186/AE186*1000 -> 559.02541 | AG186: 1 | AI186: =AJ186/1.22 -> 3278.6885 | AJ186: 4000 | AK186: =AI186*Q186 -> 19672.131 | AL186: =AK186*1.22 -> 24000
A187: STR4 | B187: Республика Башкортостан | C187: Стерлитамак | D187: Западный | E187: продажа городом | F187: А | G187: 46122 | H187: Комфорт | I187: ЖК Шиханы 2 | J187: улица Раиса Багаутдинова, 2 | K187: 53.627989 | L187: 55.883080 | M187: 2024 | N187: 11 | O187: 124 | P187: =O187*2.8 -> 347.2 | Q187: 4 | R187: 2 | S187: 1 | T187: 2 | U187: 3 | V187: Горизонтальный 4*3 | W187: Digital (без звука) | X187: видеоролик | Y187: 10 | Z187: 150 | AA187: 576 | AB187: 31 | AC187: =Q187*AA187*AB187 -> 71424 | AD187: =AE187/P187 -> 24.000889 | AE187: =((P187*2.6*R187/S187/2)*30/Z187+(P187*2.6*T187/U187)*N187*2/Z187)*AB187 -> 8333.1086 | AF187: =AL187/AE187*1000 -> 1920.0518 | AG187: 1 | AI187: =AJ187/1.22 -> 3278.6885 | AJ187: 4000 | AK187: =AI187*Q187 -> 13114.754 | AL187: =AK187*1.22 -> 16000
A188: STR5 | B188: Республика Башкортостан | C188: Стерлитамак | D188: ​Западный | E188: продажа городом | F188: А | G188: 46010 | H188: Комфорт | I188: ЖК на Проспекте Октября 85 | J188: проспект Октября, 85 | K188: 53.628993 | L188: 55.899941 | M188: 2019 | N188: 18 | O188: 230 | P188: =O188*2.8 -> 644 | Q188: 4 | R188: 2 | S188: 2 | T188: 2 | U188: 4 | V188: Горизонтальный 4*3 | W188: Digital (без звука) | X188: видеоролик | Y188: 10 | Z188: 150 | AA188: 576 | AB188: 31 | AC188: =Q188*AA188*AB188 -> 71424 | AD188: =AE188/P188 -> 17.732 | AE188: =((P188*2.6*R188/S188/2)*30/Z188+(P188*2.6*T188/U188)*N188*2/Z188)*AB188 -> 11419.408 | AF188: =AL188/AE188*1000 -> 1401.1234 | AG188: 1 | AI188: =AJ188/1.22 -> 3278.6885 | AJ188: 4000 | AK188: =AI188*Q188 -> 13114.754 | AL188: =AK188*1.22 -> 16000
A189: NFT1 | B189: Республика Башкортостан | C189: Нефтекамск | D189: ​13-й м-н | E189: продажа городом | F189: Б | G189: 46230 | H189: Комфорт | I189: ЖК Лайф | J189: улица Ленина, 84Б | K189: 56.108256 | L189: 54.235974 | M189: 2024 | N189: 16 | O189: 283 | P189: =O189*2.8 -> 792.4 | Q189: 4 | R189: 0 | S189: 2 | T189: 4 | U189: 4 | V189: Вертикальный 4*3 | W189: Digital (без звука) | X189: видеоролик | Y189: 10 | Z189: 150 | AA189: 576 | AB189: 31 | AC189: =Q189*AA189*AB189 -> 71424 | AD189: =AE189/P189 -> 17.194667 | AE189: =((P189*2.6*R189/S189/2)*30/Z189+(P189*2.6*T189/U189)*N189*2/Z189)*AB189 -> 13625.054 | AF189: =AL189/AE189*1000 -> 1174.3073 | AG189: 1 | AI189: =AJ189/1.22 -> 3278.6885 | AJ189: 4000 | AK189: =AI189*Q189 -> 13114.754 | AL189: =AK189*1.22 -> 16000
A190: NFT2 | B190: Республика Башкортостан | C190: Нефтекамск | D190: 24-й м-н | E190: продажа городом | F190: Б | G190: 46237 | H190: Комфорт | I190: ЖК Городской | J190: улица Городская, 12 | K190: 56.071248 | L190: 54.225940 | M190: 2025 | N190: 10 | O190: 210 | P190: =O190*2.8 -> 588 | Q190: 2 | R190: 0 | S190: 2 | T190: 2 | U190: 2 | V190: Вертикальный 4*3 | W190: Digital (без звука) | X190: видеоролик | Y190: 10 | Z190: 150 | AA190: 576 | AB190: 31 | AC190: =Q190*AA190*AB190 -> 35712 | AD190: =AE190/P190 -> 10.746667 | AE190: =((P190*2.6*R190/S190/2)*30/Z190+(P190*2.6*T190/U190)*N190*2/Z190)*AB190 -> 6319.04 | AF190: =AL190/AE190*1000 -> 1266.0151 | AG190: 1 | AI190: =AJ190/1.22 -> 3278.6885 | AJ190: 4000 | AK190: =AI190*Q190 -> 6557.377 | AL190: =AK190*1.22 -> 8000
A191: NFT2 | B191: Республика Башкортостан | C191: Нефтекамск | D191: 24-й м-н | E191: продажа городом | F191: Б | G191: 46237 | H191: Комфорт | I191: ЖК Городской | J191: улица Городская, 14 | K191: 56.071007 | L191: 54.226856 | M191: 2025 | N191: 10 | O191: 210 | P191: =O191*2.8 -> 588 | Q191: 4 | R191: 0 | S191: 4 | T191: 4 | U191: 4 | V191: Вертикальный 4*3 | W191: Digital (без звука) | X191: видеоролик | Y191: 10 | Z191: 150 | AA191: 576 | AB191: 31 | AC191: =Q191*AA191*AB191 -> 71424 | AD191: =AE191/P191 -> 10.746667 | AE191: =((P191*2.6*R191/S191/2)*30/Z191+(P191*2.6*T191/U191)*N191*2/Z191)*AB191 -> 6319.04 | AF191: =AL191/AE191*1000 -> 2532.0302 | AG191: 1 | AI191: =AJ191/1.22 -> 3278.6885 | AJ191: 4000 | AK191: =AI191*Q191 -> 13114.754 | AL191: =AK191*1.22 -> 16000
A192: OKT1 | B192: Республика Башкортостан | C192: Октябрьский | D192: Центральный | E192: продажа городом | F192: Б | G192: 46247 | H192: Комфорт | I192: ЖК Парковая | J192: улица Парковая, 5 | K192: 54.471085 | L192: 53.518337 | M192: 2024 | N192: 10 | O192: 235 | P192: =O192*2.8 -> 658 | Q192: 5 | R192: 5 | S192: 5 | T192: 0 | U192: 5 | V192: Вертикальный 4*3 | W192: Digital (без звука) | X192: видеоролик | Y192: 10 | Z192: 150 | AA192: 576 | AB192: 31 | AC192: =Q192*AA192*AB192 -> 89280 | AD192: =AE192/P192 -> 8.06 | AE192: =((P192*2.6*R192/S192/2)*30/Z192+(P192*2.6*T192/U192)*N192*2/Z192)*AB192 -> 5303.48 | AF192: =AL192/AE192*1000 -> 3771.1088 | AG192: 1 | AI192: =AJ192/1.22 -> 3278.6885 | AJ192: 4000 | AK192: =AI192*Q192 -> 16393.443 | AL192: =AK192*1.22 -> 20000
A193: OREN1 | B193: Оренбургская область | C193: Оренбург | D193: Дзержинский | E193: мкрн. 13_15_16 | F193: А | G193: 45952 | H193: Комфорт | I193: ЖК 15Б Микрорайон | J193: улица Автомобилистов, 13 | K193: 51.830568 | L193: 55.168964 | M193: 2023 | N193: 19 | O193: 762 | P193: =O193*2.8 -> 2133.6 | Q193: 5 | R193: 5 | S193: 6 | T193: 0 | U193: 12 | V193: Горизонтальный 4*3 | W193: Digital (без звука) | X193: видеоролик | Y193: 10 | Z193: 150 | AA193: 576 | AB193: 31 | AC193: =Q193*AA193*AB193 -> 89280 | AD193: =AE193/P193 -> 6.7166667 | AE193: =((P193*2.6*R193/S193/2)*30/Z193+(P193*2.6*T193/U193)*N193*2/Z193)*AB193 -> 14330.68 | AF193: =AL193/AE193*1000 -> 1395.6072 | AG193: 1 | AI193: =AJ193/1.22 -> 3278.6885 | AJ193: 4000 | AK193: =AI193*Q193 -> 16393.443 | AL193: =AK193*1.22 -> 20000
A194: OREN1 | B194: Оренбургская область | C194: Оренбург | D194: Дзержинский | E194: мкрн. 13_15_16 | F194: А | G194: 45952 | H194: Комфорт | I194: ЖК 15Б Микрорайон | J194: улица Автомобилистов, 13 | K194: 51.830568 | L194: 55.168964 | M194: 2023 | N194: 19 | O194: 762 | P194: =O194*2.8 -> 2133.6 | Q194: 5 | R194: 0 | S194: 6 | T194: 5 | U194: 12 | V194: Венртикальный 4*3 | W194: Digital (без звука) | X194: видеоролик | Y194: 10 | Z194: 150 | AA194: 576 | AB194: 31 | AC194: =Q194*AA194*AB194 -> 89280 | AD194: =AE194/P194 -> 8.5077778 | AE194: =((P194*2.6*R194/S194/2)*30/Z194+(P194*2.6*T194/U194)*N194*2/Z194)*AB194 -> 18152.195 | AF194: =AL194/AE194*1000 -> 1101.7951 | AG194: 1 | AI194: =AJ194/1.22 -> 3278.6885 | AJ194: 4000 | AK194: =AI194*Q194 -> 16393.443 | AL194: =AK194*1.22 -> 20000
A195: OREN1 | B195: Оренбургская область | C195: Оренбург | D195: Дзержинский | E195: мкрн. 13_15_16 | F195: А | G195: 45952 | H195: Комфорт | I195: ЖК 15Б Микрорайон | J195: улица Северный, 23 | K195: 51.828932 | L195: 55.173573 | M195: 2024 | N195: 17 | O195: 162 | P195: =O195*2.8 -> 453.6 | Q195: 6 | R195: 3 | S195: 3 | T195: 3 | U195: 4 | V195: Горизонтальный 4*3 | W195: Digital (без звука) | X195: видеоролик | Y195: 10 | Z195: 150 | AA195: 576 | AB195: 31 | AC195: =Q195*AA195*AB195 -> 107136 | AD195: =AE195/P195 -> 21.762 | AE195: =((P195*2.6*R195/S195/2)*30/Z195+(P195*2.6*T195/U195)*N195*2/Z195)*AB195 -> 9871.2432 | AF195: =AL195/AE195*1000 -> 2431.3047 | AG195: 1 | AI195: =AJ195/1.22 -> 3278.6885 | AJ195: 4000 | AK195: =AI195*Q195 -> 19672.131 | AL195: =AK195*1.22 -> 24000
A196: OREN2 | B196: Оренбургская область | C196: Оренбург | D196: Ленинский | E196: мкрн. 18_19_20 | F196: А | G196: 45952 | H196: Комфорт | I196: ЖК 17 Микрорайон | J196: улица Салмышская, 43/1 | K196: 51.823309 | L196: 55.167186 | M196: 2012 | N196: 14 | O196: 201 | P196: =O196*2.8 -> 562.8 | Q196: 4 | R196: 4 | S196: 4 | T196: 0 | U196: 8 | V196: Горизонтальный 4*3 | W196: Digital (без звука) | X196: видеоролик | Y196: 10 | Z196: 150 | AA196: 576 | AB196: 31 | AC196: =Q196*AA196*AB196 -> 71424 | AD196: =AE196/P196 -> #REF! | AE196: =((P196*2.6*S196/#REF!/2)*30/Z196+(P196*2.6*T196/U196)*N196*2/Z196)*AB196 -> #REF! | AF196: =AL196/AE196*1000 -> #REF! | AG196: 1 | AI196: =AJ196/1.22 -> 3278.6885 | AJ196: 4000 | AK196: =AI196*Q196 -> 13114.754 | AL196: =AK196*1.22 -> 16000
A197: OREN2 | B197: Оренбургская область | C197: Оренбург | D197: Ленинский | E197: мкрн. 18_19_20 | F197: А | G197: 45952 | H197: Комфорт | I197: ЖК 17 Микрорайон | J197: улица Салмышская, 43/5 | K197: 51.822089 | L197: 55.16836 | M197: 2017 | N197: 20 | O197: 568 | P197: =O197*2.8 -> 1590.4 | Q197: 4 | R197: 4 | S197: 4 | T197: 0 | U197: 8 | V197: Горизонтальный 4*3 | W197: Digital (без звука) | X197: видеоролик | Y197: 10 | Z197: 150 | AA197: 576 | AB197: 31 | AC197: =Q197*AA197*AB197 -> 71424 | AD197: =AE197/P197 -> 8.06 | AE197: =((P197*2.6*R197/S197/2)*30/Z197+(P197*2.6*T197/U197)*N197*2/Z197)*AB197 -> 12818.624 | AF197: =AL197/AE197*1000 -> 1248.1839 | AG197: 1 | AI197: =AJ197/1.22 -> 3278.6885 | AJ197: 4000 | AK197: =AI197*Q197 -> 13114.754 | AL197: =AK197*1.22 -> 16000
A198: OREN2 | B198: Оренбургская область | C198: Оренбург | D198: Ленинский | E198: мкрн. 18_19_20 | F198: А | G198: 45952 | H198: Комфорт | I198: ЖК 17 Микрорайон | J198: улица Поляничко, 6 | K198: 51.824091 | L198: 55.169786 | M198: 2025 | N198: 17 | O198: 230 | P198: =O198*2.8 -> 644 | Q198: 2 | R198: 2 | S198: 6 | T198: 0 | U198: 12 | V198: Горизонтальный 4*3 | W198: Digital (без звука) | X198: видеоролик | Y198: 10 | Z198: 150 | AA198: 576 | AB198: 31 | AC198: =Q198*AA198*AB198 -> 35712 | AD198: =AE198/P198 -> 2.6866667 | AE198: =((P198*2.6*R198/S198/2)*30/Z198+(P198*2.6*T198/U198)*N198*2/Z198)*AB198 -> 1730.2133 | AF198: =AL198/AE198*1000 -> 4623.7073 | AG198: 1 | AI198: =AJ198/1.22 -> 3278.6885 | AJ198: 4000 | AK198: =AI198*Q198 -> 6557.377 | AL198: =AK198*1.22 -> 8000
A199: OREN2 | B199: Оренбургская область | C199: Оренбург | D199: Ленинский | E199: мкрн. 18_19_20 | F199: А | G199: 45952 | H199: Комфорт | I199: ЖК 17 Микрорайон | J199: улица Поляничко, 6 | K199: 51.824091 | L199: 55.169786 | M199: 2025 | N199: 17 | O199: 230 | P199: =O199*2.8 -> 644 | Q199: 2 | R199: 0 | S199: 6 | T199: 2 | U199: 12 | V199: Вертикальный 4*3 | W199: Digital (без звука) | X199: видеоролик | Y199: 10 | Z199: 150 | AA199: 576 | AB199: 31 | AC199: =Q199*AA199*AB199 -> 35712 | AD199: =AE199/P199 -> 3.0448889 | AE199: =((P199*2.6*R199/S199/2)*30/Z199+(P199*2.6*T199/U199)*N199*2/Z199)*AB199 -> 1960.9084 | AF199: =AL199/AE199*1000 -> 4079.7417 | AG199: 1 | AI199: =AJ199/1.22 -> 3278.6885 | AJ199: 4000 | AK199: =AI199*Q199 -> 6557.377 | AL199: =AK199*1.22 -> 8000
A200: OREN2 | B200: Оренбургская область | C200: Оренбург | D200: Ленинский | E200: мкрн. 18_19_20 | F200: А | G200: 45952 | H200: Комфорт | I200: ЖК 17 Микрорайон | J200: улица Салмышская, 43/2 | K200: 51.822514 | L200: 55.168053 | M200: 2014 | N200: 13 | O200: 99 | P200: =O200*2.8 -> 277.2 | Q200: 4 | R200: 2 | S200: 2 | T200: 2 | U200: 4 | V200: Вертикальный 4*3 | W200: Digital (без звука) | X200: видеоролик | Y200: 10 | Z200: 150 | AA200: 576 | AB200: 31 | AC200: =Q200*AA200*AB200 -> 71424 | AD200: =AE200/P200 -> 15.045333 | AE200: =((P200*2.6*R200/S200/2)*30/Z200+(P200*2.6*T200/U200)*N200*2/Z200)*AB200 -> 4170.5664 | AF200: =AL200/AE200*1000 -> 3836.4094 | AG200: 1 | AI200: =AJ200/1.22 -> 3278.6885 | AJ200: 4000 | AK200: =AI200*Q200 -> 13114.754 | AL200: =AK200*1.22 -> 16000
A201: OREN3 | B201: Оренбургская область | C201: Оренбург | D201: Ленинский | E201: мкрн. 18_19_20 | F201: А | G201: 45952 | H201: Комфорт | I201: ЖК 19 Микрорайон | J201: улица Карпово, 3 | K201: 51.815186 | L201: 55.183117 | M201: 2016 | N201: 14 | O201: 241 | P201: =O201*2.8 -> 674.8 | Q201: 8 | R201: 4 | S201: 4 | T201: 4 | U201: 8 | V201: Горизонтальный 4*3 | W201: Digital (без звука) | X201: видеоролик | Y201: 10 | Z201: 150 | AA201: 576 | AB201: 31 | AC201: =Q201*AA201*AB201 -> 142848 | AD201: =AE201/P201 -> 15.582667 | AE201: =((P201*2.6*R201/S201/2)*30/Z201+(P201*2.6*T201/U201)*N201*2/Z201)*AB201 -> 10515.183 | AF201: =AL201/AE201*1000 -> 3043.2184 | AG201: 1 | AI201: =AJ201/1.22 -> 3278.6885 | AJ201: 4000 | AK201: =AI201*Q201 -> 26229.508 | AL201: =AK201*1.22 -> 32000
A202: OREN3 | B202: Оренбургская область | C202: Оренбург | D202: Ленинский | E202: мкрн. 18_19_20 | F202: А | G202: 45952 | H202: Комфорт | I202: ЖК 19 Микрорайон | J202: улица Салмышская, 67/3 | K202: 51.814412 | L202: 55.180769 | M202: 2011 | N202: 14 | O202: 117 | P202: =O202*2.8 -> 327.6 | Q202: 2 | R202: 2 | S202: 2 | T202: 0 | U202: 4 | V202: Горизонтальный 4*3 | W202: Digital (без звука) | X202: видеоролик | Y202: 10 | Z202: 150 | AA202: 576 | AB202: 31 | AC202: =Q202*AA202*AB202 -> 35712 | AD202: =AE202/P202 -> 8.06 | AE202: =((P202*2.6*R202/S202/2)*30/Z202+(P202*2.6*T202/U202)*N202*2/Z202)*AB202 -> 2640.456 | AF202: =AL202/AE202*1000 -> 3029.7797 | AG202: 1 | AI202: =AJ202/1.22 -> 3278.6885 | AJ202: 4000 | AK202: =AI202*Q202 -> 6557.377 | AL202: =AK202*1.22 -> 8000
A203: OREN4 | B203: Оренбургская область | C203: Оренбург | D203: Ленинский | E203: мкрн. 13_15_16 | F203: Б | G203: 45952 | H203: Комфорт | I203: ЖК Акварель | J203: улица Поляничко, 11/2 | K203: 51.822822 | L203: 55.174567 | M203: 2020 | N203: 14 | O203: 240 | P203: =O203*2.8 -> 672 | Q203: 3 | R203: 3 | S203: 3 | T203: 0 | U203: 6 | V203: Вертикальный 4*3 | W203: Digital (без звука) | X203: видеоролик | Y203: 10 | Z203: 150 | AA203: 576 | AB203: 31 | AC203: =Q203*AA203*AB203 -> 53568 | AD203: =AE203/P203 -> 8.06 | AE203: =((P203*2.6*R203/S203/2)*30/Z203+(P203*2.6*T203/U203)*N203*2/Z203)*AB203 -> 5416.32 | AF203: =AL203/AE203*1000 -> 2215.5264 | AG203: 1 | AI203: =AJ203/1.22 -> 3278.6885 | AJ203: 4000 | AK203: =AI203*Q203 -> 9836.0656 | AL203: =AK203*1.22 -> 12000
A204: OREN4 | B204: Оренбургская область | C204: Оренбург | D204: Ленинский | E204: мкрн. 13_15_16 | F204: Б | G204: 45952 | H204: Комфорт | I204: ЖК Акварель | J204: улица Саморядова, 6 | K204: 51.821002 | L204: 55.176029 | M204: 2021 | N204: 19 | O204: 448 | P204: =O204*2.8 -> 1254.4 | Q204: 6 | R204: 6 | S204: 6 | T204: 0 | U204: 12 | V204: Горизонтальный 4*3 | W204: Digital (без звука) | X204: видеоролик | Y204: 10 | Z204: 150 | AA204: 576 | AB204: 31 | AC204: =Q204*AA204*AB204 -> 107136 | AD204: =AE204/P204 -> 8.06 | AE204: =((P204*2.6*R204/S204/2)*30/Z204+(P204*2.6*T204/U204)*N204*2/Z204)*AB204 -> 10110.464 | AF204: =AL204/AE204*1000 -> 2373.7783 | AG204: 1 | AI204: =AJ204/1.22 -> 3278.6885 | AJ204: 4000 | AK204: =AI204*Q204 -> 19672.131 | AL204: =AK204*1.22 -> 24000
A205: OREN4 | B205: Оренбургская область | C205: Оренбург | D205: Ленинский | E205: мкрн. 13_15_16 | F205: Б | G205: 45952 | H205: Комфорт | I205: ЖК Акварель | J205: Северный проезд, 24/1 | K205: 51.827832 | L205: 55.173848 | M205: 2019 | N205: 14 | O205: 182 | P205: =O205*2.8 -> 509.6 | Q205: 4 | R205: 2 | S205: 2 | T205: 2 | U205: 4 | V205: Вертикальный 4*3 | W205: Digital (без звука) | X205: видеоролик | Y205: 10 | Z205: 150 | AA205: 576 | AB205: 31 | AC205: =Q205*AA205*AB205 -> 71424 | AD205: =AE205/P205 -> 15.582667 | AE205: =((P205*2.6*R205/S205/2)*30/Z205+(P205*2.6*T205/U205)*N205*2/Z205)*AB205 -> 7940.9269 | AF205: =AL205/AE205*1000 -> 2014.8781 | AG205: 1 | AI205: =AJ205/1.22 -> 3278.6885 | AJ205: 4000 | AK205: =AI205*Q205 -> 13114.754 | AL205: =AK205*1.22 -> 16000
A206: OREN5 | B206: Оренбургская область | C206: Оренбург | D206: Ленинский | E206: мкрн. 13_15_16 | F206: А | G206: 45803 | H206: Комфорт | I206: ЖК Акварель 2 | J206: проезд Северный,18 | K206: 51.825543 | L206: 55.168108 | M206: 2010 | N206: 15 | O206: 104 | P206: =O206*2.8 -> 291.2 | Q206: 4 | R206: 2 | S206: 2 | T206: 2 | U206: 4 | V206: Вертикальный 4*3 | W206: Digital (без звука) | X206: видеоролик | Y206: 10 | Z206: 150 | AA206: 576 | AB206: 31 | AC206: =Q206*AA206*AB206 -> 71424 | AD206: =AE206/P206 -> 16.12 | AE206: =((P206*2.6*R206/S206/2)*30/Z206+(P206*2.6*T206/U206)*N206*2/Z206)*AB206 -> 4694.144 | AF206: =AL206/AE206*1000 -> 3408.5022 | AG206: 1 | AI206: =AJ206/1.22 -> 3278.6885 | AJ206: 4000 | AK206: =AI206*Q206 -> 13114.754 | AL206: =AK206*1.22 -> 16000
A207: OREN5 | B207: Оренбургская область | C207: Оренбург | D207: Ленинский | E207: мкрн. 13_15_16 | F207: А | G207: 45803 | H207: Комфорт | I207: ЖК Акварель 2 | J207: улица Поляничко, 11/3 | K207: 51.823488 | L207: 55.176177 | M207: 2020 | N207: 15 | O207: 196 | P207: =O207*2.8 -> 548.8 | Q207: 4 | R207: 2 | S207: 2 | T207: 2 | U207: 4 | V207: Вертикальный 4*3 | W207: Digital (без звука) | X207: видеоролик | Y207: 10 | Z207: 150 | AA207: 576 | AB207: 31 | AC207: =Q207*AA207*AB207 -> 71424 | AD207: =AE207/P207 -> 16.12 | AE207: =((P207*2.6*R207/S207/2)*30/Z207+(P207*2.6*T207/U207)*N207*2/Z207)*AB207 -> 8846.656 | AF207: =AL207/AE207*1000 -> 1808.593 | AG207: 1 | AI207: =AJ207/1.22 -> 3278.6885 | AJ207: 4000 | AK207: =AI207*Q207 -> 13114.754 | AL207: =AK207*1.22 -> 16000
A208: OREN5 | B208: Оренбургская область | C208: Оренбург | D208: Ленинский | E208: мкрн. 13_15_16 | F208: А | G208: 45803 | H208: Комфорт | I208: ЖК Акварель 2 | J208: улица Поляничко, 2 | K208: 51.825651 | L208: 55.169472 | M208: 2016 | N208: 17 | O208: 159 | P208: =O208*2.8 -> 445.2 | Q208: 2 | R208: 1 | S208: 1 | T208: 1 | U208: 2 | V208: Вертикальный 4*3 | W208: Digital (без звука) | X208: видеоролик | Y208: 10 | Z208: 150 | AA208: 576 | AB208: 31 | AC208: =Q208*AA208*AB208 -> 35712 | AD208: =AE208/P208 -> 17.194667 | AE208: =((P208*2.6*R208/S208/2)*30/Z208+(P208*2.6*T208/U208)*N208*2/Z208)*AB208 -> 7655.0656 | AF208: =AL208/AE208*1000 -> 1045.0596 | AG208: 1 | AI208: =AJ208/1.22 -> 3278.6885 | AJ208: 4000 | AK208: =AI208*Q208 -> 6557.377 | AL208: =AK208*1.22 -> 8000
... A230: OREN14 | B230: Оренбургская область | C230: Оренбург | D230: Промышленный | E230: Промышленный_Центр | F230: Б | G230: 46255 | H230: Стандарт | I230: ЖК Малая земля 3 | J230: улица Пролетарская, 300 | K230: 51.807959 | L230: 55.096256 | M230: 2020 | N230: 18 | O230: 357 | P230: =O230*2.8 -> 999.6 | Q230: 4 | R230: 4 | S230: 4 | T230: 0 | U230: 8 | V230: Горизонтальный 4*3 | W230: Digital (без звука) | X230: видеоролик | Y230: 10 | Z230: 150 | AA230: 576 | AB230: 31 | AC230: =Q230*AA230*AB230 -> 71424 | AD230: =AE230/P230 -> 8.06 | AE230: =((P230*2.6*R230/S230/2)*30/Z230+(P230*2.6*T230/U230)*N230*2/Z230)*AB230 -> 8056.776 | AF230: =AL230/AE230*1000 -> 1985.906 | AG230: 1 | AI230: =AJ230/1.22 -> 3278.6885 | AJ230: 4000 | AK230: =AI230*Q230 -> 13114.754 | AL230: =AK230*1.22 -> 16000
A231: OREN14 | B231: Оренбургская область | C231: Оренбург | D231: Промышленный | F231: Б | G231: 46255 | H231: Комфорт | I231: ЖК Малая земля 3 | J231: улица Пролетарская, 300 | K231: 51.807726 | L231: 55.096344 | M231: 2020 | N231: 17 | O231: 357 | P231: =O231*2.8 -> 999.6 | Q231: 4 | R231: 0 | S231: 4 | T231: 4 | U231: 8 | V231: Вертикальный 4*3 | W231: Digital (без звука) | X231: видеоролик | Y231: 10 | Z231: 150 | AA231: 576 | AB231: 31 | AC231: =Q231*AA231*AB231 -> 71424 | AD231: =AE231/P231 -> 9.1346667 | AE231: =((P231*2.6*R231/S231/2)*30/Z231+(P231*2.6*T231/U231)*N231*2/Z231)*AB231 -> 9131.0128 | AF231: =AL231/AE231*1000 -> 1752.27 | AG231: 1 | AI231: =AJ231/1.22 -> 3278.6885 | AJ231: 4000 | AK231: =AI231*Q231 -> 13114.754 | AL231: =AK231*1.22 -> 16000
A232: OREN14 | B232: Оренбургская область | C232: Оренбург | D232: Промышленный | F232: Б | G232: 46255 | H232: Комфорт | I232: ЖК Малая земля 3 | J232: улица Пролетарская, 292 | K232: 51.805532 | L232: 55.095608 | M232: 2019 | N232: 19 | O232: 299 | P232: =O232*2.8 -> 837.2 | Q232: 8 | R232: 4 | S232: 4 | T232: 4 | U232: 8 | V232: Вертикальный 4*3 | W232: Digital (без звука) | X232: видеоролик | Y232: 10 | Z232: 150 | AA232: 576 | AB232: 31 | AC232: =Q232*AA232*AB232 -> 142848 | AD232: =AE232/P232 -> 18.269333 | AE232: =((P232*2.6*R232/S232/2)*30/Z232+(P232*2.6*T232/U232)*N232*2/Z232)*AB232 -> 15295.086 | AF232: =AL232/AE232*1000 -> 2092.1752 | AG232: 1 | AI232: =AJ232/1.22 -> 3278.6885 | AJ232: 4000 | AK232: =AI232*Q232 -> 26229.508 | AL232: =AK232*1.22 -> 32000
A233: OREN15 | B233: Оренбургская область | C233: Оренбург | D233: Ленинский | E233: мкрн. 18_19_20 | F233: А | G233: 45989 | H233: Стандарт | I233: ЖК Молодежный 1 | J233: улица Карпова, 3/1 | K233: 51.817196 | L233: 55.181866 | M233: 2016 | N233: 19 | O233: 576 | P233: =O233*2.8 -> 1612.8 | Q233: 8 | R233: 8 | S233: 8 | T233: 0 | U233: 16 | V233: Горизонтальный 4*3 | W233: Digital (без звука) | X233: видеоролик | Y233: 10 | Z233: 150 | AA233: 576 | AB233: 31 | AC233: =Q233*AA233*AB233 -> 142848 | AD233: =AE233/P233 -> 8.06 | AE233: =((P233*2.6*R233/S233/2)*30/Z233+(P233*2.6*T233/U233)*N233*2/Z233)*AB233 -> 12999.168 | AF233: =AL233/AE233*1000 -> 2461.696 | AG233: 1 | AI233: =AJ233/1.22 -> 3278.6885 | AJ233: 4000 | AK233: =AI233*Q233 -> 26229.508 | AL233: =AK233*1.22 -> 32000
A234: OREN15 | B234: Оренбургская область | C234: Оренбург | D234: Ленинский | E234: мкрн. 18_19_20 | F234: А | G234: 45989 | H234: Стандарт | I234: ЖК Молодежный 1 | J234: улица Карпова, 3/1 | K234: 51.817196 | L234: 55.181866 | M234: 2016 | N234: 19 | O234: 576 | P234: =O234*2.8 -> 1612.8 | Q234: 8 | R234: 0 | S234: 8 | T234: 8 | U234: 16 | V234: Вертикальный 4*3 | W234: Digital (без звука) | X234: видеоролик | Y234: 10 | Z234: 150 | AA234: 576 | AB234: 31 | AC234: =Q234*AA234*AB234 -> 142848 | AD234: =AE234/P234 -> 10.209333 | AE234: =((P234*2.6*R234/S234/2)*30/Z234+(P234*2.6*T234/U234)*N234*2/Z234)*AB234 -> 16465.613 | AF234: =AL234/AE234*1000 -> 1943.4442 | AG234: 1 | AI234: =AJ234/1.22 -> 3278.6885 | AJ234: 4000 | AK234: =AI234*Q234 -> 26229.508 | AL234: =AK234*1.22 -> 32000
A235: OREN16 | B235: Оренбургская область | C235: Оренбург | D235: Ленинский | E235: мкрн. 13_15_16 | F235: А | G235: 45989 | H235: Стандарт | I235: ЖК Звездный | J235: улица Братьев Хусаиновых, 8 | K235: 51.823776 | L235: 55.178223 | M235: 2021 | N235: 17 | O235: 297 | P235: =O235*2.8 -> 831.6 | Q235: 3 | R235: 3 | S235: 3 | T235: 0 | U235: 6 | V235: Горизонтальный 4*3 | W235: Digital (без звука) | X235: видеоролик | Y235: 10 | Z235: 150 | AA235: 576 | AB235: 31 | AC235: =Q235*AA235*AB235 -> 53568 | AD235: =AE235/P235 -> 8.06 | AE235: =((P235*2.6*R235/S235/2)*30/Z235+(P235*2.6*T235/U235)*N235*2/Z235)*AB235 -> 6702.696 | AF235: =AL235/AE235*1000 -> 1790.3244 | AG235: 1 | AI235: =AJ235/1.22 -> 3278.6885 | AJ235: 4000 | AK235: =AI235*Q235 -> 9836.0656 | AL235: =AK235*1.22 -> 12000
A236: OREN16 | B236: Оренбургская область | C236: Оренбург | D236: Ленинский | E236: мкрн. 13_15_16 | F236: А | G236: 45989 | H236: Стандарт | I236: ЖК Звездный | J236: улица Братьев Хусаиновых, 8 | K236: 51.823776 | L236: 55.178223 | M236: 2021 | N236: 17 | O236: 297 | P236: =O236*2.8 -> 831.6 | Q236: 3 | R236: 0 | S236: 3 | T236: 3 | U236: 6 | V236: Вертикальный 4*3 | W236: Digital (без звука) | X236: видеоролик | Y236: 10 | Z236: 150 | AA236: 576 | AB236: 31 | AC236: =Q236*AA236*AB236 -> 53568 | AD236: =AE236/P236 -> 9.1346667 | AE236: =((P236*2.6*R236/S236/2)*30/Z236+(P236*2.6*T236/U236)*N236*2/Z236)*AB236 -> 7596.3888 | AF236: =AL236/AE236*1000 -> 1579.698 | AG236: 1 | AI236: =AJ236/1.22 -> 3278.6885 | AJ236: 4000 | AK236: =AI236*Q236 -> 9836.0656 | AL236: =AK236*1.22 -> 12000
A237: OREN16 | B237: Оренбургская область | C237: Оренбург | D237: Ленинский | E237: мкрн. 13_15_16 | F237: А | G237: 45989 | H237: Стандарт | I237: ЖК Звездный | J237: улица Братьев Хусаиновых, 6 | K237: 51.824999 | L237: 55.176968 | M237: 2025 | N237: 20 | O237: 594 | P237: =O237*2.8 -> 1663.2 | Q237: 5 | R237: 5 | S237: 5 | T237: 0 | U237: 10 | V237: Горизонтальный 4*3 | W237: Digital (без звука) | X237: видеоролик | Y237: 10 | Z237: 150 | AA237: 576 | AB237: 31 | AC237: =Q237*AA237*AB237 -> 89280 | AD237: =AE237/P237 -> 8.06 | AE237: =((P237*2.6*R237/S237/2)*30/Z237+(P237*2.6*T237/U237)*N237*2/Z237)*AB237 -> 13405.392 | AF237: =AL237/AE237*1000 -> 1491.937 | AG237: 1 | AI237: =AJ237/1.22 -> 3278.6885 | AJ237: 4000 | AK237: =AI237*Q237 -> 16393.443 | AL237: =AK237*1.22 -> 20000
A238: OREN16 | B238: Оренбургская область | C238: Оренбург | D238: Ленинский | E238: мкрн. 13_15_16 | F238: А | G238: 45989 | H238: Стандарт | I238: ЖК Звездный | J238: улица Братьев Хусаиновых, 6 | K238: 51.824999 | L238: 55.176968 | M238: 2025 | N238: 20 | O238: 594 | P238: =O238*2.8 -> 1663.2 | Q238: 5 | R238: 0 | S238: 5 | T238: 5 | U238: 10 | V238: Вертикальный 4*3 | W238: Digital (без звука) | X238: видеоролик | Y238: 10 | Z238: 150 | AA238: 576 | AB238: 31 | AC238: =Q238*AA238*AB238 -> 89280 | AD238: =AE238/P238 -> 10.746667 | AE238: =((P238*2.6*R238/S238/2)*30/Z238+(P238*2.6*T238/U238)*N238*2/Z238)*AB238 -> 17873.856 | AF238: =AL238/AE238*1000 -> 1118.9527 | AG238: 1 | AI238: =AJ238/1.22 -> 3278.6885 | AJ238: 4000 | AK238: =AI238*Q238 -> 16393.443 | AL238: =AK238*1.22 -> 20000
A239: OREN17 | B239: Оренбургская область | C239: Оренбург | D239: Ленинский | E239: мкрн. Южный | F239: Б | G239: 45995 | H239: Стандарт | I239: ЖК Южный | J239: улица Илекская, 2/2 | K239: 51.721118 | L239: 55.108154 | M239: 2013 | N239: 14 | O239: 83 | P239: =O239*2.8 -> 232.4 | Q239: 1 | R239: 1 | S239: 1 | T239: 0 | U239: 2 | V239: Горизонтальный 4*3 | W239: Digital (без звука) | X239: видеоролик | Y239: 10 | Z239: 150 | AA239: 576 | AB239: 31 | AC239: =Q239*AA239*AB239 -> 17856 | AD239: =AE239/P239 -> 8.06 | AE239: =((P239*2.6*R239/S239/2)*30/Z239+(P239*2.6*T239/U239)*N239*2/Z239)*AB239 -> 1873.144 | AF239: =AL239/AE239*1000 -> 2135.4471 | AG239: 1 | AI239: =AJ239/1.22 -> 3278.6885 | AJ239: 4000 | AK239: =AI239*Q239 -> 3278.6885 | AL239: =AK239*1.22 -> 4000
A240: OREN17 | B240: Оренбургская область | C240: Оренбург | D240: Ленинский | E240: мкрн. Южный | F240: Б | G240: 45995 | H240: Стандарт | I240: ЖК Южный | J240: улица Беляевская,15/1 | K240: 51.721636 | L240: 55.109629 | M240: 2017 | N240: 17 | O240: 175 | P240: =O240*2.8 -> 490 | Q240: 2 | R240: 2 | S240: 2 | T240: 0 | U240: 4 | V240: Горизонтальный 4*3 | W240: Digital (без звука) | X240: видеоролик | Y240: 10 | Z240: 150 | AA240: 576 | AB240: 31 | AC240: =Q240*AA240*AB240 -> 35712 | AD240: =AE240/P240 -> 8.06 | AE240: =((P240*2.6*R240/S240/2)*30/Z240+(P240*2.6*T240/U240)*N240*2/Z240)*AB240 -> 3949.4 | AF240: =AL240/AE240*1000 -> 2025.6241 | AG240: 1 | AI240: =AJ240/1.22 -> 3278.6885 | AJ240: 4000 | AK240: =AI240*Q240 -> 6557.377 | AL240: =AK240*1.22 -> 8000
A241: OREN17 | B241: Оренбургская область | C241: Оренбург | D241: Ленинский | E241: мкрн. Южный | F241: Б | G241: 45995 | H241: Стандарт | I241: ЖК Южный | J241: улица Беляевская, 15 | K241: 51.722049 | L241: 55.107403 | M241: 2016 | N241: 15 | O241: 572 | P241: =O241*2.8 -> 1601.6 | Q241: 8 | R241: 8 | S241: 8 | T241: 0 | U241: 16 | V241: Горизонтальный 4*3 | W241: Digital (без звука) | X241: видеоролик | Y241: 10 | Z241: 150 | AA241: 576 | AB241: 31 | AC241: =Q241*AA241*AB241 -> 142848 | AD241: =AE241/P241 -> 8.06 | AE241: =((P241*2.6*R241/S241/2)*30/Z241+(P241*2.6*T241/U241)*N241*2/Z241)*AB241 -> 12908.896 | AF241: =AL241/AE241*1000 -> 2478.9107 | AG241: 1 | AI241: =AJ241/1.22 -> 3278.6885 | AJ241: 4000 | AK241: =AI241*Q241 -> 26229.508 | AL241: =AK241*1.22 -> 32000
A242: OREN17 | B242: Оренбургская область | C242: Оренбург | D242: Ленинский | E242: мкрн. Южный | F242: Б | G242: 45995 | H242: Стандарт | I242: ЖК Южный | J242: улица Центральная, 13/1 | K242: 51.713082 | L242: 55.111625 | M242: 2023 | N242: 17 | O242: 136 | P242: =O242*2.8 -> 380.8 | Q242: 1 | R242: 1 | S242: 1 | T242: 0 | U242: 2 | V242: Горизонтальный 4*3 | W242: Digital (без звука) | X242: видеоролик | Y242: 10 | Z242: 150 | AA242: 576 | AB242: 31 | AC242: =Q242*AA242*AB242 -> 17856 | AD242: =AE242/P242 -> 8.06 | AE242: =((P242*2.6*R242/S242/2)*30/Z242+(P242*2.6*T242/U242)*N242*2/Z242)*AB242 -> 3069.248 | AF242: =AL242/AE242*1000 -> 1303.2508 | AG242: 1 | AI242: =AJ242/1.22 -> 3278.6885 | AJ242: 4000 | AK242: =AI242*Q242 -> 3278.6885 | AL242: =AK242*1.22 -> 4000
A243: OREN18 | B243: Оренбургская область | C243: Оренбург | D243: Ленинский | E243: мкрн. Дубки | F243: А | G243: 45995 | H243: Комфорт | I243: ЖК Донковцева 1 | J243: улица Донковцева, 1 | K243: 51.770590 | L243: 55.162496 | M243: 2019 | N243: 19 | O243: 348 | P243: =O243*2.8 -> 974.4 | Q243: 5 | R243: 5 | S243: 5 | T243: 0 | U243: 10 | V243: Горизонтальный 4*3 | W243: Digital (без звука) | X243: видеоролик | Y243: 10 | Z243: 150 | AA243: 576 | AB243: 31 | AC243: =Q243*AA243*AB243 -> 89280 | AD243: =AE243/P243 -> 8.06 | AE243: =((P243*2.6*R243/S243/2)*30/Z243+(P243*2.6*T243/U243)*N243*2/Z243)*AB243 -> 7853.664 | AF243: =AL243/AE243*1000 -> 2546.5821 | AG243: 1 | AI243: =AJ243/1.22 -> 3278.6885 | AJ243: 4000 | AK243: =AI243*Q243 -> 16393.443 | AL243: =AK243*1.22 -> 20000
A244: OREN18 | B244: Оренбургская область | C244: Оренбург | D244: Ленинский | E244: мкрн. Дубки | F244: А | G244: 45995 | H244: Комфорт | I244: ЖК Донковцева 1 | J244: улица Донковцева, 3 | K244: 51.769821 | L244: 55.162451 | M244: 2019 | N244: 19 | O244: 197 | P244: =O244*2.8 -> 551.6 | Q244: 3 | R244: 3 | S244: 3 | T244: 0 | U244: 6 | V244: Горизонтальный 4*3 | W244: Digital (без звука) | X244: видеоролик | Y244: 10 | Z244: 150 | AA244: 576 | AB244: 31 | AC244: =Q244*AA244*AB244 -> 53568 | AD244: =AE244/P244 -> 8.06 | AE244: =((P244*2.6*R244/S244/2)*30/Z244+(P244*2.6*T244/U244)*N244*2/Z244)*AB244 -> 4445.896 | AF244: =AL244/AE244*1000 -> 2699.1185 | AG244: 1 | AI244: =AJ244/1.22 -> 3278.6885 | AJ244: 4000 | AK244: =AI244*Q244 -> 9836.0656 | AL244: =AK244*1.22 -> 12000
... A260: OREN25 | B260: Оренбургская область | C260: Оренбург | D260: Ленинский | E260: мкрн. Дубки | F260: Б | G260: 46101 | H260: Комфорт | I260: ЖК Дрезден | J260: улица Ленинградская, 92 | K260: 51.777489 | L260: 55.145051 | M260: 2014 | N260: 11 | O260: 105 | P260: =O260*2.8 -> 294 | Q260: 8 | R260: 4 | S260: 4 | T260: 4 | U260: 4 | V260: Горизонтальный 4*3 | W260: Digital (без звука) | X260: видеоролик | Y260: 10 | Z260: 150 | AA260: 576 | AB260: 31 | AC260: =Q260*AA260*AB260 -> 142848 | AD260: =AE260/P260 -> 19.881333 | AE260: =((P260*2.6*R260/S260/2)*30/Z260+(P260*2.6*T260/U260)*N260*2/Z260)*AB260 -> 5845.112 | AF260: =AL260/AE260*1000 -> 5474.6599 | AG260: 1 | AI260: =AJ260/1.22 -> 3278.6885 | AJ260: 4000 | AK260: =AI260*Q260 -> 26229.508 | AL260: =AK260*1.22 -> 32000
A261: OREN25 | B261: Оренбургская область | C261: Оренбург | D261: Ленинский | E261: мкрн. Дубки | F261: Б | G261: 46101 | H261: Комфорт | I261: ЖК Дрезден | J261: улица Мало-Ленинская, 167/2 | K261: 51.775255, 55.140793 | M261: 2016 | N261: 18 | O261: 256 | P261: =O261*2.8 -> 716.8 | Q261: 6 | R261: 3 | S261: 1 | T261: 3 | U261: 1 | V261: Вертикальный 4*3 | W261: Digital (без звука) | X261: видеоролик | Y261: 10 | Z261: 150 | AA261: 576 | AB261: 31 | AC261: =Q261*AA261*AB261 -> 107136 | AD261: =AE261/P261 -> 82.212 | AE261: =((P261*2.6*R261/S261/2)*30/Z261+(P261*2.6*T261/U261)*N261*2/Z261)*AB261 -> 58929.562 | AF261: =AL261/AE261*1000 -> 407.26588 | AG261: 1 | AI261: =AJ261/1.22 -> 3278.6885 | AJ261: 4000 | AK261: =AI261*Q261 -> 19672.131 | AL261: =AK261*1.22 -> 24000
A262: OREN26 | B262: Оренбургская область | C262: Оренбург | D262: Ленинский | E262: Промышленный_Центр | F262: Б | G262: 46107 | H262: Комфорт | I262: ЖК Премьер 2 | J262: Почтовый переулок, 11 | K262: 51.760986 | L262: 55.109909 | M262: 2011 | N262: 8 | O262: 63 | P262: =O262*2.8 -> 176.4 | Q262: 3 | R262: 3 | S262: 3 | T262: 0 | U262: 3 | V262: Горизонтальный 4*3 | W262: Digital (без звука) | X262: видеоролик | Y262: 10 | Z262: 150 | AA262: 576 | AB262: 31 | AC262: =Q262*AA262*AB262 -> 53568 | AD262: =AE262/P262 -> 8.06 | AE262: =((P262*2.6*R262/S262/2)*30/Z262+(P262*2.6*T262/U262)*N262*2/Z262)*AB262 -> 1421.784 | AF262: =AL262/AE262*1000 -> 8440.1006 | AG262: 1 | AI262: =AJ262/1.22 -> 3278.6885 | AJ262: 4000 | AK262: =AI262*Q262 -> 9836.0656 | AL262: =AK262*1.22 -> 12000
A263: OREN26 | B263: Оренбургская область | C263: Оренбург | D263: Центральный | E263: Промышленный_Центр | F263: Б | G263: 46107 | H263: Комфорт | I263: ЖК Премьер 2 | J263: улица Маршала Жукова, 27 | K263: 51.773176 | L263: 55.108085 | M263: 2007 | N263: 14 | O263: 72 | P263: =O263*2.8 -> 201.6 | Q263: 4 | R263: 0 | S263: 1 | T263: 4 | U263: 2 | V263: Вертикальный 4*3 | W263: Digital (без звука) | X263: видеоролик | Y263: 10 | Z263: 150 | AA263: 576 | AB263: 31 | AC263: =Q263*AA263*AB263 -> 71424 | AD263: =AE263/P263 -> 30.090667 | AE263: =((P263*2.6*R263/S263/2)*30/Z263+(P263*2.6*T263/U263)*N263*2/Z263)*AB263 -> 6066.2784 | AF263: =AL263/AE263*1000 -> 2637.5314 | AG263: 1 | AI263: =AJ263/1.22 -> 3278.6885 | AJ263: 4000 | AK263: =AI263*Q263 -> 13114.754 | AL263: =AK263*1.22 -> 16000
A264: OREN26 | B264: Оренбургская область | C264: Оренбург | D264: Ленинский | E264: Промышленный_Центр | F264: Б | G264: 46107 | H264: Комфорт | I264: ЖК Премьер 2 | J264: улица Краснознаменная, 47 | K264: 51.767123 | L264: 55.107879 | M264: 2021 | N264: 10 | O264: 66 | P264: =O264*2.8 -> 184.8 | Q264: 4 | R264: 0 | S264: 2 | T264: 4 | U264: 2 | V264: Вертикальный 4*3 | W264: Digital (без звука) | X264: видеоролик | Y264: 10 | Z264: 150 | AA264: 576 | AB264: 31 | AC264: =Q264*AA264*AB264 -> 71424 | AD264: =AE264/P264 -> 21.493333 | AE264: =((P264*2.6*R264/S264/2)*30/Z264+(P264*2.6*T264/U264)*N264*2/Z264)*AB264 -> 3971.968 | AF264: =AL264/AE264*1000 -> 4028.2298 | AG264: 1 | AI264: =AJ264/1.22 -> 3278.6885 | AJ264: 4000 | AK264: =AI264*Q264 -> 13114.754 | AL264: =AK264*1.22 -> 16000
A265: OREN26 | B265: Оренбургская область | C265: Оренбург | D265: Ленинский | E265: Промышленный_Центр | F265: Б | G265: 46107 | H265: Комфорт | I265: ЖК Премьер 2 | J265: улица Ленинская, 59/1 | K265: 51.763144 | L265: 55.113466 | M265: 2006 | N265: 11 | O265: 94 | P265: =O265*2.8 -> 263.2 | Q265: 4 | R265: 0 | S265: 4 | T265: 4 | U265: 4 | V265: Вертикальный 4*3 | W265: Digital (без звука) | X265: видеоролик | Y265: 10 | Z265: 150 | AA265: 576 | AB265: 31 | AC265: =Q265*AA265*AB265 -> 71424 | AD265: =AE265/P265 -> 11.821333 | AE265: =((P265*2.6*R265/S265/2)*30/Z265+(P265*2.6*T265/U265)*N265*2/Z265)*AB265 -> 3111.3749 | AF265: =AL265/AE265*1000 -> 5142.4211 | AG265: 1 | AI265: =AJ265/1.22 -> 3278.6885 | AJ265: 4000 | AK265: =AI265*Q265 -> 13114.754 | AL265: =AK265*1.22 -> 16000
A266: OREN27 | B266: Оренбургская область | C266: Оренбург | D266: Центральный | E266: Промышленный_Центр | F266: Б | G266: 46133 | H266: Комфорт | I266: ЖК Риверсайд | J266: улица Черепановых, 2А | K266: 51.754018 | L266: 55.090577 | M266: 2015 | N266: 14 | O266: 119 | P266: =O266*2.8 -> 333.2 | Q266: 2 | R266: 2 | S266: 3 | T266: 0 | U266: 4 | V266: Вертикальный 4*3 | W266: Digital (без звука) | X266: видеоролик | Y266: 10 | Z266: 150 | AA266: 576 | AB266: 31 | AC266: =Q266*AA266*AB266 -> 35712 | AD266: =AE266/P266 -> 5.3733333 | AE266: =((P266*2.6*R266/S266/2)*30/Z266+(P266*2.6*T266/U266)*N266*2/Z266)*AB266 -> 1790.3947 | AF266: =AL266/AE266*1000 -> 4468.2886 | AG266: 1 | AI266: =AJ266/1.22 -> 3278.6885 | AJ266: 4000 | AK266: =AI266*Q266 -> 6557.377 | AL266: =AK266*1.22 -> 8000
A267: OREN27 | B267: Оренбургская область | C267: Оренбург | D267: Центральный | E267: Промышленный_Центр | F267: Б | G267: 46133 | H267: Комфорт | I267: ЖК Риверсайд | J267: улица Яицкая,1/2 | K267: 51.754469 | L267: 55.090757 | M267: 2015 | N267: 14 | O267: 172 | P267: =O267*2.8 -> 481.6 | Q267: 3 | R267: 3 | S267: 3 | T267: 0 | U267: 6 | V267: Вертикальный 4*3 | W267: Digital (без звука) | X267: видеоролик | Y267: 10 | Z267: 150 | AA267: 576 | AB267: 31 | AC267: =Q267*AA267*AB267 -> 53568 | AD267: =AE267/P267 -> 8.06 | AE267: =((P267*2.6*R267/S267/2)*30/Z267+(P267*2.6*T267/U267)*N267*2/Z267)*AB267 -> 3881.696 | AF267: =AL267/AE267*1000 -> 3091.4322 | AG267: 1 | AI267: =AJ267/1.22 -> 3278.6885 | AJ267: 4000 | AK267: =AI267*Q267 -> 9836.0656 | AL267: =AK267*1.22 -> 12000
A268: OREN27 | B268: Оренбургская область | C268: Оренбург | D268: Центральный | E268: Промышленный_Центр | F268: Б | G268: 46133 | H268: Комфорт | I268: ЖК Риверсайд | J268: улица Яицкая,1/3 | K268: 51.754469 | L268: 55.090757 | M268: 2015 | N268: 14 | O268: 172 | P268: =O268*2.8 -> 481.6 | Q268: 2 | R268: 2 | S268: 3 | T268: 0 | U268: 6 | V268: Вертикальный 4*3 | W268: Digital (без звука) | X268: видеоролик | Y268: 10 | Z268: 150 | AA268: 576 | AB268: 31 | AC268: =Q268*AA268*AB268 -> 35712 | AD268: =AE268/P268 -> 5.3733333 | AE268: =((P268*2.6*R268/S268/2)*30/Z268+(P268*2.6*T268/U268)*N268*2/Z268)*AB268 -> 2587.7973 | AF268: =AL268/AE268*1000 -> 3091.4322 | AG268: 1 | AI268: =AJ268/1.22 -> 3278.6885 | AJ268: 4000 | AK268: =AI268*Q268 -> 6557.377 | AL268: =AK268*1.22 -> 8000
A269: OREN28 | B269: Оренбургская область | C269: Оренбург | D269: Центральный | F269: Б | G269: 46258 | H269: Комфорт | I269: ЖК Риверсайд 2 | J269: улица Яицкая, 9 | K269: 51.755177, 55.089580 | M269: 2025 | N269: 11 | O269: 311 | P269: =O269*2.8 -> 870.8 | Q269: 12 | R269: 6 | S269: 6 | T269: 6 | U269: 6 | V269: Вертикальный 4*3 | W269: Digital (без звука) | X269: видеоролик | Y269: 10 | Z269: 150 | AA269: 576 | AB269: 31 | AC269: =Q269*AA269*AB269 -> 214272 | AD269: =AE269/P269 -> 19.881333 | AE269: =((P269*2.6*R269/S269/2)*30/Z269+(P269*2.6*T269/U269)*N269*2/Z269)*AB269 -> 17312.665 | AF269: =AL269/AE269*1000 -> 2772.5367 | AG269: 1 | AI269: =AJ269/1.22 -> 3278.6885 | AJ269: 4000 | AK269: =AI269*Q269 -> 39344.262 | AL269: =AK269*1.22 -> 48000
A270: OREN29 | B270: Оренбургская область | C270: Оренбург | D270: Ленинский | E270: мкрн. 13_15_16 | F270: Б | G270: 46133 | H270: Комфорт | I270: ЖК Новизна | J270: улица Поляничко, 8 | K270: 51.823042 | L270: 55.172198 | M270: 2017 | N270: 18 | O270: 494 | P270: =O270*2.8 -> 1383.2 | Q270: 12 | R270: 6 | S270: 6 | T270: 6 | U270: 12 | V270: Вертикальный 4*3 | W270: Digital (без звука) | X270: видеоролик | Y270: 10 | Z270: 150 | AA270: 576 | AB270: 31 | AC270: =Q270*AA270*AB270 -> 214272 | AD270: =AE270/P270 -> 17.732 | AE270: =((P270*2.6*R270/S270/2)*30/Z270+(P270*2.6*T270/U270)*N270*2/Z270)*AB270 -> 24526.902 | AF270: =AL270/AE270*1000 -> 1957.0347 | AG270: 1 | AI270: =AJ270/1.22 -> 3278.6885 | AJ270: 4000 | AK270: =AI270*Q270 -> 39344.262 | AL270: =AK270*1.22 -> 48000
A271: OREN30 | B271: Оренбургская область | C271: Оренбург | D271: Дзержинский | E271: мкрн. 13_15_16 | F271: Б | G271: 46154 | H271: Комфорт | I271: ЖК Загородное шоссе | J271: улица Загородное шоссе, 14 | K271: 51.837847 | L271: 55.162685 | M271: 2015 | N271: 17 | O271: 505 | P271: =O271*2.8 -> 1414 | Q271: 5 | R271: 5 | S271: 5 | T271: 0 | U271: 10 | V271: Горизонтальный 4*3 | W271: Digital (без звука) | X271: видеоролик | Y271: 10 | Z271: 150 | AA271: 576 | AB271: 31 | AC271: =Q271*AA271*AB271 -> 89280 | AD271: =AE271/P271 -> 8.06 | AE271: =((P271*2.6*R271/S271/2)*30/Z271+(P271*2.6*T271/U271)*N271*2/Z271)*AB271 -> 11396.84 | AF271: =AL271/AE271*1000 -> 1754.8724 | AG271: 1 | AI271: =AJ271/1.22 -> 3278.6885 | AJ271: 4000 | AK271: =AI271*Q271 -> 16393.443 | AL271: =AK271*1.22 -> 20000
A272: OREN30 | B272: Оренбургская область | C272: Оренбург | D272: Дзержинский | E272: мкрн. 13_15_16 | F272: Б | G272: 46154 | H272: Комфорт | I272: ЖК Загородное шоссе | J272: улица Загородное шоссе, 14 | K272: 51.837847 | L272: 55.162686 | M272: 2015 | N272: 17 | O272: 505 | P272: =O272*2.8 -> 1414 | Q272: 5 | R272: 0 | S272: 5 | T272: 5 | U272: 10 | V272: Вертикальный 4*3 | W272: Digital (без звука) | X272: видеоролик | Y272: 10 | Z272: 150 | AA272: 576 | AB272: 31 | AC272: =Q272*AA272*AB272 -> 89280 | AD272: =AE272/P272 -> 9.1346667 | AE272: =((P272*2.6*R272/S272/2)*30/Z272+(P272*2.6*T272/U272)*N272*2/Z272)*AB272 -> 12916.419 | AF272: =AL272/AE272*1000 -> 1548.4168 | AG272: 1 | AI272: =AJ272/1.22 -> 3278.6885 | AJ272: 4000 | AK272: =AI272*Q272 -> 16393.443 | AL272: =AK272*1.22 -> 20000
A273: OREN31 | B273: Оренбургская область | C273: Оренбург | D273: Ленинский | E273: мкрн. 13_15_16 | F273: Б | G273: 46162 | H273: Комфорт | I273: ЖК 15 Микрорайон | J273: улица Поляничко, 11/5 | K273: 51.822948 | L273: 55.177552 | M273: 2021 | N273: 17 | O273: 235 | P273: =O273*2.8 -> 658 | Q273: 6 | R273: 0 | S273: 3 | T273: 6 | U273: 6 | V273: Вертикальный 4*3 | W273: Digital (без звука) | X273: видеоролик | Y273: 10 | Z273: 150 | AA273: 576 | AB273: 31 | AC273: =Q273*AA273*AB273 -> 107136 | AD273: =AE273/P273 -> 18.269333 | AE273: =((P273*2.6*R273/S273/2)*30/Z273+(P273*2.6*T273/U273)*N273*2/Z273)*AB273 -> 12021.221 | AF273: =AL273/AE273*1000 -> 1996.4694 | AG273: 1 | AI273: =AJ273/1.22 -> 3278.6885 | AJ273: 4000 | AK273: =AI273*Q273 -> 19672.131 | AL273: =AK273*1.22 -> 24000
A274: OREN31 | B274: Оренбургская область | C274: Оренбург | D274: Ленинский | E274: мкрн. 13_15_16 | F274: Б | G274: 46162 | H274: Комфорт | I274: ЖК 15 Микрорайон | J274: Северный проезд, 22 | K274: 51.827050 | L274: 55.172315 | M274: 2018 | N274: 20 | O274: 162 | P274: =O274*2.8 -> 453.6 | Q274: 2 | R274: 0 | S274: 1 | T274: 2 | U274: 2 | V274: Вертикальный 4*3 | W274: Digital (без звука) | X274: видеоролик | Y274: 10 | Z274: 150 | AA274: 576 | AB274: 31 | AC274: =Q274*AA274*AB274 -> 35712 | AD274: =AE274/P274 -> 21.493333 | AE274: =((P274*2.6*R274/S274/2)*30/Z274+(P274*2.6*T274/U274)*N274*2/Z274)*AB274 -> 9749.376 | AF274: =AL274/AE274*1000 -> 820.56534 | AG274: 1 | AI274: =AJ274/1.22 -> 3278.6885 | AJ274: 4000 | AK274: =AI274*Q274 -> 6557.377 | AL274: =AK274*1.22 -> 8000
A275: OREN31 | B275: Оренбургская область | C275: Оренбург | D275: Ленинский | E275: мкрн. 13_15_16 | F275: Б | G275: 46162 | H275: Комфорт | I275: ЖК 15 Микрорайон | J275: улица Братьев Хусаиновых, 2/2 | K275: 51.826299 | L275: 55.173914 | M275: 2019 | N275: 18 | O275: 372 | P275: =O275*2.8 -> 1041.6 | Q275: 4 | R275: 0 | S275: 4 | T275: 4 | U275: 8 | V275: Вертикальный 4*3 | W275: Digital (без звука) | X275: видеоролик | Y275: 10 | Z275: 150 | AA275: 576 | AB275: 31 | AC275: =Q275*AA275*AB275 -> 71424 | AD275: =AE275/P275 -> 9.672 | AE275: =((P275*2.6*R275/S275/2)*30/Z275+(P275*2.6*T275/U275)*N275*2/Z275)*AB275 -> 10074.355 | AF275: =AL275/AE275*1000 -> 1588.191 | AG275: 1 | AI275: =AJ275/1.22 -> 3278.6885 | AJ275: 4000 | AK275: =AI275*Q275 -> 13114.754 | AL275: =AK275*1.22 -> 16000
A276: OREN31 | B276: Оренбургская область | C276: Оренбург | D276: Ленинский | E276: мкрн. 13_15_16 | F276: Б | G276: 46162 | H276: Комфорт | I276: ЖК 15 Микрорайон | J276: улица Братьев Хусаиновых, 2/2 | K276: 51.826299 | L276: 55.173914 | M276: 2019 | N276: 18 | O276: 372 | P276: =O276*2.8 -> 1041.6 | Q276: 4 | R276: 4 | S276: 4 | T276: 0 | U276: 8 | V276: Горизонтальный 4*3 | W276: Digital (без звука) | X276: видеоролик | Y276: 10 | Z276: 150 | AA276: 576 | AB276: 31 | AC276: =Q276*AA276*AB276 -> 71424 | AD276: =AE276/P276 -> 8.06 | AE276: =((P276*2.6*R276/S276/2)*30/Z276+(P276*2.6*T276/U276)*N276*2/Z276)*AB276 -> 8395.296 | AF276: =AL276/AE276*1000 -> 1905.8292 | AG276: 1 | AI276: =AJ276/1.22 -> 3278.6885 | AJ276: 4000 | AK276: =AI276*Q276 -> 13114.754 | AL276: =AK276*1.22 -> 16000
A277: OREN32 | B277: Оренбургская область | C277: Оренбург | D277: Ленинский | E277: мкрн. 18_19_20 | F277: Б | G277: 46167 | H277: Комфорт | I277: ЖК 18 микрорайон | J277: улица Диагностики, 17/1 | K277: 51.817770 | L277: 55.168012 | M277: 2007 | N277: 10 | O277: 460 | P277: =O277*2.8 -> 1288 | Q277: 10 | R277: 0 | S277: 10 | T277: 10 | U277: 10 | V277: Вертикальный 4*3 | W277: Digital (без звука) | X277: видеоролик | Y277: 10 | Z277: 150 | AA277: 576 | AB277: 31 | AC277: =Q277*AA277*AB277 -> 178560 | AD277: =AE277/P277 -> 10.746667 | AE277: =((P277*2.6*R277/S277/2)*30/Z277+(P277*2.6*T277/U277)*N277*2/Z277)*AB277 -> 13841.707 | AF277: =AL277/AE277*1000 -> 2889.8171 | AG277: 1 | AI277: =AJ277/1.22 -> 3278.6885 | AJ277: 4000 | AK277: =AI277*Q277 -> 32786.885 | AL277: =AK277*1.22 -> 40000
A278: OREN32 | B278: Оренбургская область | C278: Оренбург | D278: Ленинский | E278: мкрн. 18_19_20 | F278: Б | G278: 46167 | H278: Комфорт | I278: ЖК 18 микрорайон | J278: улица Салмышская улица, 58 | K278: 51.816579 | L278: 55.171282 | M278: 2007 | N278: 17 | O278: 190 | P278: =O278*2.8 -> 532 | Q278: 2 | R278: 0 | S278: 1 | T278: 10 | U278: 3 | V278: Вертикальный 4*3 | W278: Digital (без звука) | X278: видеоролик | Y278: 10 | Z278: 150 | AA278: 576 | AB278: 31 | AC278: =Q278*AA278*AB278 -> 35712 | AD278: =AE278/P278 -> 60.897778 | AE278: =((P278*2.6*R278/S278/2)*30/Z278+(P278*2.6*T278/U278)*N278*2/Z278)*AB278 -> 32397.618 | AF278: =AL278/AE278*1000 -> 246.93174 | AG278: 1 | AI278: =AJ278/1.22 -> 3278.6885 | AJ278: 4000 | AK278: =AI278*Q278 -> 6557.377 | AL278: =AK278*1.22 -> 8000
A279: OREN33 | B279: Оренбургская область | C279: Оренбург | D279: Ленинский | E279: мкрн. 18_19_20 | F279: А | G279: 46167 | H279: Комфорт | I279: ЖК Долгие горы | J279: улица Гаранькина, 26 | K279: 51.807915 | L279: 55.179052 | M279: 2026 | N279: 17 | O279: 192 | P279: =O279*2.8 -> 537.6 | Q279: 6 | R279: 3 | S279: 4 | T279: 3 | U279: 8 | V279: Вертикальный 4*3 | W279: Digital (без звука) | X279: видеоролик | Y279: 10 | Z279: 150 | AA279: 576 | AB279: 31 | AC279: =Q279*AA279*AB279 -> 107136 | AD279: =AE279/P279 -> 12.896 | AE279: =((P279*2.6*R279/S279/2)*30/Z279+(P279*2.6*T279/U279)*N279*2/Z279)*AB279 -> 6932.8896 | AF279: =AL279/AE279*1000 -> 3461.76 | AG279: 1 | AI279: =AJ279/1.22 -> 3278.6885 | AJ279: 4000 | AK279: =AI279*Q279 -> 19672.131 | AL279: =AK279*1.22 -> 24000
A280: OREN34 | B280: Оренбургская область | C280: Оренбург | D280: Ленинский | E280: мкрн. 18_19_20 | F280: Б | G280: 46167 | H280: Комфорт | I280: ЖК Фермер | J280: улица Высотная, 2 | K280: 51.815822 | L280: 55.176573 | M280: 2016 | N280: 16 | O280: 240 | P280: =O280*2.8 -> 672 | Q280: 4 | R280: 0 | S280: 4 | T280: 4 | U280: 8 | V280: Вертикальный 4*3 | W280: Digital (без звука) | X280: видеоролик | Y280: 10 | Z280: 150 | AA280: 576 | AB280: 31 | AC280: =Q280*AA280*AB280 -> 71424 | AD280: =AE280/P280 -> 8.5973333 | AE280: =((P280*2.6*R280/S280/2)*30/Z280+(P280*2.6*T280/U280)*N280*2/Z280)*AB280 -> 5777.408 | AF280: =AL280/AE280*1000 -> 2769.408 | AG280: 1 | AI280: =AJ280/1.22 -> 3278.6885 | AJ280: 4000 | AK280: =AI280*Q280 -> 13114.754 | AL280: =AK280*1.22 -> 16000
A281: OREN34 | B281: Оренбургская область | C281: Оренбург | D281: Ленинский | E281: мкрн. 18_19_20 | F281: Б | G281: 46167 | H281: Комфорт | I281: ЖК Фермер | J281: улица Высотная, 2 | K281: 51.815822 | L281: 55.176574 | M281: 2016 | N281: 16 | O281: 240 | P281: =O281*2.8 -> 672 | Q281: 4 | R281: 4 | S281: 4 | T281: 0 | U281: 8 | V281: Горизонтальный 4*3 | W281: Digital (без звука) | X281: видеоролик | Y281: 10 | Z281: 150 | AA281: 576 | AB281: 31 | AC281: =Q281*AA281*AB281 -> 71424 | AD281: =AE281/P281 -> 8.06 | AE281: =((P281*2.6*R281/S281/2)*30/Z281+(P281*2.6*T281/U281)*N281*2/Z281)*AB281 -> 5416.32 | AF281: =AL281/AE281*1000 -> 2954.0352 | AG281: 1 | AI281: =AJ281/1.22 -> 3278.6885 | AJ281: 4000 | AK281: =AI281*Q281 -> 13114.754 | AL281: =AK281*1.22 -> 16000
... A284: OREN35 | B284: Оренбургская область | C284: Оренбург | D284: Ленинский | E284: мкрн. 18_19_20 | F284: А | G284: 46175 | H284: Комфорт | I284: ЖК Диагностики | J284: улица Салмышская, 52/3 | K284: 51.819140 | L284: 55.167716 | M284: 2017 | N284: 14 | O284: 65 | P284: =O284*2.8 -> 182 | Q284: 2 | R284: 1 | S284: 1 | T284: 1 | U284: 2 | V284: Вертикальный 4*3 | W284: Digital (без звука) | X284: видеоролик | Y284: 10 | Z284: 150 | AA284: 576 | AB284: 31 | AC284: =Q284*AA284*AB284 -> 35712 | AD284: =AE284/P284 -> 15.582667 | AE284: =((P284*2.6*R284/S284/2)*30/Z284+(P284*2.6*T284/U284)*N284*2/Z284)*AB284 -> 2836.0453 | AF284: =AL284/AE284*1000 -> 2820.8294 | AG284: 1 | AI284: =AJ284/1.22 -> 3278.6885 | AJ284: 4000 | AK284: =AI284*Q284 -> 6557.377 | AL284: =AK284*1.22 -> 8000
A285: OREN35 | B285: Оренбургская область | C285: Оренбург | D285: Ленинский | F285: А | G285: 46255 | H285: Комфорт | I285: ЖК Диагностики | J285: улица Салмышская, 56А | K285: 51.816679 | L285: 55.172315 | M285: 2017 | N285: 10 | O285: 40 | P285: =O285*2.8 -> 112 | Q285: 2 | R285: 1 | S285: 1 | T285: 1 | U285: 2 | V285: Вертикальный 4*3 | W285: Digital (без звука) | X285: видеоролик | Y285: 10 | Z285: 150 | AA285: 576 | AB285: 31 | AC285: =Q285*AA285*AB285 -> 35712 | AD285: =AE285/P285 -> 13.433333 | AE285: =((P285*2.6*R285/S285/2)*30/Z285+(P285*2.6*T285/U285)*N285*2/Z285)*AB285 -> 1504.5333 | AF285: =AL285/AE285*1000 -> 5317.2634 | AG285: 1 | AI285: =AJ285/1.22 -> 3278.6885 | AJ285: 4000 | AK285: =AI285*Q285 -> 6557.377 | AL285: =AK285*1.22 -> 8000
A286: OREN36 | B286: Оренбургская область | C286: Оренбург | D286: Ленинский | E286: мкрн. Дубки | F286: Б | G286: 46190 | H286: Комфорт | I286: ЖК Чкалова | J286: улица Чкалова, 51/1 | K286: 51.769944 | L286: 55.135017 | M286: 2014 | N286: 20 | O286: 401 | P286: =O286*2.8 -> 1122.8 | Q286: 12 | R286: 6 | S286: 6 | T286: 6 | U286: 12 | V286: Вертикальный 4*3 | W286: Digital (без звука) | X286: видеоролик | Y286: 10 | Z286: 150 | AA286: 576 | AB286: 31 | AC286: =Q286*AA286*AB286 -> 214272 | AD286: =AE286/P286 -> 18.806667 | AE286: =((P286*2.6*R286/S286/2)*30/Z286+(P286*2.6*T286/U286)*N286*2/Z286)*AB286 -> 21116.125 | AF286: =AL286/AE286*1000 -> 2273.1443 | AG286: 1 | AI286: =AJ286/1.22 -> 3278.6885 | AJ286: 4000 | AK286: =AI286*Q286 -> 39344.262 | AL286: =AK286*1.22 -> 48000
A287: OREN36 | B287: Оренбургская область | C287: Оренбург | D287: Ленинский | E287: мкрн. Дубки | F287: Б | G287: 46190 | H287: Комфорт | I287: ЖК Чкалова | J287: улица Чкалова, 53/3 | K287: 51.771203 | L287: 55.138421 | M287: 2017 | N287: 15 | O287: 120 | P287: =O287*2.8 -> 336 | Q287: 2 | R287: 1 | S287: 1 | T287: 1 | U287: 2 | V287: Вертикальный 4*3 | W287: Digital (без звука) | X287: видеоролик | Y287: 10 | Z287: 150 | AA287: 576 | AB287: 31 | AC287: =Q287*AA287*AB287 -> 35712 | AD287: =AE287/P287 -> 16.12 | AE287: =((P287*2.6*R287/S287/2)*30/Z287+(P287*2.6*T287/U287)*N287*2/Z287)*AB287 -> 5416.32 | AF287: =AL287/AE287*1000 -> 1477.0176 | AG287: 1 | AI287: =AJ287/1.22 -> 3278.6885 | AJ287: 4000 | AK287: =AI287*Q287 -> 6557.377 | AL287: =AK287*1.22 -> 8000
A288: OREN37 | B288: Оренбургская область | C288: Оренбург | D288: Ленинский | E288: мкрн. 13_15_16 | F288: Б | G288: 46190 | H288: Комфорт | I288: ЖК Северный проезд | J288: Северный проезд, 24 | K288: 51.827445 | L288: 55.173078 | M288: 2019 | N288: 14 | O288: 182 | P288: =O288*2.8 -> 509.6 | Q288: 4 | R288: 2 | S288: 2 | T288: 2 | U288: 4 | V288: Вертикальный 4*3 | W288: Digital (без звука) | X288: видеоролик | Y288: 10 | Z288: 150 | AA288: 576 | AB288: 31 | AC288: =Q288*AA288*AB288 -> 71424 | AD288: =AE288/P288 -> 15.582667 | AE288: =((P288*2.6*R288/S288/2)*30/Z288+(P288*2.6*T288/U288)*N288*2/Z288)*AB288 -> 7940.9269 | AF288: =AL288/AE288*1000 -> 2014.8781 | AG288: 1 | AI288: =AJ288/1.22 -> 3278.6885 | AJ288: 4000 | AK288: =AI288*Q288 -> 13114.754 | AL288: =AK288*1.22 -> 16000
...

Sheet Генеральный баннер
D1: Прайс на размещение рекламного баннера
A2: GID | B2: Регион | C2: Город | D2: Район | E2: Название пакета | F2: Категория ЖК | G2: Дата застройки экранов | H2: Класс жилья | I2: Наименование ЖК | J2: Адрес | K2: Коррдинаты (широта, долгота) | M2: Год сдачи дома | N2: Этажность | O2: Количество квартир | P2: Количество жильцов | Q2: Всего экранов | R2: Число экранов в холле | S2: Всего холлов в доме | T2: Число экранов в лифте | U2: Всего лифтов в доме | V2: Тип экрана | W2: Способ показа | X2: Формат | Y2: Период/дней | Z2: Частота контакта рекламы c 1 жителем (Frequency) | AA2: Количество контактов с рекламой (OTS) | AB2: Стоимость 1000 контактов (CPT) с НДС для Федерального и крупного бизнеса | AC2: ФО/скрин с камеры | AD2: Фото | AE2: Цена за размещение на 1 экране/месяц руб. без НДС | AF2: Цена за размещение на 1 экране/месяц руб. в т.ч НДС 22% | AG2: Стоимость размещения в 1 доме/1 месяц, руб. без НДС | AH2: Стоимость размещения в 1 доме/1 месяц, руб. в т.ч.НДС 22%
A3: U1 | B3: Республика Башкортостан | C3: Уфа | D3: Ленинский | E3: Проспект | F3: А | G3: 45839 | H3: Бизнес | I3: ЖК Видинеевский | J3: улица Пархоменко, 156Б | K3: 54.743697 | L3: 55.969246 | M3: 2021 | N3: 14 | O3: 412 | P3: =O3*2.8 -> 1153.6 | Q3: 2 | R3: 1 | S3: 3 | T3: 1 | U3: 6 | V3: Горизонтальный 4*3 | W3: Digital (без звука) | X3: статичный баннер | Y3: 31 | Z3: =AA3/P3 -> 13.433333 | AA3: =((P3*2.6*R3/S3/2)/2+(P3*2.6*T3/U3)/2)*Y3 -> 15496.693 | AB3: =AH3/AA3*1000 -> 1032.4783 | AC3: 1 | AE3: =AF3/1.22 -> 6557.377 | AF3: 8000 | AG3: =AE3*Q3 -> 13114.754 | AH3: =AG3*1.22 -> 16000
A4: U1 | B4: Республика Башкортостан | C4: Уфа | D4: Ленинский | E4: Проспект | F4: А | G4: 45839 | H4: Бизнес | I4: ЖК Видинеевский | J4: улица Пархоменко, 156В | K4: 54.744659 | L4: 55.969713 | M4: 2019 | N4: 26 | O4: 232 | P4: =O4*2.8 -> 649.6 | Q4: 2 | R4: 1 | S4: 1 | T4: 1 | U4: 3 | V4: Горизонтальный 4*3 | W4: Digital (без звука) | X4: статичный баннер | Y4: 31 | Z4: =AA4/P4 -> 33.583333 | AA4: =((P4*2.6*R4/S4/2)/2+(P4*2.6*T4/U4)/2)*Y4 -> 21815.733 | AB4: =AH4/AA4*1000 -> 733.41564 | AC4: 1 | AE4: =AF4/1.22 -> 6557.377 | AF4: 8000 | AG4: =AE4*Q4 -> 13114.754 | AH4: =AG4*1.22 -> 16000
A5: U1 | B5: Республика Башкортостан | C5: Уфа | D5: Ленинский | E5: Проспект | F5: А | G5: 45839 | H5: Бизнес | I5: ЖК Видинеевский | J5: улица Пархоменко, 156Г | K5: 54.744939 | L5: 55.970603 | M5: 2023 | N5: 25 | O5: 173 | P5: =O5*2.8 -> 484.4 | Q5: 1 | R5: 0 | S5: 1 | T5: 1 | U5: 3 | V5: Горизонтальный 4*3 | W5: Digital (без звука) | X5: статичный баннер | Y5: 31 | Z5: =AA5/P5 -> 13.433333 | AA5: =((P5*2.6*R5/S5/2)/2+(P5*2.6*T5/U5)/2)*Y5 -> 6507.1067 | AB5: =AH5/AA5*1000 -> 1229.4251 | AC5: 1 | AE5: =AF5/1.22 -> 6557.377 | AF5: 8000 | AG5: =AE5*Q5 -> 6557.377 | AH5: =AG5*1.22 -> 8000
A6: U1 | B6: Республика Башкортостан | C6: Уфа | D6: Ленинский | E6: Проспект | F6: А | G6: 45839 | H6: Бизнес | I6: ЖК Видинеевский | J6: лица Пархоменко, 156Е | K6: 54.744482 | L6: 55.972408 | M6: 2025 | N6: 26 | O6: 233 | P6: =O6*2.8 -> 652.4 | Q6: 3 | R6: 0 | S6: 1 | T6: 3 | U6: 3 | V6: Горизонтальный 4*3 | W6: Digital (без звука) | X6: статичный баннер | Y6: 31 | Z6: =AA6/P6 -> 40.3 | AA6: =((P6*2.6*R6/S6/2)/2+(P6*2.6*T6/U6)/2)*Y6 -> 26291.72 | AB6: =AH6/AA6*1000 -> 912.83492 | AC6: 1 | AE6: =AF6/1.22 -> 6557.377 | AF6: 8000 | AG6: =AE6*Q6 -> 19672.131 | AH6: =AG6*1.22 -> 24000
A7: U1 | B7: Республика Башкортостан | C7: Уфа | D7: Ленинский | E7: Проспект | F7: А | G7: 45839 | H7: Бизнес | I7: ЖК Видинеевский | J7: улица Пархоменко, 156Ж | K7: 54.743999 | L7: 55.972094 | M7: 2024 | N7: 15 | O7: 289 | P7: =O7*2.8 -> 809.2 | Q7: 4 | R7: 2 | S7: 1 | T7: 2 | U7: 4 | V7: Горизонтальный 4*3 | W7: Digital (без звука) | X7: статичный баннер | Y7: 31 | Z7: =AA7/P7 -> 60.45 | AA7: =((P7*2.6*R7/S7/2)/2+(P7*2.6*T7/U7)/2)*Y7 -> 48916.14 | AB7: =AH7/AA7*1000 -> 654.18081 | AC7: 1 | AE7: =AF7/1.22 -> 6557.377 | AF7: 8000 | AG7: =AE7*Q7 -> 26229.508 | AH7: =AG7*1.22 -> 32000
A8: U2 | B8: Республика Башкортостан | C8: Уфа | D8: Кировский | E8: Зеленая Роща 2 | F8: Б | G8: 45985 | H8: Комфорт | I8: ЖК Южный | J8: улица Генерала Рыленко, 8 | K8: 54.695476 | L8: 55.989638 | M8: 2021 | N8: 28 | O8: 301 | P8: =O8*2.8 -> 842.8 | Q8: 3 | R8: 1 | S8: 1 | T8: 2 | U8: 4 | V8: Горизонтальный 4*3 | W8: Digital (без звука) | X8: статичный баннер | Y8: 31 | Z8: =AA8/P8 -> 40.3 | AA8: =((P8*2.6*R8/S8/2)/2+(P8*2.6*T8/U8)/2)*Y8 -> 33964.84 | AB8: =AH8/AA8*1000 -> 706.61307 | AC8: 1 | AE8: =AF8/1.22 -> 6557.377 | AF8: 8000 | AG8: =AE8*Q8 -> 19672.131 | AH8: =AG8*1.22 -> 24000
A9: U3 | B9: Республика Башкортостан | C9: Уфа | D9: Кировский | E9: Центр | F9: А | G9: 45950 | H9: Бизнес | I9: ЖК Выбор первых | J9: улица Айская, 61 | K9: 54.727375 | L9: 55.976172 | M9: 2024 | N9: 10 | O9: 329 | P9: =O9*2.8 -> 921.2 | Q9: 5 | R9: 0 | S9: 5 | T9: 5 | U9: 5 | V9: Горизонтальный 4*3 | W9: Digital (без звука) | X9: статичный баннер | Y9: 31 | Z9: =AA9/P9 -> 40.3 | AA9: =((P9*2.6*R9/S9/2)/2+(P9*2.6*T9/U9)/2)*Y9 -> 37124.36 | AB9: =AH9/AA9*1000 -> 1077.4597 | AC9: 1 | AE9: =AF9/1.22 -> 6557.377 | AF9: 8000 | AG9: =AE9*Q9 -> 32786.885 | AH9: =AG9*1.22 -> 40000
A10: U4 | B10: Республика Башкортостан | C10: Уфа | D10: Калининский | E10: Инорс_Сипайлово | F10: Б | G10: 45961 | H10: Стандарт | I10: ЖК Акварель | J10: улица Лётчика Кобелева, 1 | K10: 54.778409 | L10: 56.137887 | M10: 2023 | N10: 19 | O10: 102 | P10: =O10*2.8 -> 285.6 | Q10: 1 | R10: 1 | S10: 8 | T10: 0 | U10: 16 | V10: Горизонтальный 4*3 | W10: Digital (без звука) | X10: статичный баннер | Y10: 31 | Z10: =AA10/P10 -> 2.51875 | AA10: =((P10*2.6*R10/S10/2)/2+(P10*2.6*T10/U10)/2)*Y10 -> 719.355 | AB10: =AH10/AA10*1000 -> 11121.074 | AC10: 1 | AE10: =AF10/1.22 -> 6557.377 | AF10: 8000 | AG10: =AE10*Q10 -> 6557.377 | AH10: =AG10*1.22 -> 8000
A11: U4 | B11: Республика Башкортостан | C11: Уфа | D11: Калининский | E11: Инорс_Сипайлово | F11: Б | G11: 45961 | H11: Стандарт | I11: ЖК Акварель | J11: улица Лётчика Кобелева, 3/3 | K11: 54.778180 | L11: 56.134411 | M11: 2018 | N11: 27 | O11: 338 | P11: =O11*2.8 -> 946.4 | Q11: 1 | R11: 1 | S11: 1 | T11: 0 | U11: 3 | V11: Горизонтальный 4*3 | W11: Digital (без звука) | X11: статичный баннер | Y11: 31 | Z11: =AA11/P11 -> 20.15 | AA11: =((P11*2.6*R11/S11/2)/2+(P11*2.6*T11/U11)/2)*Y11 -> 19069.96 | AB11: =AH11/AA11*1000 -> 419.50796 | AC11: 1 | AE11: =AF11/1.22 -> 6557.377 | AF11: 8000 | AG11: =AE11*Q11 -> 6557.377 | AH11: =AG11*1.22 -> 8000
A12: U4 | B12: Республика Башкортостан | C12: Уфа | D12: Калининский | E12: Инорс_Сипайлово | F12: Б | G12: 45961 | H12: Стандарт | I12: ЖК Акварель | J12: улица Ферина, 33 | K12: 54.777126 | L12: 56.132030 | M12: 2017 | N12: 18 | O12: 187 | P12: =O12*2.8 -> 523.6 | Q12: 2 | R12: 0 | S12: 2 | T12: 2 | U12: 4 | V12: Вертикальный 4*3 | W12: Digital (без звука) | X12: статичный баннер | Y12: 31 | Z12: =AA12/P12 -> 20.15 | AA12: =((P12*2.6*R12/S12/2)/2+(P12*2.6*T12/U12)/2)*Y12 -> 10550.54 | AB12: =AH12/AA12*1000 -> 1516.5101 | AC12: 1 | AE12: =AF12/1.22 -> 6557.377 | AF12: 8000 | AG12: =AE12*Q12 -> 13114.754 | AH12: =AG12*1.22 -> 16000
A13: U5 | B13: Республика Башкортостан | C13: Уфа | D13: Ленинский | E13: Центр | F13: Б | G13: 45961 | H13: Бизнес | I13: ЖК Старый центр | J13: улица Чернышевского, 26 | K13: 54.731545 | L13: 55.928831 | M13: 2023 | N13: 19 | O13: 321 | P13: =O13*2.8 -> 898.8 | Q13: 2 | R13: 2 | S13: 2 | T13: 0 | U13: 4 | V13: Горизонтальный 4*3 | W13: Digital (без звука) | X13: статичный баннер | Y13: 31 | Z13: =AA13/P13 -> 20.15 | AA13: =((P13*2.6*R13/S13/2)/2+(P13*2.6*T13/U13)/2)*Y13 -> 18110.82 | AB13: =AH13/AA13*1000 -> 883.44978 | AC13: 1 | AE13: =AF13/1.22 -> 6557.377 | AF13: 8000 | AG13: =AE13*Q13 -> 13114.754 | AH13: =AG13*1.22 -> 16000
A14: U5 | B14: Республика Башкортостан | C14: Уфа | D14: Ленинский | E14: Центр | F14: Б | G14: 45961 | H14: Бизнес | I14: ЖК Старый центр | J14: улица Коммунистическая, 15 | K14: 54.729512 | L14: 55.929083 | M14: 2020 | N14: 15 | O14: 151 | P14: =O14*2.8 -> 422.8 | Q14: 2 | R14: 2 | S14: 2 | T14: 0 | U14: 4 | V14: Горизонтальный 4*3 | W14: Digital (без звука) | X14: статичный баннер | Y14: 31 | Z14: =AA14/P14 -> 20.15 | AA14: =((P14*2.6*R14/S14/2)/2+(P14*2.6*T14/U14)/2)*Y14 -> 8519.42 | AB14: =AH14/AA14*1000 -> 1878.0621 | AC14: 1 | AE14: =AF14/1.22 -> 6557.377 | AF14: 8000 | AG14: =AE14*Q14 -> 13114.754 | AH14: =AG14*1.22 -> 16000
... A131: U79 | B131: Республика Башкортостан | C131: Уфа | D131: Кировский | E131: Зеленая Роща 2 | F131: А | G131: 46171 | H131: Комфорт | I131: квартал Кузнецовский затон | J131: улица Просвещения, 11/1 | K131: 54.689997 | L131: 55.972204 | M131: 2019 | N131: 11 | O131: 70 | P131: =O131*2.8 -> 196 | Q131: 1 | R131: 0 | S131: 1 | T131: 1 | U131: 1 | V131: Вертикальный 4*3 | W131: Digital (без звука) | X131: статичный баннер | Y131: 31 | Z131: =AA131/P131 -> 40.3 | AA131: =((P131*2.6*R131/S131/2)/2+(P131*2.6*T131/U131)/2)*Y131 -> 7898.8 | AB131: =AH131/AA131*1000 -> 1012.8121 | AC131: 1 | AE131: =AF131/1.22 -> 6557.377 | AF131: 8000 | AG131: =AE131*Q131 -> 6557.377 | AH131: =AG131*1.22 -> 8000
A132: U79 | B132: Республика Башкортостан | C132: Уфа | D132: Кировский | E132: Зеленая Роща 2 | F132: А | G132: 46244 | H132: Комфорт | I132: квартал Кузнецовский затон | J132: улица Бородинская, 20/1 | K132: 54.686208, 55.984572 | M132: 2023 | N132: 12 | O132: 158 | P132: =O132*2.8 -> 442.4 | Q132: 2 | R132: 0 | S132: 1 | T132: 2 | U132: 2 | V132: Вертикальный 4*3 | W132: Digital (без звука) | X132: статичный баннер | Y132: 31 | Z132: =AA132/P132 -> 40.3 | AA132: =((P132*2.6*R132/S132/2)/2+(P132*2.6*T132/U132)/2)*Y132 -> 17828.72 | AB132: =AH132/AA132*1000 -> 897.42842 | AC132: 1 | AE132: =AF132/1.22 -> 6557.377 | AF132: 8000 | AG132: =AE132*Q132 -> 13114.754 | AH132: =AG132*1.22 -> 16000
A133: U80 | B133: Республика Башкортостан | C133: Уфа | D133: Ленинский | E133: Ленинский 1 Затон_мкрн. 8 Марта | F133: А | G133: 46183 | H133: Стандарт | I133: Квартал Летчиков | J133: улица Летчиков, 16/1 | K133: 54.795296 | L133: 55.867126 | M133: 2014 | N133: 18 | O133: 90 | P133: =O133*2.8 -> 252 | Q133: 2 | R133: 0 | S133: 1 | T133: 2 | U133: 2 | V133: Вертикальный 4*3 | W133: Digital (без звука) | X133: статичный баннер | Y133: 31 | Z133: =AA133/P133 -> 40.3 | AA133: =((P133*2.6*R133/S133/2)/2+(P133*2.6*T133/U133)/2)*Y133 -> 10155.6 | AB133: =AH133/AA133*1000 -> 1575.4854 | AC133: 1 | AE133: =AF133/1.22 -> 6557.377 | AF133: 8000 | AG133: =AE133*Q133 -> 13114.754 | AH133: =AG133*1.22 -> 16000
A134: U80 | B134: Республика Башкортостан | C134: Уфа | D134: Ленинский | E134: Ленинский 1 Затон_мкрн. 8 Марта | F134: А | G134: 46183 | H134: Стандарт | I134: Квартал Летчиков | J134: улица Летчиков, 18 | K134: 54.79523 | L134: 55.868527 | M134: 2013 | N134: 14 | O134: 154 | P134: =O134*2.8 -> 431.2 | Q134: 3 | R134: 0 | S134: 3 | T134: 3 | U134: 6 | V134: Вертикальный 4*3 | W134: Digital (без звука) | X134: статичный баннер | Y134: 31 | Z134: =AA134/P134 -> 20.15 | AA134: =((P134*2.6*R134/S134/2)/2+(P134*2.6*T134/U134)/2)*Y134 -> 8688.68 | AB134: =AH134/AA134*1000 -> 2762.2147 | AC134: 1 | AE134: =AF134/1.22 -> 6557.377 | AF134: 8000 | AG134: =AE134*Q134 -> 19672.131 | AH134: =AG134*1.22 -> 24000
A135: U81 | B135: Республика Башкортостан | C135: Уфа | D135: Октябрьский | E135: Инорс_Сипайлово | F135: А | G135: 46168 | H135: Комфорт | I135: Квартал Олимп | J135: улица Маршала Жукова, 4/4 | K135: 54.765952 | L135: 56.051225 | M135: 2002 | N135: 10 | O135: 150 | P135: =O135*2.8 -> 420 | Q135: 3 | R135: 0 | S135: 3 | T135: 3 | U135: 3 | V135: Вертикальный 4*3 | W135: Digital (без звука) | X135: статичный баннер | Y135: 31 | Z135: =AA135/P135 -> 40.3 | AA135: =((P135*2.6*R135/S135/2)/2+(P135*2.6*T135/U135)/2)*Y135 -> 16926 | AB135: =AH135/AA135*1000 -> 1417.9369 | AC135: 1 | AE135: =AF135/1.22 -> 6557.377 | AF135: 8000 | AG135: =AE135*Q135 -> 19672.131 | AH135: =AG135*1.22 -> 24000
A136: U82 | B136: Республика Башкортостан | C136: Уфа | D136: Октябрьский | E136: Инорс_Сипайлово | F136: А | G136: 46196 | H136: Комфорт | I136: Квартал Олимп 2 | J136: улица Маршала Жукова, 4/1 | K136: 54.767256 | L136: 56.053738 | M136: 1995 | N136: 10 | O136: 290 | P136: =O136*2.8 -> 812 | Q136: 8 | R136: 0 | S136: 8 | T136: 8 | U136: 8 | V136: Вертикальный 4*3 | W136: Digital (без звука) | X136: статичный баннер | Y136: 31 | Z136: =AA136/P136 -> 40.3 | AA136: =((P136*2.6*R136/S136/2)/2+(P136*2.6*T136/U136)/2)*Y136 -> 32723.6 | AB136: =AH136/AA136*1000 -> 1955.775 | AC136: 1 | AE136: =AF136/1.22 -> 6557.377 | AF136: 8000 | AG136: =AE136*Q136 -> 52459.016 | AH136: =AG136*1.22 -> 64000
A137: U83 | B137: Республика Башкортостан | C137: Уфа | D137: Октябрьский | E137: Инорс_Сипайлово | F137: А | G137: 46186 | H137: Комфорт | I137: Квартал Олимп 3 | J137: улица Юрия Гагарина, 10/2 | K137: 54.763763 | L137: 56.050715 | M137: 2001 | N137: 9 | O137: 207 | P137: =O137*2.8 -> 579.6 | Q137: 7 | R137: 0 | S137: 7 | T137: 7 | U137: 7 | V137: Вертикальный 4*3 | W137: Digital (без звука) | X137: статичный баннер | Y137: 31 | Z137: =AA137/P137 -> 40.3 | AA137: =((P137*2.6*R137/S137/2)/2+(P137*2.6*T137/U137)/2)*Y137 -> 23357.88 | AB137: =AH137/AA137*1000 -> 2397.4779 | AC137: 1 | AE137: =AF137/1.22 -> 6557.377 | AF137: 8000 | AG137: =AE137*Q137 -> 45901.639 | AH137: =AG137*1.22 -> 56000
A138: U84 | B138: Республика Башкортостан | C138: Уфа | D138: Октябрьский | E138: Инорс_Сипайлово | F138: Б | G138: 46188 | H138: Комфорт | I138: Квартал Маяк | J138: улица Маршала Жукова, 3/2 | K138: 54.766198 | L138: 56.047695 | M138: 2007 | N138: 18 | O138: 80 | P138: =O138*2.8 -> 224 | Q138: 2 | R138: 0 | S138: 1 | T138: 2 | U138: 2 | V138: Вертикальный 4*3 | W138: Digital (без звука) | X138: статичный баннер | Y138: 31 | Z138: =AA138/P138 -> 40.3 | AA138: =((P138*2.6*R138/S138/2)/2+(P138*2.6*T138/U138)/2)*Y138 -> 9027.2 | AB138: =AH138/AA138*1000 -> 1772.4211 | AC138: 1 | AE138: =AF138/1.22 -> 6557.377 | AF138: 8000 | AG138: =AE138*Q138 -> 13114.754 | AH138: =AG138*1.22 -> 16000
A139: U85 | B139: Республика Башкортостан | C139: Уфа | D139: Кировский | E139: Зеленая Роща 2 | F139: Б | G139: 46191 | H139: Комфорт | I139: ЖК Южный 2 | J139: улица Загира Исмагилова, 16/1 | K139: 54.698573 | L139: 55.982071 | M139: 2009 | N139: 9 | O139: 71 | P139: =O139*2.8 -> 198.8 | Q139: 2 | R139: 0 | S139: 2 | T139: 2 | U139: 2 | V139: Вертикальный 4*3 | W139: Digital (без звука) | X139: статичный баннер | Y139: 31 | Z139: =AA139/P139 -> 40.3 | AA139: =((P139*2.6*R139/S139/2)/2+(P139*2.6*T139/U139)/2)*Y139 -> 8011.64 | AB139: =AH139/AA139*1000 -> 1997.0942 | AC139: 1 | AE139: =AF139/1.22 -> 6557.377 | AF139: 8000 | AG139: =AE139*Q139 -> 13114.754 | AH139: =AG139*1.22 -> 16000
A140: U85 | B140: Республика Башкортостан | C140: Уфа | D140: Кировский | E140: Зеленая Роща 2 | F140: Б | G140: 46191 | H140: Комфорт | I140: ЖК Южный 2 | J140: улица Загира Исмагилова, д. 18 | K140: 54.698718 | L140: 55.980256 | M140: 2012 | N140: 13 | O140: 148 | P140: =O140*2.8 -> 414.4 | Q140: 2 | R140: 0 | S140: 2 | T140: 2 | U140: 4 | V140: Вертикальный 4*3 | W140: Digital (без звука) | X140: статичный баннер | Y140: 31 | Z140: =AA140/P140 -> 20.15 | AA140: =((P140*2.6*R140/S140/2)/2+(P140*2.6*T140/U140)/2)*Y140 -> 8350.16 | AB140: =AH140/AA140*1000 -> 1916.1309 | AC140: 1 | AE140: =AF140/1.22 -> 6557.377 | AF140: 8000 | AG140: =AE140*Q140 -> 13114.754 | AH140: =AG140*1.22 -> 16000
A141: U86 | B141: Республика Башкортостан | C141: Уфа | D141: Дёмский | E141: Дёмский_мкрн. Цветы Башкирии | F141: А | G141: 46191 | H141: Комфорт | I141: ЖК Яркий Квартал Париж 1 | J141: Яркий бульвар, 10 | K141: 54.695817 | L141: 55.859804 | M141: 2022 | N141: 19 | O141: 204 | P141: =O141*2.8 -> 571.2 | Q141: 3 | R141: 0 | S141: 1 | T141: 3 | U141: 3 | V141: Вертикальный 4*3 | W141: Digital (без звука) | X141: статичный баннер | Y141: 31 | Z141: =AA141/P141 -> 40.3 | AA141: =((P141*2.6*R141/S141/2)/2+(P141*2.6*T141/U141)/2)*Y141 -> 23019.36 | AB141: =AH141/AA141*1000 -> 1042.6007 | AC141: 1 | AE141: =AF141/1.22 -> 6557.377 | AF141: 8000 | AG141: =AE141*Q141 -> 19672.131 | AH141: =AG141*1.22 -> 24000
A142: U87 | B142: Республика Башкортостан | C142: Уфа | D142: Дёмский | E142: Дёмский_мкрн. Цветы Башкирии | F142: А | G142: 46217 | H142: Комфорт | I142: ЖК Яркий Квартал Париж 2 | J142: улица Евгения Столярова, 13 | K142: 54.695185 | L142: 55.857586 | M142: 2025 | N142: 26 | O142: 288 | P142: =O142*2.8 -> 806.4 | Q142: 3 | R142: 0 | S142: 1 | T142: 3 | U142: 4 | V142: Вертикальный 4*3 | W142: Digital (без звука) | X142: статичный баннер | Y142: 31 | Z142: =AA142/P142 -> 30.225 | AA142: =((P142*2.6*R142/S142/2)/2+(P142*2.6*T142/U142)/2)*Y142 -> 24373.44 | AB142: =AH142/AA142*1000 -> 984.6784 | AC142: 1 | AE142: =AF142/1.22 -> 6557.377 | AF142: 8000 | AG142: =AE142*Q142 -> 19672.131 | AH142: =AG142*1.22 -> 24000
A143: U88 | B143: Республика Башкортостан | C143: Уфа | D143: Дёмский | E143: Дёмский_мкрн. Цветы Башкирии | F143: А | G143: 46217 | H143: Комфорт | I143: ЖК Яркий Квартал Париж 3 | J143: улица Архитектора Калимуллина, 12 | K143: 54.694867 | L143: 55.859257 | M143: 2025 | N143: 26 | O143: 288 | P143: =O143*2.8 -> 806.4 | Q143: 3 | R143: 0 | S143: 1 | T143: 3 | U143: 4 | V143: Вертикальный 4*3 | W143: Digital (без звука) | X143: статичный баннер | Y143: 31 | Z143: =AA143/P143 -> 30.225 | AA143: =((P143*2.6*R143/S143/2)/2+(P143*2.6*T143/U143)/2)*Y143 -> 24373.44 | AB143: =AH143/AA143*1000 -> 984.6784 | AC143: 1 | AE143: =AF143/1.22 -> 6557.377 | AF143: 8000 | AG143: =AE143*Q143 -> 19672.131 | AH143: =AG143*1.22 -> 24000
A144: U89 | B144: Республика Башкортостан | C144: Уфа | D144: Дёмский | E144: Дёмский_мкрн. Цветы Башкирии | F144: А | G144: 46202 | H144: Стандарт | I144: ЖК Новая Дёма | J144: улица Генерала Кусимова, 20 | K144: 54.717392 | L144: 55.842467 | M144: 2025 | N144: 19 | O144: 808 | P144: =O144*2.8 -> 2262.4 | Q144: 8 | R144: 0 | S144: 8 | T144: 8 | U144: 16 | V144: Вертикальный 4*3 | W144: Digital (без звука) | X144: статичный баннер | Y144: 31 | Z144: =AA144/P144 -> 20.15 | AA144: =((P144*2.6*R144/S144/2)/2+(P144*2.6*T144/U144)/2)*Y144 -> 45587.36 | AB144: =AH144/AA144*1000 -> 1403.8979 | AC144: 1 | AE144: =AF144/1.22 -> 6557.377 | AF144: 8000 | AG144: =AE144*Q144 -> 52459.016 | AH144: =AG144*1.22 -> 64000
... A181: U120 | B181: Республика Башкортостан | C181: Уфа | D181: Кировский | E181: Зеленая Роща 2 | F181: Б | G181: 46248 | H181: Комфорт | I181: ЖК на Перовской 54 | J181: улица Софьи Перовской, 54 | K181: 54.697172 | L181: 55.992477 | M181: 2010 | N181: 18 | O181: 321 | P181: =O181*2.8 -> 898.8 | Q181: 5 | R181: 0 | S181: 5 | T181: 5 | U181: 10 | V181: Вертикальный 4*3 | W181: Digital (без звука) | X181: статичный баннер | Y181: 31 | Z181: =AA181/P181 -> 20.15 | AA181: =((P181*2.6*R181/S181/2)/2+(P181*2.6*T181/U181)/2)*Y181 -> 18110.82 | AB181: =AH181/AA181*1000 -> 2208.6245 | AC181: 1 | AE181: =AF181/1.22 -> 6557.377 | AF181: 8000 | AG181: =AE181*Q181 -> 32786.885 | AH181: =AG181*1.22 -> 40000
A182: U121 | B182: Республика Башкортостан | C182: Уфа | D182: Октябрьский | F182: Б | G182: 46254 | H182: Комфорт | I182: ЖК на Набережной реки Уфы 3/5 | J182: улица Набережная реки Уфы, 3/5 | K182: 54.761940 | L182: 56.052637 | M182: 2000 | N182: 10 | O182: 86 | P182: =O182*2.8 -> 240.8 | Q182: 2 | R182: 0 | S182: 2 | T182: 2 | U182: 2 | V182: Вертикальный 4*3 | W182: Digital (без звука) | X182: статичный баннер | Y182: 31 | Z182: =AA182/P182 -> 40.3 | AA182: =((P182*2.6*R182/S182/2)/2+(P182*2.6*T182/U182)/2)*Y182 -> 9704.24 | AB182: =AH182/AA182*1000 -> 1648.7638 | AC182: 1 | AE182: =AF182/1.22 -> 6557.377 | AF182: 8000 | AG182: =AE182*Q182 -> 13114.754 | AH182: =AG182*1.22 -> 16000
A183: U122 | B183: Республика Башкортостан | C183: Уфа | D183: Первомайский | F183: Б | G183: 46254 | H183: Стандарт | I183: ЖК Мечтателей | J183: улица Рашита Нигмати, 12 | K183: 54.710131 | L183: 55.842665 | M183: 2025 | N183: 12 | O183: 289 | P183: =O183*2.8 -> 809.2 | Q183: 5 | R183: 0 | S183: 5 | T183: 5 | U183: 4 | V183: Вертикальный 4*3 | W183: Digital (без звука) | X183: статичный баннер | Y183: 31 | Z183: =AA183/P183 -> 50.375 | AA183: =((P183*2.6*R183/S183/2)/2+(P183*2.6*T183/U183)/2)*Y183 -> 40763.45 | AB183: =AH183/AA183*1000 -> 981.27121 | AC183: 1 | AE183: =AF183/1.22 -> 6557.377 | AF183: 8000 | AG183: =AE183*Q183 -> 32786.885 | AH183: =AG183*1.22 -> 40000
A184: STR1 | B184: Республика Башкортостан | C184: Стерлитамак | D184: ​Западный | E184: продажа городом | F184: А | G184: 45972 | H184: Комфорт | I184: ЖК Браво | J184: улица Интернациональная, 61 | K184: 54.811887 | L184: 56.077233 | M184: 2024 | N184: 10 | O184: 519 | P184: =O184*2.8 -> 1453.2 | Q184: 10 | R184: 5 | S184: 1 | T184: 5 | U184: 7 | V184: Горизонтальный 4*3 | W184: Digital (без звука) | X184: статичный баннер | Y184: 31 | Z184: =AA184/P184 -> 129.53571 | AA184: =((P184*2.6*R184/S184/2)/2+(P184*2.6*T184/U184)/2)*Y184 -> 188241.3 | AB184: =AH184/AA184*1000 -> 424.98644 | AC184: 1 | AE184: =AF184/1.22 -> 6557.377 | AF184: 8000 | AG184: =AE184*Q184 -> 65573.77 | AH184: =AG184*1.22 -> 80000
A185: STR2 | B185: Республика Башкортостан | C185: Стерлитамак | D185: ​Западный | E185: продажа городом | F185: А | G185: 46219 | H185: Комфорт | I185: ЖК Браво 2 | J185: улица Интернациональная, 63 | K185: 54.811726 | L185: 56.077790 | M185: 2025 | N185: 17 | O185: 363 | P185: =363*2.8 -> 1016.4 | Q185: 10 | R185: 5 | S185: 5 | T185: 5 | U185: 10 | V185: Горизонтальный 4*3 | W185: Digital (без звука) | X185: статичный баннер | Y185: 31 | Z185: =AA185/P185 -> 40.3 | AA185: =((P185*2.6*R185/S185/2)/2+(P185*2.6*T185/U185)/2)*Y185 -> 40960.92 | AB185: =AH185/AA185*1000 -> 1953.0811 | AC185: 1 | AE185: =AF185/1.22 -> 6557.377 | AF185: 8000 | AG185: =AE185*Q185 -> 65573.77 | AH185: =AG185*1.22 -> 80000
A186: STR3 | B186: Республика Башкортостан | C186: Стерлитамак | D186: Западный | E186: продажа городом | F186: А | G186: 45951 | H186: Комфорт | I186: ЖК Шиханы | J186: проспект Октября, 99 | K186: 53.629169 | L186: 55.883017 | M186: 2023 | N186: 20 | O186: 439 | P186: =O186*2.8 -> 1229.2 | Q186: 6 | R186: 3 | S186: 1 | T186: 3 | U186: 6 | V186: Горизонтальный 4*3 | W186: Digital (без звука) | X186: статичный баннер | Y186: 31 | Z186: =AA186/P186 -> 80.6 | AA186: =((P186*2.6*R186/S186/2)/2+(P186*2.6*T186/U186)/2)*Y186 -> 99073.52 | AB186: =AH186/AA186*1000 -> 484.48869 | AC186: 1 | AE186: =AF186/1.22 -> 6557.377 | AF186: 8000 | AG186: =AE186*Q186 -> 39344.262 | AH186: =AG186*1.22 -> 48000
A187: STR4 | B187: Республика Башкортостан | C187: Стерлитамак | D187: Западный | E187: продажа городом | F187: А | G187: 46122 | H187: Комфорт | I187: ЖК Шиханы 2 | J187: улица Раиса Багаутдинова, 2 | K187: 53.627989 | L187: 55.883080 | M187: 2024 | N187: 11 | O187: 124 | P187: =O187*2.8 -> 347.2 | Q187: 4 | R187: 2 | S187: 1 | T187: 2 | U187: 3 | V187: Горизонтальный 4*3 | W187: Digital (без звука) | X187: статичный баннер | Y187: 31 | Z187: =AA187/P187 -> 67.166667 | AA187: =((P187*2.6*R187/S187/2)/2+(P187*2.6*T187/U187)/2)*Y187 -> 23320.267 | AB187: =AH187/AA187*1000 -> 1372.197 | AC187: 1 | AE187: =AF187/1.22 -> 6557.377 | AF187: 8000 | AG187: =AE187*Q187 -> 26229.508 | AH187: =AG187*1.22 -> 32000
A188: STR5 | B188: Республика Башкортостан | C188: Стерлитамак | D188: ​Западный | E188: продажа городом | F188: А | G188: 46010 | H188: Комфорт | I188: ЖК на Проспекте Октября 85 | J188: проспект Октября, 85 | K188: 53.628993 | L188: 55.899941 | M188: 2019 | N188: 18 | O188: 230 | P188: =O188*2.8 -> 644 | Q188: 4 | R188: 2 | S188: 2 | T188: 2 | U188: 4 | V188: Горизонтальный 4*3 | W188: Digital (без звука) | X188: статичный баннер | Y188: 31 | Z188: =AA188/P188 -> 40.3 | AA188: =((P188*2.6*R188/S188/2)/2+(P188*2.6*T188/U188)/2)*Y188 -> 25953.2 | AB188: =AH188/AA188*1000 -> 1232.9886 | AC188: 1 | AE188: =AF188/1.22 -> 6557.377 | AF188: 8000 | AG188: =AE188*Q188 -> 26229.508 | AH188: =AG188*1.22 -> 32000
A189: NFT1 | B189: Республика Башкортостан | C189: Нефтекамск | D189: ​13-й м-н | E189: продажа городом | F189: Б | G189: 46230 | H189: Комфорт | I189: ЖК Лайф | J189: улица Ленина, 84Б | K189: 56.108256 | L189: 54.235974 | M189: 2024 | N189: 16 | O189: 283 | P189: =O189*2.8 -> 792.4 | Q189: 4 | R189: 0 | S189: 2 | T189: 4 | U189: 4 | V189: Вертикальный 4*3 | W189: Digital (без звука) | X189: статичный баннер | Y189: 31 | Z189: =AA189/P189 -> 40.3 | AA189: =((P189*2.6*R189/S189/2)/2+(P189*2.6*T189/U189)/2)*Y189 -> 31933.72 | AB189: =AH189/AA189*1000 -> 1002.0755 | AC189: 1 | AE189: =AF189/1.22 -> 6557.377 | AF189: 8000 | AG189: =AE189*Q189 -> 26229.508 | AH189: =AG189*1.22 -> 32000
A190: NFT2 | B190: Республика Башкортостан | C190: Нефтекамск | D190: 24-й м-н | E190: продажа городом | F190: Б | G190: 46237 | H190: Комфорт | I190: ЖК Городской | J190: улица Городская, 12 | K190: 56.071248 | L190: 54.225940 | M190: 2025 | N190: 10 | O190: 210 | P190: =O190*2.8 -> 588 | Q190: 2 | R190: 0 | S190: 2 | T190: 2 | U190: 2 | V190: Вертикальный 4*3 | W190: Digital (без звука) | X190: статичный баннер | Y190: 31 | Z190: =AA190/P190 -> 40.3 | AA190: =((P190*2.6*R190/S190/2)/2+(P190*2.6*T190/U190)/2)*Y190 -> 23696.4 | AB190: =AH190/AA190*1000 -> 675.20805 | AC190: 1 | AE190: =AF190/1.22 -> 6557.377 | AF190: 8000 | AG190: =AE190*Q190 -> 13114.754 | AH190: =AG190*1.22 -> 16000
A191: NFT2 | B191: Республика Башкортостан | C191: Нефтекамск | D191: 24-й м-н | E191: продажа городом | F191: Б | G191: 46237 | H191: Комфорт | I191: ЖК Городской | J191: улица Городская, 14 | K191: 56.071007 | L191: 54.226856 | M191: 2025 | N191: 10 | O191: 210 | P191: =O191*2.8 -> 588 | Q191: 4 | R191: 0 | S191: 4 | T191: 4 | U191: 4 | V191: Вертикальный 4*3 | W191: Digital (без звука) | X191: статичный баннер | Y191: 31 | Z191: =AA191/P191 -> 40.3 | AA191: =((P191*2.6*R191/S191/2)/2+(P191*2.6*T191/U191)/2)*Y191 -> 23696.4 | AB191: =AH191/AA191*1000 -> 1350.4161 | AC191: 1 | AE191: =AF191/1.22 -> 6557.377 | AF191: 8000 | AG191: =AE191*Q191 -> 26229.508 | AH191: =AG191*1.22 -> 32000
A192: OKT1 | B192: Республика Башкортостан | C192: Октябрьский | D192: Центральный | E192: продажа городом | F192: Б | G192: 46247 | H192: Комфорт | I192: ЖК Парковая | J192: улица Парковая, 5 | K192: 54.471085 | L192: 53.518337 | M192: 2024 | N192: 10 | O192: 235 | P192: =O192*2.8 -> 658 | Q192: 5 | R192: 5 | S192: 5 | T192: 0 | U192: 5 | V192: Вертикальный 4*3 | W192: Digital (без звука) | X192: статичный баннер | Y192: 31 | Z192: =AA192/P192 -> 20.15 | AA192: =((P192*2.6*R192/S192/2)/2+(P192*2.6*T192/U192)/2)*Y192 -> 13258.7 | AB192: =AH192/AA192*1000 -> 3016.887 | AC192: 1 | AE192: =AF192/1.22 -> 6557.377 | AF192: 8000 | AG192: =AE192*Q192 -> 32786.885 | AH192: =AG192*1.22 -> 40000
A193: OREN1 | B193: Оренбургская область | C193: Оренбург | D193: Дзержинский | E193: мкрн. 13_15_16 | F193: А | G193: 45952 | H193: Комфорт | I193: ЖК 15Б Микрорайон | J193: улица Автомобилистов, 13 | K193: 51.830568 | L193: 55.168964 | M193: 2023 | N193: 19 | O193: 762 | P193: =O193*2.8 -> 2133.6 | Q193: 5 | R193: 5 | S193: 6 | T193: 0 | U193: 12 | V193: Горизонтальный 4*3 | W193: Digital (без звука) | X193: статичный баннер | Y193: 31 | Z193: =AA193/P193 -> 16.791667 | AA193: =((P193*2.6*R193/S193/2)/2+(P193*2.6*T193/U193)/2)*Y193 -> 35826.7 | AB193: =AH193/AA193*1000 -> 1116.4857 | AC193: 1 | AE193: =AF193/1.22 -> 6557.377 | AF193: 8000 | AG193: =AE193*Q193 -> 32786.885 | AH193: =AG193*1.22 -> 40000
A194: OREN1 | B194: Оренбургская область | C194: Оренбург | D194: Дзержинский | E194: мкрн. 13_15_16 | F194: А | G194: 45952 | H194: Комфорт | I194: ЖК 15Б Микрорайон | J194: улица Автомобилистов, 13 | K194: 51.830568 | L194: 55.168964 | M194: 2023 | N194: 19 | O194: 762 | P194: =O194*2.8 -> 2133.6 | Q194: 5 | R194: 0 | S194: 6 | T194: 5 | U194: 12 | V194: Венртикальный 4*3 | W194: Digital (без звука) | X194: статичный баннер | Y194: 31 | Z194: =AA194/P194 -> 16.791667 | AA194: =((P194*2.6*R194/S194/2)/2+(P194*2.6*T194/U194)/2)*Y194 -> 35826.7 | AB194: =AH194/AA194*1000 -> 1116.4857 | AC194: 1 | AE194: =AF194/1.22 -> 6557.377 | AF194: 8000 | AG194: =AE194*Q194 -> 32786.885 | AH194: =AG194*1.22 -> 40000
A195: OREN1 | B195: Оренбургская область | C195: Оренбург | D195: Дзержинский | E195: мкрн. 13_15_16 | F195: А | G195: 45952 | H195: Комфорт | I195: ЖК 15Б Микрорайон | J195: улица Северный, 23 | K195: 51.828932 | L195: 55.173573 | M195: 2024 | N195: 17 | O195: 162 | P195: =O195*2.8 -> 453.6 | Q195: 6 | R195: 3 | S195: 3 | T195: 3 | U195: 4 | V195: Горизонтальный 4*3 | W195: Digital (без звука) | X195: статичный баннер | Y195: 31 | Z195: =AA195/P195 -> 50.375 | AA195: =((P195*2.6*R195/S195/2)/2+(P195*2.6*T195/U195)/2)*Y195 -> 22850.1 | AB195: =AH195/AA195*1000 -> 2100.6473 | AC195: 1 | AE195: =AF195/1.22 -> 6557.377 | AF195: 8000 | AG195: =AE195*Q195 -> 39344.262 | AH195: =AG195*1.22 -> 48000
A196: OREN2 | B196: Оренбургская область | C196: Оренбург | D196: Ленинский | E196: мкрн. 18_19_20 | F196: А | G196: 45952 | H196: Комфорт | I196: ЖК 17 Микрорайон | J196: улица Салмышская, 43/1 | K196: 51.823309 | L196: 55.167186 | M196: 2012 | N196: 14 | O196: 201 | P196: =O196*2.8 -> 562.8 | Q196: 4 | R196: 4 | S196: 4 | T196: 0 | U196: 8 | V196: Горизонтальный 4*3 | W196: Digital (без звука) | X196: статичный баннер | Y196: 31 | Z196: =AA196/P196 -> 20.15 | AA196: =((P196*2.6*R196/S196/2)/2+(P196*2.6*T196/U196)/2)*Y196 -> 11340.42 | AB196: =AH196/AA196*1000 -> 2821.765 | AC196: 1 | AE196: =AF196/1.22 -> 6557.377 | AF196: 8000 | AG196: =AE196*Q196 -> 26229.508 | AH196: =AG196*1.22 -> 32000
A197: OREN2 | B197: Оренбургская область | C197: Оренбург | D197: Ленинский | E197: мкрн. 18_19_20 | F197: А | G197: 45952 | H197: Комфорт | I197: ЖК 17 Микрорайон | J197: улица Салмышская, 43/5 | K197: 51.822089 | L197: 55.16836 | M197: 2017 | N197: 20 | O197: 568 | P197: =O197*2.8 -> 1590.4 | Q197: 4 | R197: 4 | S197: 4 | T197: 0 | U197: 8 | V197: Горизонтальный 4*3 | W197: Digital (без звука) | X197: статичный баннер | Y197: 31 | Z197: =AA197/P197 -> 20.15 | AA197: =((P197*2.6*R197/S197/2)/2+(P197*2.6*T197/U197)/2)*Y197 -> 32046.56 | AB197: =AH197/AA197*1000 -> 998.54711 | AC197: 1 | AE197: =AF197/1.22 -> 6557.377 | AF197: 8000 | AG197: =AE197*Q197 -> 26229.508 | AH197: =AG197*1.22 -> 32000
... A230: OREN14 | B230: Оренбургская область | C230: Оренбург | D230: Промышленный | E230: Промышленный_Центр | F230: Б | G230: 46255 | H230: Стандарт | I230: ЖК Малая земля 3 | J230: улица Пролетарская, 300 | K230: 51.807959 | L230: 55.096256 | M230: 2020 | N230: 18 | O230: 357 | P230: =O230*2.8 -> 999.6 | Q230: 4 | R230: 4 | S230: 4 | T230: 0 | U230: 8 | V230: Горизонтальный 4*3 | W230: Digital (без звука) | X230: статичный баннер | Y230: 31 | Z230: =AA230/P230 -> 20.15 | AA230: =((P230*2.6*R230/S230/2)/2+(P230*2.6*T230/U230)/2)*Y230 -> 20141.94 | AB230: =AH230/AA230*1000 -> 1588.7248 | AC230: 1 | AE230: =AF230/1.22 -> 6557.377 | AF230: 8000 | AG230: =AE230*Q230 -> 26229.508 | AH230: =AG230*1.22 -> 32000
A231: OREN14 | B231: Оренбургская область | C231: Оренбург | D231: Промышленный | F231: Б | G231: 46255 | H231: Комфорт | I231: ЖК Малая земля 3 | J231: улица Пролетарская, 300 | K231: 51.807726 | L231: 55.096344 | M231: 2020 | N231: 17 | O231: 357 | P231: =O231*2.8 -> 999.6 | Q231: 4 | R231: 0 | S231: 4 | T231: 4 | U231: 8 | V231: Вертикальный 4*3 | W231: Digital (без звука) | X231: статичный баннер | Y231: 31 | Z231: =AA231/P231 -> 20.15 | AA231: =((P231*2.6*R231/S231/2)/2+(P231*2.6*T231/U231)/2)*Y231 -> 20141.94 | AB231: =AH231/AA231*1000 -> 1588.7248 | AC231: 1 | AE231: =AF231/1.22 -> 6557.377 | AF231: 8000 | AG231: =AE231*Q231 -> 26229.508 | AH231: =AG231*1.22 -> 32000
A232: OREN14 | B232: Оренбургская область | C232: Оренбург | D232: Промышленный | F232: Б | G232: 46255 | H232: Комфорт | I232: ЖК Малая земля 3 | J232: улица Пролетарская, 292 | K232: 51.805532 | L232: 55.095608 | M232: 2019 | N232: 19 | O232: 299 | P232: =O232*2.8 -> 837.2 | Q232: 8 | R232: 4 | S232: 4 | T232: 4 | U232: 8 | V232: Вертикальный 4*3 | W232: Digital (без звука) | X232: статичный баннер | Y232: 31 | Z232: =AA232/P232 -> 40.3 | AA232: =((P232*2.6*R232/S232/2)/2+(P232*2.6*T232/U232)/2)*Y232 -> 33739.16 | AB232: =AH232/AA232*1000 -> 1896.9056 | AC232: 1 | AE232: =AF232/1.22 -> 6557.377 | AF232: 8000 | AG232: =AE232*Q232 -> 52459.016 | AH232: =AG232*1.22 -> 64000
A233: OREN15 | B233: Оренбургская область | C233: Оренбург | D233: Ленинский | E233: мкрн. 18_19_20 | F233: А | G233: 45989 | H233: Стандарт | I233: ЖК Молодежный 1 | J233: улица Карпова, 3/1 | K233: 51.817196 | L233: 55.181866 | M233: 2016 | N233: 19 | O233: 576 | P233: =O233*2.8 -> 1612.8 | Q233: 8 | R233: 8 | S233: 8 | T233: 0 | U233: 16 | V233: Горизонтальный 4*3 | W233: Digital (без звука) | X233: статичный баннер | Y233: 31 | Z233: =AA233/P233 -> 20.15 | AA233: =((P233*2.6*R233/S233/2)/2+(P233*2.6*T233/U233)/2)*Y233 -> 32497.92 | AB233: =AH233/AA233*1000 -> 1969.3568 | AC233: 1 | AE233: =AF233/1.22 -> 6557.377 | AF233: 8000 | AG233: =AE233*Q233 -> 52459.016 | AH233: =AG233*1.22 -> 64000
A234: OREN15 | B234: Оренбургская область | C234: Оренбург | D234: Ленинский | E234: мкрн. 18_19_20 | F234: А | G234: 45989 | H234: Стандарт | I234: ЖК Молодежный 1 | J234: улица Карпова, 3/1 | K234: 51.817196 | L234: 55.181866 | M234: 2016 | N234: 19 | O234: 576 | P234: =O234*2.8 -> 1612.8 | Q234: 8 | R234: 0 | S234: 8 | T234: 8 | U234: 16 | V234: Вертикальный 4*3 | W234: Digital (без звука) | X234: статичный баннер | Y234: 31 | Z234: =AA234/P234 -> 20.15 | AA234: =((P234*2.6*R234/S234/2)/2+(P234*2.6*T234/U234)/2)*Y234 -> 32497.92 | AB234: =AH234/AA234*1000 -> 1969.3568 | AC234: 1 | AE234: =AF234/1.22 -> 6557.377 | AF234: 8000 | AG234: =AE234*Q234 -> 52459.016 | AH234: =AG234*1.22 -> 64000
A235: OREN16 | B235: Оренбургская область | C235: Оренбург | D235: Ленинский | E235: мкрн. 13_15_16 | F235: А | G235: 45989 | H235: Стандарт | I235: ЖК Звездный | J235: улица Братьев Хусаиновых, 8 | K235: 51.823776 | L235: 55.178223 | M235: 2021 | N235: 17 | O235: 297 | P235: =O235*2.8 -> 831.6 | Q235: 3 | R235: 3 | S235: 3 | T235: 0 | U235: 6 | V235: Горизонтальный 4*3 | W235: Digital (без звука) | X235: статичный баннер | Y235: 31 | Z235: =AA235/P235 -> 20.15 | AA235: =((P235*2.6*R235/S235/2)/2+(P235*2.6*T235/U235)/2)*Y235 -> 16756.74 | AB235: =AH235/AA235*1000 -> 1432.2595 | AC235: 1 | AE235: =AF235/1.22 -> 6557.377 | AF235: 8000 | AG235: =AE235*Q235 -> 19672.131 | AH235: =AG235*1.22 -> 24000
A236: OREN16 | B236: Оренбургская область | C236: Оренбург | D236: Ленинский | E236: мкрн. 13_15_16 | F236: А | G236: 45989 | H236: Стандарт | I236: ЖК Звездный | J236: улица Братьев Хусаиновых, 8 | K236: 51.823776 | L236: 55.178223 | M236: 2021 | N236: 17 | O236: 297 | P236: =O236*2.8 -> 831.6 | Q236: 3 | R236: 0 | S236: 3 | T236: 3 | U236: 6 | V236: Вертикальный 4*3 | W236: Digital (без звука) | X236: статичный баннер | Y236: 31 | Z236: =AA236/P236 -> 20.15 | AA236: =((P236*2.6*R236/S236/2)/2+(P236*2.6*T236/U236)/2)*Y236 -> 16756.74 | AB236: =AH236/AA236*1000 -> 1432.2595 | AC236: 1 | AE236: =AF236/1.22 -> 6557.377 | AF236: 8000 | AG236: =AE236*Q236 -> 19672.131 | AH236: =AG236*1.22 -> 24000
A237: OREN16 | B237: Оренбургская область | C237: Оренбург | D237: Ленинский | E237: мкрн. 13_15_16 | F237: А | G237: 45989 | H237: Стандарт | I237: ЖК Звездный | J237: улица Братьев Хусаиновых, 6 | K237: 51.824999 | L237: 55.176968 | M237: 2025 | N237: 20 | O237: 594 | P237: =O237*2.8 -> 1663.2 | Q237: 5 | R237: 5 | S237: 5 | T237: 0 | U237: 10 | V237: Горизонтальный 4*3 | W237: Digital (без звука) | X237: статичный баннер | Y237: 31 | Z237: =AA237/P237 -> 20.15 | AA237: =((P237*2.6*R237/S237/2)/2+(P237*2.6*T237/U237)/2)*Y237 -> 33513.48 | AB237: =AH237/AA237*1000 -> 1193.5496 | AC237: 1 | AE237: =AF237/1.22 -> 6557.377 | AF237: 8000 | AG237: =AE237*Q237 -> 32786.885 | AH237: =AG237*1.22 -> 40000
A238: OREN16 | B238: Оренбургская область | C238: Оренбург | D238: Ленинский | E238: мкрн. 13_15_16 | F238: А | G238: 45989 | H238: Стандарт | I238: ЖК Звездный | J238: улица Братьев Хусаиновых, 6 | K238: 51.824999 | L238: 55.176968 | M238: 2025 | N238: 20 | O238: 594 | P238: =O238*2.8 -> 1663.2 | Q238: 5 | R238: 0 | S238: 5 | T238: 5 | U238: 10 | V238: Вертикальный 4*3 | W238: Digital (без звука) | X238: статичный баннер | Y238: 31 | Z238: =AA238/P238 -> 20.15 | AA238: =((P238*2.6*R238/S238/2)/2+(P238*2.6*T238/U238)/2)*Y238 -> 33513.48 | AB238: =AH238/AA238*1000 -> 1193.5496 | AC238: 1 | AE238: =AF238/1.22 -> 6557.377 | AF238: 8000 | AG238: =AE238*Q238 -> 32786.885 | AH238: =AG238*1.22 -> 40000
A239: OREN17 | B239: Оренбургская область | C239: Оренбург | D239: Ленинский | E239: мкрн. Южный | F239: Б | G239: 45995 | H239: Стандарт | I239: ЖК Южный | J239: улица Илекская, 2/2 | K239: 51.721118 | L239: 55.108154 | M239: 2013 | N239: 14 | O239: 83 | P239: =O239*2.8 -> 232.4 | Q239: 1 | R239: 1 | S239: 1 | T239: 0 | U239: 2 | V239: Горизонтальный 4*3 | W239: Digital (без звука) | X239: статичный баннер | Y239: 31 | Z239: =AA239/P239 -> 20.15 | AA239: =((P239*2.6*R239/S239/2)/2+(P239*2.6*T239/U239)/2)*Y239 -> 4682.86 | AB239: =AH239/AA239*1000 -> 1708.3577 | AC239: 1 | AE239: =AF239/1.22 -> 6557.377 | AF239: 8000 | AG239: =AE239*Q239 -> 6557.377 | AH239: =AG239*1.22 -> 8000
A240: OREN17 | B240: Оренбургская область | C240: Оренбург | D240: Ленинский | E240: мкрн. Южный | F240: Б | G240: 45995 | H240: Стандарт | I240: ЖК Южный | J240: улица Беляевская,15/1 | K240: 51.721636 | L240: 55.109629 | M240: 2017 | N240: 17 | O240: 175 | P240: =O240*2.8 -> 490 | Q240: 2 | R240: 2 | S240: 2 | T240: 0 | U240: 4 | V240: Горизонтальный 4*3 | W240: Digital (без звука) | X240: статичный баннер | Y240: 31 | Z240: =AA240/P240 -> 20.15 | AA240: =((P240*2.6*R240/S240/2)/2+(P240*2.6*T240/U240)/2)*Y240 -> 9873.5 | AB240: =AH240/AA240*1000 -> 1620.4993 | AC240: 1 | AE240: =AF240/1.22 -> 6557.377 | AF240: 8000 | AG240: =AE240*Q240 -> 13114.754 | AH240: =AG240*1.22 -> 16000
A241: OREN17 | B241: Оренбургская область | C241: Оренбург | D241: Ленинский | E241: мкрн. Южный | F241: Б | G241: 45995 | H241: Стандарт | I241: ЖК Южный | J241: улица Беляевская, 15 | K241: 51.722049 | L241: 55.107403 | M241: 2016 | N241: 15 | O241: 572 | P241: =O241*2.8 -> 1601.6 | Q241: 8 | R241: 8 | S241: 8 | T241: 0 | U241: 16 | V241: Горизонтальный 4*3 | W241: Digital (без звука) | X241: статичный баннер | Y241: 31 | Z241: =AA241/P241 -> 20.15 | AA241: =((P241*2.6*R241/S241/2)/2+(P241*2.6*T241/U241)/2)*Y241 -> 32272.24 | AB241: =AH241/AA241*1000 -> 1983.1285 | AC241: 1 | AE241: =AF241/1.22 -> 6557.377 | AF241: 8000 | AG241: =AE241*Q241 -> 52459.016 | AH241: =AG241*1.22 -> 64000
A242: OREN17 | B242: Оренбургская область | C242: Оренбург | D242: Ленинский | E242: мкрн. Южный | F242: Б | G242: 45995 | H242: Стандарт | I242: ЖК Южный | J242: улица Центральная, 13/1 | K242: 51.713082 | L242: 55.111625 | M242: 2023 | N242: 17 | O242: 136 | P242: =O242*2.8 -> 380.8 | Q242: 1 | R242: 1 | S242: 1 | T242: 0 | U242: 2 | V242: Горизонтальный 4*3 | W242: Digital (без звука) | X242: статичный баннер | Y242: 31 | Z242: =AA242/P242 -> 20.15 | AA242: =((P242*2.6*R242/S242/2)/2+(P242*2.6*T242/U242)/2)*Y242 -> 7673.12 | AB242: =AH242/AA242*1000 -> 1042.6007 | AC242: 1 | AE242: =AF242/1.22 -> 6557.377 | AF242: 8000 | AG242: =AE242*Q242 -> 6557.377 | AH242: =AG242*1.22 -> 8000
A243: OREN18 | B243: Оренбургская область | C243: Оренбург | D243: Ленинский | E243: мкрн. Дубки | F243: А | G243: 45995 | H243: Комфорт | I243: ЖК Донковцева 1 | J243: улица Донковцева, 1 | K243: 51.770590 | L243: 55.162496 | M243: 2019 | N243: 19 | O243: 348 | P243: =O243*2.8 -> 974.4 | Q243: 5 | R243: 5 | S243: 5 | T243: 0 | U243: 10 | V243: Горизонтальный 4*3 | W243: Digital (без звука) | X243: статичный баннер | Y243: 31 | Z243: =AA243/P243 -> 20.15 | AA243: =((P243*2.6*R243/S243/2)/2+(P243*2.6*T243/U243)/2)*Y243 -> 19634.16 | AB243: =AH243/AA243*1000 -> 2037.2657 | AC243: 1 | AE243: =AF243/1.22 -> 6557.377 | AF243: 8000 | AG243: =AE243*Q243 -> 32786.885 | AH243: =AG243*1.22 -> 40000
A244: OREN18 | B244: Оренбургская область | C244: Оренбург | D244: Ленинский | E244: мкрн. Дубки | F244: А | G244: 45995 | H244: Комфорт | I244: ЖК Донковцева 1 | J244: улица Донковцева, 3 | K244: 51.769821 | L244: 55.162451 | M244: 2019 | N244: 19 | O244: 197 | P244: =O244*2.8 -> 551.6 | Q244: 3 | R244: 3 | S244: 3 | T244: 0 | U244: 6 | V244: Горизонтальный 4*3 | W244: Digital (без звука) | X244: статичный баннер | Y244: 31 | Z244: =AA244/P244 -> 20.15 | AA244: =((P244*2.6*R244/S244/2)/2+(P244*2.6*T244/U244)/2)*Y244 -> 11114.74 | AB244: =AH244/AA244*1000 -> 2159.2948 | AC244: 1 | AE244: =AF244/1.22 -> 6557.377 | AF244: 8000 | AG244: =AE244*Q244 -> 19672.131 | AH244: =AG244*1.22 -> 24000
... A260: OREN25 | B260: Оренбургская область | C260: Оренбург | D260: Ленинский | E260: мкрн. Дубки | F260: Б | G260: 46101 | H260: Комфорт | I260: ЖК Дрезден | J260: улица Ленинградская, 92 | K260: 51.777489 | L260: 55.145051 | M260: 2014 | N260: 11 | O260: 105 | P260: =O260*2.8 -> 294 | Q260: 8 | R260: 4 | S260: 4 | T260: 4 | U260: 4 | V260: Горизонтальный 4*3 | W260: Digital (без звука) | X260: статичный баннер | Y260: 31 | Z260: =AA260/P260 -> 60.45 | AA260: =((P260*2.6*R260/S260/2)/2+(P260*2.6*T260/U260)/2)*Y260 -> 17772.3 | AB260: =AH260/AA260*1000 -> 3601.1096 | AC260: 1 | AE260: =AF260/1.22 -> 6557.377 | AF260: 8000 | AG260: =AE260*Q260 -> 52459.016 | AH260: =AG260*1.22 -> 64000
A261: OREN25 | B261: Оренбургская область | C261: Оренбург | D261: Ленинский | E261: мкрн. Дубки | F261: Б | G261: 46101 | H261: Комфорт | I261: ЖК Дрезден | J261: улица Мало-Ленинская, 167/2 | K261: 51.775255, 55.140793 | M261: 2016 | N261: 18 | O261: 256 | P261: =O261*2.8 -> 716.8 | Q261: 6 | R261: 3 | S261: 1 | T261: 3 | U261: 1 | V261: Вертикальный 4*3 | W261: Digital (без звука) | X261: статичный баннер | Y261: 31 | Z261: =AA261/P261 -> 181.35 | AA261: =((P261*2.6*R261/S261/2)/2+(P261*2.6*T261/U261)/2)*Y261 -> 129991.68 | AB261: =AH261/AA261*1000 -> 369.2544 | AC261: 1 | AE261: =AF261/1.22 -> 6557.377 | AF261: 8000 | AG261: =AE261*Q261 -> 39344.262 | AH261: =AG261*1.22 -> 48000
A262: OREN26 | B262: Оренбургская область | C262: Оренбург | D262: Ленинский | E262: Промышленный_Центр | F262: Б | G262: 46107 | H262: Комфорт | I262: ЖК Премьер 2 | J262: Почтовый переулок, 11 | K262: 51.760986 | L262: 55.109909 | M262: 2011 | N262: 8 | O262: 63 | P262: =O262*2.8 -> 176.4 | Q262: 3 | R262: 3 | S262: 3 | T262: 0 | U262: 3 | V262: Горизонтальный 4*3 | W262: Digital (без звука) | X262: статичный баннер | Y262: 31 | Z262: =AA262/P262 -> 20.15 | AA262: =((P262*2.6*R262/S262/2)/2+(P262*2.6*T262/U262)/2)*Y262 -> 3554.46 | AB262: =AH262/AA262*1000 -> 6752.0805 | AC262: 1 | AE262: =AF262/1.22 -> 6557.377 | AF262: 8000 | AG262: =AE262*Q262 -> 19672.131 | AH262: =AG262*1.22 -> 24000
A263: OREN26 | B263: Оренбургская область | C263: Оренбург | D263: Центральный | E263: Промышленный_Центр | F263: Б | G263: 46107 | H263: Комфорт | I263: ЖК Премьер 2 | J263: улица Маршала Жукова, 27 | K263: 51.773176 | L263: 55.108085 | M263: 2007 | N263: 14 | O263: 72 | P263: =O263*2.8 -> 201.6 | Q263: 4 | R263: 0 | S263: 1 | T263: 4 | U263: 2 | V263: Вертикальный 4*3 | W263: Digital (без звука) | X263: статичный баннер | Y263: 31 | Z263: =AA263/P263 -> 80.6 | AA263: =((P263*2.6*R263/S263/2)/2+(P263*2.6*T263/U263)/2)*Y263 -> 16248.96 | AB263: =AH263/AA263*1000 -> 1969.3568 | AC263: 1 | AE263: =AF263/1.22 -> 6557.377 | AF263: 8000 | AG263: =AE263*Q263 -> 26229.508 | AH263: =AG263*1.22 -> 32000
A264: OREN26 | B264: Оренбургская область | C264: Оренбург | D264: Ленинский | E264: Промышленный_Центр | F264: Б | G264: 46107 | H264: Комфорт | I264: ЖК Премьер 2 | J264: улица Краснознаменная, 47 | K264: 51.767123 | L264: 55.107879 | M264: 2021 | N264: 10 | O264: 66 | P264: =O264*2.8 -> 184.8 | Q264: 4 | R264: 0 | S264: 2 | T264: 4 | U264: 2 | V264: Вертикальный 4*3 | W264: Digital (без звука) | X264: статичный баннер | Y264: 31 | Z264: =AA264/P264 -> 80.6 | AA264: =((P264*2.6*R264/S264/2)/2+(P264*2.6*T264/U264)/2)*Y264 -> 14894.88 | AB264: =AH264/AA264*1000 -> 2148.3892 | AC264: 1 | AE264: =AF264/1.22 -> 6557.377 | AF264: 8000 | AG264: =AE264*Q264 -> 26229.508 | AH264: =AG264*1.22 -> 32000
A265: OREN26 | B265: Оренбургская область | C265: Оренбург | D265: Ленинский | E265: Промышленный_Центр | F265: Б | G265: 46107 | H265: Комфорт | I265: ЖК Премьер 2 | J265: улица Ленинская, 59/1 | K265: 51.763144 | L265: 55.113466 | M265: 2006 | N265: 11 | O265: 94 | P265: =O265*2.8 -> 263.2 | Q265: 4 | R265: 0 | S265: 4 | T265: 4 | U265: 4 | V265: Вертикальный 4*3 | W265: Digital (без звука) | X265: статичный баннер | Y265: 31 | Z265: =AA265/P265 -> 40.3 | AA265: =((P265*2.6*R265/S265/2)/2+(P265*2.6*T265/U265)/2)*Y265 -> 10606.96 | AB265: =AH265/AA265*1000 -> 3016.887 | AC265: 1 | AE265: =AF265/1.22 -> 6557.377 | AF265: 8000 | AG265: =AE265*Q265 -> 26229.508 | AH265: =AG265*1.22 -> 32000
A266: OREN27 | B266: Оренбургская область | C266: Оренбург | D266: Центральный | E266: Промышленный_Центр | F266: Б | G266: 46133 | H266: Комфорт | I266: ЖК Риверсайд | J266: улица Черепановых, 2А | K266: 51.754018 | L266: 55.090577 | M266: 2015 | N266: 14 | O266: 119 | P266: =O266*2.8 -> 333.2 | Q266: 2 | R266: 2 | S266: 3 | T266: 0 | U266: 4 | V266: Вертикальный 4*3 | W266: Digital (без звука) | X266: статичный баннер | Y266: 31 | Z266: =AA266/P266 -> 13.433333 | AA266: =((P266*2.6*R266/S266/2)/2+(P266*2.6*T266/U266)/2)*Y266 -> 4475.9867 | AB266: =AH266/AA266*1000 -> 3574.6308 | AC266: 1 | AE266: =AF266/1.22 -> 6557.377 | AF266: 8000 | AG266: =AE266*Q266 -> 13114.754 | AH266: =AG266*1.22 -> 16000
A267: OREN27 | B267: Оренбургская область | C267: Оренбург | D267: Центральный | E267: Промышленный_Центр | F267: Б | G267: 46133 | H267: Комфорт | I267: ЖК Риверсайд | J267: улица Яицкая,1/2 | K267: 51.754469 | L267: 55.090757 | M267: 2015 | N267: 14 | O267: 172 | P267: =O267*2.8 -> 481.6 | Q267: 3 | R267: 3 | S267: 3 | T267: 0 | U267: 6 | V267: Вертикальный 4*3 | W267: Digital (без звука) | X267: статичный баннер | Y267: 31 | Z267: =AA267/P267 -> 20.15 | AA267: =((P267*2.6*R267/S267/2)/2+(P267*2.6*T267/U267)/2)*Y267 -> 9704.24 | AB267: =AH267/AA267*1000 -> 2473.1458 | AC267: 1 | AE267: =AF267/1.22 -> 6557.377 | AF267: 8000 | AG267: =AE267*Q267 -> 19672.131 | AH267: =AG267*1.22 -> 24000
A268: OREN27 | B268: Оренбургская область | C268: Оренбург | D268: Центральный | E268: Промышленный_Центр | F268: Б | G268: 46133 | H268: Комфорт | I268: ЖК Риверсайд | J268: улица Яицкая,1/3 | K268: 51.754469 | L268: 55.090757 | M268: 2015 | N268: 14 | O268: 172 | P268: =O268*2.8 -> 481.6 | Q268: 2 | R268: 2 | S268: 3 | T268: 0 | U268: 6 | V268: Вертикальный 4*3 | W268: Digital (без звука) | X268: статичный баннер | Y268: 31 | Z268: =AA268/P268 -> 13.433333 | AA268: =((P268*2.6*R268/S268/2)/2+(P268*2.6*T268/U268)/2)*Y268 -> 6469.4933 | AB268: =AH268/AA268*1000 -> 2473.1458 | AC268: 1 | AE268: =AF268/1.22 -> 6557.377 | AF268: 8000 | AG268: =AE268*Q268 -> 13114.754 | AH268: =AG268*1.22 -> 16000
A269: OREN28 | B269: Оренбургская область | C269: Оренбург | D269: Центральный | F269: Б | G269: 46258 | H269: Комфорт | I269: ЖК Риверсайд 2 | J269: улица Яицкая, 9 | K269: 51.755177, 55.089580 | M269: 2025 | N269: 11 | O269: 311 | P269: =O269*2.8 -> 870.8 | Q269: 12 | R269: 6 | S269: 6 | T269: 6 | U269: 6 | V269: Вертикальный 4*3 | W269: Digital (без звука) | X269: статичный баннер | Y269: 31 | Z269: =AA269/P269 -> 60.45 | AA269: =((P269*2.6*R269/S269/2)/2+(P269*2.6*T269/U269)/2)*Y269 -> 52639.86 | AB269: =AH269/AA269*1000 -> 1823.7131 | AC269: 1 | AE269: =AF269/1.22 -> 6557.377 | AF269: 8000 | AG269: =AE269*Q269 -> 78688.525 | AH269: =AG269*1.22 -> 96000
A270: OREN29 | B270: Оренбургская область | C270: Оренбург | D270: Ленинский | E270: мкрн. 13_15_16 | F270: Б | G270: 46133 | H270: Комфорт | I270: ЖК Новизна | J270: улица Поляничко, 8 | K270: 51.823042 | L270: 55.172198 | M270: 2017 | N270: 18 | O270: 494 | P270: =O270*2.8 -> 1383.2 | Q270: 12 | R270: 6 | S270: 6 | T270: 6 | U270: 12 | V270: Вертикальный 4*3 | W270: Digital (без звука) | X270: статичный баннер | Y270: 31 | Z270: =AA270/P270 -> 40.3 | AA270: =((P270*2.6*R270/S270/2)/2+(P270*2.6*T270/U270)/2)*Y270 -> 55742.96 | AB270: =AH270/AA270*1000 -> 1722.1906 | AC270: 1 | AE270: =AF270/1.22 -> 6557.377 | AF270: 8000 | AG270: =AE270*Q270 -> 78688.525 | AH270: =AG270*1.22 -> 96000
A271: OREN30 | B271: Оренбургская область | C271: Оренбург | D271: Дзержинский | E271: мкрн. 13_15_16 | F271: Б | G271: 46154 | H271: Комфорт | I271: ЖК Загородное шоссе | J271: улица Загородное шоссе, 14 | K271: 51.837847 | L271: 55.162685 | M271: 2015 | N271: 17 | O271: 505 | P271: =O271*2.8 -> 1414 | Q271: 5 | R271: 5 | S271: 5 | T271: 0 | U271: 10 | V271: Горизонтальный 4*3 | W271: Digital (без звука) | X271: статичный баннер | Y271: 31 | Z271: =AA271/P271 -> 20.15 | AA271: =((P271*2.6*R271/S271/2)/2+(P271*2.6*T271/U271)/2)*Y271 -> 28492.1 | AB271: =AH271/AA271*1000 -> 1403.8979 | AC271: 1 | AE271: =AF271/1.22 -> 6557.377 | AF271: 8000 | AG271: =AE271*Q271 -> 32786.885 | AH271: =AG271*1.22 -> 40000
A272: OREN30 | B272: Оренбургская область | C272: Оренбург | D272: Дзержинский | E272: мкрн. 13_15_16 | F272: Б | G272: 46154 | H272: Комфорт | I272: ЖК Загородное шоссе | J272: улица Загородное шоссе, 14 | K272: 51.837847 | L272: 55.162686 | M272: 2015 | N272: 17 | O272: 505 | P272: =O272*2.8 -> 1414 | Q272: 5 | R272: 0 | S272: 5 | T272: 5 | U272: 10 | V272: Вертикальный 4*3 | W272: Digital (без звука) | X272: статичный баннер | Y272: 31 | Z272: =AA272/P272 -> 20.15 | AA272: =((P272*2.6*R272/S272/2)/2+(P272*2.6*T272/U272)/2)*Y272 -> 28492.1 | AB272: =AH272/AA272*1000 -> 1403.8979 | AC272: 1 | AE272: =AF272/1.22 -> 6557.377 | AF272: 8000 | AG272: =AE272*Q272 -> 32786.885 | AH272: =AG272*1.22 -> 40000
A273: OREN31 | B273: Оренбургская область | C273: Оренбург | D273: Ленинский | E273: мкрн. 13_15_16 | F273: Б | G273: 46162 | H273: Комфорт | I273: ЖК 15 Микрорайон | J273: улица Поляничко, 11/5 | K273: 51.822948 | L273: 55.177552 | M273: 2021 | N273: 17 | O273: 235 | P273: =O273*2.8 -> 658 | Q273: 6 | R273: 0 | S273: 3 | T273: 6 | U273: 6 | V273: Вертикальный 4*3 | W273: Digital (без звука) | X273: статичный баннер | Y273: 31 | Z273: =AA273/P273 -> 40.3 | AA273: =((P273*2.6*R273/S273/2)/2+(P273*2.6*T273/U273)/2)*Y273 -> 26517.4 | AB273: =AH273/AA273*1000 -> 1810.1322 | AC273: 1 | AE273: =AF273/1.22 -> 6557.377 | AF273: 8000 | AG273: =AE273*Q273 -> 39344.262 | AH273: =AG273*1.22 -> 48000
A274: OREN31 | B274: Оренбургская область | C274: Оренбург | D274: Ленинский | E274: мкрн. 13_15_16 | F274: Б | G274: 46162 | H274: Комфорт | I274: ЖК 15 Микрорайон | J274: Северный проезд, 22 | K274: 51.827050 | L274: 55.172315 | M274: 2018 | N274: 20 | O274: 162 | P274: =O274*2.8 -> 453.6 | Q274: 2 | R274: 0 | S274: 1 | T274: 2 | U274: 2 | V274: Вертикальный 4*3 | W274: Digital (без звука) | X274: статичный баннер | Y274: 31 | Z274: =AA274/P274 -> 40.3 | AA274: =((P274*2.6*R274/S274/2)/2+(P274*2.6*T274/U274)/2)*Y274 -> 18280.08 | AB274: =AH274/AA274*1000 -> 875.26969 | AC274: 1 | AE274: =AF274/1.22 -> 6557.377 | AF274: 8000 | AG274: =AE274*Q274 -> 13114.754 | AH274: =AG274*1.22 -> 16000
A275: OREN31 | B275: Оренбургская область | C275: Оренбург | D275: Ленинский | E275: мкрн. 13_15_16 | F275: Б | G275: 46162 | H275: Комфорт | I275: ЖК 15 Микрорайон | J275: улица Братьев Хусаиновых, 2/2 | K275: 51.826299 | L275: 55.173914 | M275: 2019 | N275: 18 | O275: 372 | P275: =O275*2.8 -> 1041.6 | Q275: 4 | R275: 0 | S275: 4 | T275: 4 | U275: 8 | V275: Вертикальный 4*3 | W275: Digital (без звука) | X275: статичный баннер | Y275: 31 | Z275: =AA275/P275 -> 20.15 | AA275: =((P275*2.6*R275/S275/2)/2+(P275*2.6*T275/U275)/2)*Y275 -> 20988.24 | AB275: =AH275/AA275*1000 -> 1524.6633 | AC275: 1 | AE275: =AF275/1.22 -> 6557.377 | AF275: 8000 | AG275: =AE275*Q275 -> 26229.508 | AH275: =AG275*1.22 -> 32000
A276: OREN31 | B276: Оренбургская область | C276: Оренбург | D276: Ленинский | E276: мкрн. 13_15_16 | F276: Б | G276: 46162 | H276: Комфорт | I276: ЖК 15 Микрорайон | J276: улица Братьев Хусаиновых, 2/2 | K276: 51.826299 | L276: 55.173914 | M276: 2019 | N276: 18 | O276: 372 | P276: =O276*2.8 -> 1041.6 | Q276: 4 | R276: 4 | S276: 4 | T276: 0 | U276: 8 | V276: Горизонтальный 4*3 | W276: Digital (без звука) | X276: статичный баннер | Y276: 31 | Z276: =AA276/P276 -> 20.15 | AA276: =((P276*2.6*R276/S276/2)/2+(P276*2.6*T276/U276)/2)*Y276 -> 20988.24 | AB276: =AH276/AA276*1000 -> 1524.6633 | AC276: 1 | AE276: =AF276/1.22 -> 6557.377 | AF276: 8000 | AG276: =AE276*Q276 -> 26229.508 | AH276: =AG276*1.22 -> 32000
A277: OREN32 | B277: Оренбургская область | C277: Оренбург | D277: Ленинский | E277: мкрн. 18_19_20 | F277: Б | G277: 46167 | H277: Комфорт | I277: ЖК 18 микрорайон | J277: улица Диагностики, 17/1 | K277: 51.817770 | L277: 55.168012 | M277: 2007 | N277: 10 | O277: 460 | P277: =O277*2.8 -> 1288 | Q277: 10 | R277: 0 | S277: 10 | T277: 10 | U277: 10 | V277: Вертикальный 4*3 | W277: Digital (без звука) | X277: статичный баннер | Y277: 31 | Z277: =AA277/P277 -> 40.3 | AA277: =((P277*2.6*R277/S277/2)/2+(P277*2.6*T277/U277)/2)*Y277 -> 51906.4 | AB277: =AH277/AA277*1000 -> 1541.2358 | AC277: 1 | AE277: =AF277/1.22 -> 6557.377 | AF277: 8000 | AG277: =AE277*Q277 -> 65573.77 | AH277: =AG277*1.22 -> 80000
A278: OREN32 | B278: Оренбургская область | C278: Оренбург | D278: Ленинский | E278: мкрн. 18_19_20 | F278: Б | G278: 46167 | H278: Комфорт | I278: ЖК 18 микрорайон | J278: улица Салмышская улица, 58 | K278: 51.816579 | L278: 55.171282 | M278: 2007 | N278: 17 | O278: 190 | P278: =O278*2.8 -> 532 | Q278: 2 | R278: 0 | S278: 1 | T278: 10 | U278: 3 | V278: Вертикальный 4*3 | W278: Digital (без звука) | X278: статичный баннер | Y278: 31 | Z278: =AA278/P278 -> 134.33333 | AA278: =((P278*2.6*R278/S278/2)/2+(P278*2.6*T278/U278)/2)*Y278 -> 71465.333 | AB278: =AH278/AA278*1000 -> 223.88477 | AC278: 1 | AE278: =AF278/1.22 -> 6557.377 | AF278: 8000 | AG278: =AE278*Q278 -> 13114.754 | AH278: =AG278*1.22 -> 16000
A279: OREN33 | B279: Оренбургская область | C279: Оренбург | D279: Ленинский | E279: мкрн. 18_19_20 | F279: А | G279: 46167 | H279: Комфорт | I279: ЖК Долгие горы | J279: улица Гаранькина, 26 | K279: 51.807915 | L279: 55.179052 | M279: 2026 | N279: 17 | O279: 192 | P279: =O279*2.8 -> 537.6 | Q279: 6 | R279: 3 | S279: 4 | T279: 3 | U279: 8 | V279: Вертикальный 4*3 | W279: Digital (без звука) | X279: статичный баннер | Y279: 31 | Z279: =AA279/P279 -> 30.225 | AA279: =((P279*2.6*R279/S279/2)/2+(P279*2.6*T279/U279)/2)*Y279 -> 16248.96 | AB279: =AH279/AA279*1000 -> 2954.0352 | AC279: 1 | AE279: =AF279/1.22 -> 6557.377 | AF279: 8000 | AG279: =AE279*Q279 -> 39344.262 | AH279: =AG279*1.22 -> 48000
A280: OREN34 | B280: Оренбургская область | C280: Оренбург | D280: Ленинский | E280: мкрн. 18_19_20 | F280: Б | G280: 46167 | H280: Комфорт | I280: ЖК Фермер | J280: улица Высотная, 2 | K280: 51.815822 | L280: 55.176573 | M280: 2016 | N280: 16 | O280: 240 | P280: =O280*2.8 -> 672 | Q280: 4 | R280: 0 | S280: 4 | T280: 4 | U280: 8 | V280: Вертикальный 4*3 | W280: Digital (без звука) | X280: статичный баннер | Y280: 31 | Z280: =AA280/P280 -> 20.15 | AA280: =((P280*2.6*R280/S280/2)/2+(P280*2.6*T280/U280)/2)*Y280 -> 13540.8 | AB280: =AH280/AA280*1000 -> 2363.2282 | AC280: 1 | AE280: =AF280/1.22 -> 6557.377 | AF280: 8000 | AG280: =AE280*Q280 -> 26229.508 | AH280: =AG280*1.22 -> 32000
A281: OREN34 | B281: Оренбургская область | C281: Оренбург | D281: Ленинский | E281: мкрн. 18_19_20 | F281: Б | G281: 46167 | H281: Комфорт | I281: ЖК Фермер | J281: улица Высотная, 2 | K281: 51.815822 | L281: 55.176574 | M281: 2016 | N281: 16 | O281: 240 | P281: =O281*2.8 -> 672 | Q281: 4 | R281: 4 | S281: 4 | T281: 0 | U281: 8 | V281: Горизонтальный 4*3 | W281: Digital (без звука) | X281: статичный баннер | Y281: 31 | Z281: =AA281/P281 -> 20.15 | AA281: =((P281*2.6*R281/S281/2)/2+(P281*2.6*T281/U281)/2)*Y281 -> 13540.8 | AB281: =AH281/AA281*1000 -> 2363.2282 | AC281: 1 | AE281: =AF281/1.22 -> 6557.377 | AF281: 8000 | AG281: =AE281*Q281 -> 26229.508 | AH281: =AG281*1.22 -> 32000
... A284: OREN35 | B284: Оренбургская область | C284: Оренбург | D284: Ленинский | E284: мкрн. 18_19_20 | F284: А | G284: 46175 | H284: Комфорт | I284: ЖК Диагностики | J284: улица Салмышская, 52/3 | K284: 51.819140 | L284: 55.167716 | M284: 2017 | N284: 14 | O284: 65 | P284: =O284*2.8 -> 182 | Q284: 2 | R284: 1 | S284: 1 | T284: 1 | U284: 2 | V284: Вертикальный 4*3 | W284: Digital (без звука) | X284: статичный баннер | Y284: 31 | Z284: =AA284/P284 -> 40.3 | AA284: =((P284*2.6*R284/S284/2)/2+(P284*2.6*T284/U284)/2)*Y284 -> 7334.6 | AB284: =AH284/AA284*1000 -> 2181.4414 | AC284: 1 | AE284: =AF284/1.22 -> 6557.377 | AF284: 8000 | AG284: =AE284*Q284 -> 13114.754 | AH284: =AG284*1.22 -> 16000
A285: OREN35 | B285: Оренбургская область | C285: Оренбург | D285: Ленинский | F285: А | G285: 46255 | H285: Комфорт | I285: ЖК Диагностики | J285: улица Салмышская, 56А | K285: 51.816679 | L285: 55.172315 | M285: 2017 | N285: 10 | O285: 40 | P285: =O285*2.8 -> 112 | Q285: 2 | R285: 1 | S285: 1 | T285: 1 | U285: 2 | V285: Вертикальный 4*3 | W285: Digital (без звука) | X285: статичный баннер | Y285: 31 | Z285: =AA285/P285 -> 40.3 | AA285: =((P285*2.6*R285/S285/2)/2+(P285*2.6*T285/U285)/2)*Y285 -> 4513.6 | AB285: =AH285/AA285*1000 -> 3544.8423 | AC285: 1 | AE285: =AF285/1.22 -> 6557.377 | AF285: 8000 | AG285: =AE285*Q285 -> 13114.754 | AH285: =AG285*1.22 -> 16000
A286: OREN36 | B286: Оренбургская область | C286: Оренбург | D286: Ленинский | E286: мкрн. Дубки | F286: Б | G286: 46190 | H286: Комфорт | I286: ЖК Чкалова | J286: улица Чкалова, 51/1 | K286: 51.769944 | L286: 55.135017 | M286: 2014 | N286: 20 | O286: 401 | P286: =O286*2.8 -> 1122.8 | Q286: 12 | R286: 6 | S286: 6 | T286: 6 | U286: 12 | V286: Вертикальный 4*3 | W286: Digital (без звука) | X286: статичный баннер | Y286: 31 | Z286: =AA286/P286 -> 40.3 | AA286: =((P286*2.6*R286/S286/2)/2+(P286*2.6*T286/U286)/2)*Y286 -> 45248.84 | AB286: =AH286/AA286*1000 -> 2121.6013 | AC286: 1 | AE286: =AF286/1.22 -> 6557.377 | AF286: 8000 | AG286: =AE286*Q286 -> 78688.525 | AH286: =AG286*1.22 -> 96000
A287: OREN36 | B287: Оренбургская область | C287: Оренбург | D287: Ленинский | E287: мкрн. Дубки | F287: Б | G287: 46190 | H287: Комфорт | I287: ЖК Чкалова | J287: улица Чкалова, 53/3 | K287: 51.771203 | L287: 55.138421 | M287: 2017 | N287: 15 | O287: 120 | P287: =O287*2.8 -> 336 | Q287: 2 | R287: 1 | S287: 1 | T287: 1 | U287: 2 | V287: Вертикальный 4*3 | W287: Digital (без звука) | X287: статичный баннер | Y287: 31 | Z287: =AA287/P287 -> 40.3 | AA287: =((P287*2.6*R287/S287/2)/2+(P287*2.6*T287/U287)/2)*Y287 -> 13540.8 | AB287: =AH287/AA287*1000 -> 1181.6141 | AC287: 1 | AE287: =AF287/1.22 -> 6557.377 | AF287: 8000 | AG287: =AE287*Q287 -> 13114.754 | AH287: =AG287*1.22 -> 16000
A288: OREN37 | B288: Оренбургская область | C288: Оренбург | D288: Ленинский | E288: мкрн. 13_15_16 | F288: Б | G288: 46190 | H288: Комфорт | I288: ЖК Северный проезд | J288: Северный проезд, 24 | K288: 51.827445 | L288: 55.173078 | M288: 2019 | N288: 14 | O288: 182 | P288: =O288*2.8 -> 509.6 | Q288: 4 | R288: 2 | S288: 2 | T288: 2 | U288: 4 | V288: Вертикальный 4*3 | W288: Digital (без звука) | X288: статичный баннер | Y288: 31 | Z288: =AA288/P288 -> 40.3 | AA288: =((P288*2.6*R288/S288/2)/2+(P288*2.6*T288/U288)/2)*Y288 -> 20536.88 | AB288: =AH288/AA288*1000 -> 1558.1724 | AC288: 1 | AE288: =AF288/1.22 -> 6557.377 | AF288: 8000 | AG288: =AE288*Q288 -> 26229.508 | AH288: =AG288*1.22 -> 32000
A289: OREN37 | B289: Оренбургская область | C289: Оренбург | D289: Ленинский | E289: мкрн. 13_15_16 | F289: Б | G289: 46247 | H289: Комфорт | I289: ЖК Северный проезд | J289: Северный проезд, 20/1 | K289: 51.826772 | L289: 55.171453 | M289: 2018 | N289: 14 | O289: 182 | P289: =O289*2.8 -> 509.6 | Q289: 4 | R289: 2 | S289: 2 | T289: 2 | U289: 4 | V289: Вертикальный 4*3 | W289: Digital (без звука) | X289: статичный баннер | Y289: 31 | Z289: =AA289/P289 -> 40.3 | AA289: =((P289*2.6*R289/S289/2)/2+(P289*2.6*T289/U289)/2)*Y289 -> 20536.88 | AB289: =AH289/AA289*1000 -> 1558.1724 | AC289: 1 | AE289: =AF289/1.22 -> 6557.377 | AF289: 8000 | AG289: =AE289*Q289 -> 26229.508 | AH289: =AG289*1.22 -> 32000
A290: OREN38 | B290: Оренбургская область | C290: Оренбург | D290: Ленинский | E290: мкрн. 18_19_20 | F290: Б | G290: 46203 | H290: Комфорт | I290: ЖК Фермер 2 | J290: улица Диагностики, 9/1 | K290: 51.818327 | L290: 55.166916 | M290: 2009 | N290: 11 | O290: 100 | P290: =O290*2.8 -> 280 | Q290: 4 | R290: 2 | S290: 2 | T290: 2 | U290: 2 | V290: Вертикальный 4*3 | W290: Digital (без звука) | X290: статичный баннер | Y290: 31 | Z290: =AA290/P290 -> 60.45 | AA290: =((P290*2.6*R290/S290/2)/2+(P290*2.6*T290/U290)/2)*Y290 -> 16926 | AB290: =AH290/AA290*1000 -> 1890.5825 | AC290: 1 | AE290: =AF290/1.22 -> 6557.377 | AF290: 8000 | AG290: =AE290*Q290 -> 26229.508 | AH290: =AG290*1.22 -> 32000
A291: OREN38 | B291: Оренбургская область | C291: Оренбург | D291: Ленинский | E291: мкрн. 18_19_20 | F291: Б | G291: 46203 | H291: Комфорт | I291: ЖК Фермер 2 | J291: улица Диагностики, 9 | K291: 51.818695 | L291: 55.167221 | M291: 2007 | N291: 11 | O291: 100 | P291: =O291*2.8 -> 280 | Q291: 4 | R291: 2 | S291: 2 | T291: 2 | U291: 2 | V291: Вертикальный 4*3 | W291: Digital (без звука) | X291: статичный баннер | Y291: 31 | Z291: =AA291/P291 -> 60.45 | AA291: =((P291*2.6*R291/S291/2)/2+(P291*2.6*T291/U291)/2)*Y291 -> 16926 | AB291: =AH291/AA291*1000 -> 1890.5825 | AC291: 1 | AE291: =AF291/1.22 -> 6557.377 | AF291: 8000 | AG291: =AE291*Q291 -> 26229.508 | AH291: =AG291*1.22 -> 32000
A292: OREN38 | B292: Оренбургская область | C292: Оренбург | D292: Ленинский | E292: мкрн. 18_19_20 | F292: Б | G292: 46203 | H292: Комфорт | I292: ЖК Фермер 2 | J292: улица Салмышская, 48/2 | K292: 51.821061 | L292: 55.167608 | M292: 2008 | N292: 17 | O292: 101 | P292: =O292*2.8 -> 282.8 | Q292: 2 | R292: 1 | S292: 1 | T292: 1 | U292: 2 | V292: Вертикальный 4*3 | W292: Digital (без звука) | X292: статичный баннер | Y292: 31 | Z292: =AA292/P292 -> 40.3 | AA292: =((P292*2.6*R292/S292/2)/2+(P292*2.6*T292/U292)/2)*Y292 -> 11396.84 | AB292: =AH292/AA292*1000 -> 1403.8979 | AC292: 1 | AE292: =AF292/1.22 -> 6557.377 | AF292: 8000 | AG292: =AE292*Q292 -> 13114.754 | AH292: =AG292*1.22 -> 16000
A293: OREN39 | B293: Оренбургская область | C293: Оренбург | D293: Ленинский | E293: мкрн. 13_15_16 | F293: Б | G293: 46203 | H293: Комфорт | I293: ЖК Поляничко | J293: улица Поляничко, 2А | K293: 51.825158 | L293: 55.170087 | M293: 2016 | N293: 15 | O293: 120 | P293: =O293*2.8 -> 336 | Q293: 2 | R293: 1 | S293: 1 | T293: 1 | U293: 2 | V293: Вертикальный 4*3 | W293: Digital (без звука) | X293: статичный баннер | Y293: 31 | Z293: =AA293/P293 -> 40.3 | AA293: =((P293*2.6*R293/S293/2)/2+(P293*2.6*T293/U293)/2)*Y293 -> 13540.8 | AB293: =AH293/AA293*1000 -> 1181.6141 | AC293: 1 | AE293: =AF293/1.22 -> 6557.377 | AF293: 8000 | AG293: =AE293*Q293 -> 13114.754 | AH293: =AG293*1.22 -> 16000
A294: OREN39 | B294: Оренбургская область | C294: Оренбург | D294: Ленинский | E294: мкрн. 13_15_16 | F294: Б | G294: 46203 | H294: Комфорт | I294: ЖК Поляничко | J294: улица Поляничко, 7/1 | K294: 51.825141 | L294: 55.174588 | M294: 2018 | N294: 14 | O294: 216 | P294: =O294*2.8 -> 604.8 | Q294: 8 | R294: 4 | S294: 4 | T294: 4 | U294: 8 | V294: Вертикальный 4*3 | W294: Digital (без звука) | X294: статичный баннер | Y294: 31 | Z294: =AA294/P294 -> 40.3 | AA294: =((P294*2.6*R294/S294/2)/2+(P294*2.6*T294/U294)/2)*Y294 -> 24373.44 | AB294: =AH294/AA294*1000 -> 2625.8091 | AC294: 1 | AE294: =AF294/1.22 -> 6557.377 | AF294: 8000 | AG294: =AE294*Q294 -> 52459.016 | AH294: =AG294*1.22 -> 64000
A295: OREN40 | B295: Оренбургская область | C295: Оренбург | D295: Дзержинский | E295: мкрн. 13_15_16 | F295: Б | G295: 46216 | H295: Комфорт | I295: ЖК Просторная | J295: улица Просторная, 19/2 | K295: 51.838259 | L295: 55.157861 | M295: 2008 | N295: 14 | O295: 187 | P295: =O295*2.8 -> 523.6 | Q295: 4 | R295: 0 | S295: 4 | T295: 4 | U295: 8 | V295: Вертикальный 4*3 | W295: Digital (без звука) | X295: статичный баннер | Y295: 31 | Z295: =AA295/P295 -> 20.15 | AA295: =((P295*2.6*R295/S295/2)/2+(P295*2.6*T295/U295)/2)*Y295 -> 10550.54 | AB295: =AH295/AA295*1000 -> 3033.0201 | AC295: 1 | AE295: =AF295/1.22 -> 6557.377 | AF295: 8000 | AG295: =AE295*Q295 -> 26229.508 | AH295: =AG295*1.22 -> 32000
A296: OREN41 | B296: Оренбургская область | C296: Оренбург | D296: Промышленный | E296: Промышленный_Центр | F296: Б | G296: 46216 | H296: Комфорт | I296: ЖК Юркина | J296: улица Юркина, 6 | K296: 51.800441 | L296: 55.080076 | M296: 2025 | N296: 24 | O296: 400 | P296: =O296*2.8 -> 1120 | Q296: 7 | R296: 0 | S296: 3 | T296: 7 | U296: 6 | V296: Вертикальный 4*3 | W296: Digital (без звука) | X296: статичный баннер | Y296: 31 | Z296: =AA296/P296 -> 47.016667 | AA296: =((P296*2.6*R296/S296/2)/2+(P296*2.6*T296/U296)/2)*Y296 -> 52658.667 | AB296: =AH296/AA296*1000 -> 1063.4527 | AC296: 1 | AE296: =AF296/1.22 -> 6557.377 | AF296: 8000 | AG296: =AE296*Q296 -> 45901.639 | AH296: =AG296*1.22 -> 56000
A297: OREN41 | B297: Оренбургская область | C297: Оренбург | D297: Промышленный | E297: Промышленный_Центр | F297: Б | G297: 46247 | H297: Комфорт | I297: ЖК Юркина | J297: улица Юркина, 2 | K297: 51.800575 | L297: 55.076752 | M297: 2025 | N297: 24 | O297: 721 | P297: =O297*2.8 -> 2018.8 | Q297: 4 | R297: 1 | S297: 3 | T297: 3 | U297: 9 | V297: Вертикальный 4*3 | W297: Digital (без звука) | X297: статичный баннер | Y297: 31 | Z297: =AA297/P297 -> 20.15 | AA297: =((P297*2.6*R297/S297/2)/2+(P297*2.6*T297/U297)/2)*Y297 -> 40678.82 | AB297: =AH297/AA297*1000 -> 786.65015 | AC297: 1 | AE297: =AF297/1.22 -> 6557.377 | AF297: 8000 | AG297: =AE297*Q297 -> 26229.508 | AH297: =AG297*1.22 -> 32000
... A311: OREN47 | B311: Оренбургская область | C311: Оренбург | D311: Ленинский | E311: мкрн. 18_19_20 | F311: Б | G311: 46260 | H311: Комфорт | I311: ЖК Высотная | J311: улица Высотная, 6 | K311: 51.816481 | L311: 55.178547 | M311: 2013 | N311: 14 | O311: 139 | P311: =O311*2.8 -> 389.2 | Q311: 2 | R311: 0 | S311: 2 | T311: 2 | U311: 4 | V311: Вертикальный 4*3 | W311: Digital (без звука) | X311: статичный баннер | Y311: 31 | Z311: =AA311/P311 -> 20.15 | AA311: =((P311*2.6*R311/S311/2)/2+(P311*2.6*T311/U311)/2)*Y311 -> 7842.38 | AB311: =AH311/AA311*1000 -> 2040.197 | AC311: 1 | AE311: =AF311/1.22 -> 6557.377 | AF311: 8000 | AG311: =AE311*Q311 -> 13114.754 | AH311: =AG311*1.22 -> 16000
A312: OREN48 | B312: Оренбургская область | C312: Оренбург | D312: Ленинский | F312: Б | G312: 46255 | H312: Комфорт | I312: ЖК Движение | J312: улица Братьев Хусаиновых, 4 | K312: 51.826627 | L312: 55.175917 | M312: 2020 | N312: 18 | O312: 359 | P312: =O312*2.8 -> 1005.2 | Q312: 6 | R312: 3 | S312: 3 | T312: 3 | U312: 3 | V312: Вертикальный 4*3 | W312: Digital (без звука) | X312: статичный баннер | Y312: 31 | Z312: =AA312/P312 -> 60.45 | AA312: =((P312*2.6*R312/S312/2)/2+(P312*2.6*T312/U312)/2)*Y312 -> 60764.34 | AB312: =AH312/AA312*1000 -> 789.93699 | AC312: 1 | AE312: =AF312/1.22 -> 6557.377 | AF312: 8000 | AG312: =AE312*Q312 -> 39344.262 | AH312: =AG312*1.22 -> 48000
A313: OREN49 | B313: Оренбургская область | C313: Оренбург | D313: Ленинский | F313: Б | G313: 46258 | H313: Комфорт | I313: ЖК Грандпарк | J313: улица Ильи Глазунова, 12 | K313: 51.761934 | L313: 55.216413 | M313: 2026 | N313: 13 | O313: 156 | P313: =O313*2.8 -> 436.8 | Q313: 3 | R313: 0 | S313: 3 | T313: 3 | U313: 6 | V313: Вертикальный 4*3 | W313: Digital (без звука) | X313: статичный баннер | Y313: 31 | Z313: =AA313/P313 -> 20.15 | AA313: =((P313*2.6*R313/S313/2)/2+(P313*2.6*T313/U313)/2)*Y313 -> 8801.52 | AB313: =AH313/AA313*1000 -> 2726.8017 | AC313: 1 | AE313: =AF313/1.22 -> 6557.377 | AF313: 8000 | AG313: =AE313*Q313 -> 19672.131 | AH313: =AG313*1.22 -> 24000
A314: OREN49 | B314: Оренбургская область | C314: Оренбург | D314: Ленинский | F314: Б | G314: 46258 | H314: Комфорт | I314: ЖК Грандпарк | J314: улица Ильи Глазунова, 10 | K314: 51.761254 | L314: 55.215479 | M314: 2025 | N314: 10 | O314: 160 | P314: =O314*2.8 -> 448 | Q314: 4 | R314: 0 | S314: 4 | T314: 4 | U314: 6 | V314: Вертикальный 4*3 | W314: Digital (без звука) | X314: статичный баннер | Y314: 31 | Z314: =AA314/P314 -> 26.866667 | AA314: =((P314*2.6*R314/S314/2)/2+(P314*2.6*T314/U314)/2)*Y314 -> 12036.267 | AB314: =AH314/AA314*1000 -> 2658.6317 | AC314: 1 | AE314: =AF314/1.22 -> 6557.377 | AF314: 8000 | AG314: =AE314*Q314 -> 26229.508 | AH314: =AG314*1.22 -> 32000
...

Sheet Выбор адресов
D1: Основной эфир | P1: Генеральный баннер
A3: Выберите регион | B3: Выберите город | C3: Выберите ЖК | D3: Количество показов в сутки на 1 экран | E3: Количество показов в месяц | F3: Количество квартир | G3: Всего экранов | H3: Хронометраж ролика, сек. | I3: OTS за период | J3: Стоимость размещения в 1 доме/1 месяц, руб. в т.ч.НДС 22% | K3: GID | L3: Категория ЖК | M3: тип города | N3: скидка по категории | O3: стоимость с учетом скидки | P3: Количество квартир | Q3: Всего экранов | R3: OTS за период | S3: Стоимость размещения в 1 доме/1 месяц, руб. в т.ч.НДС 22% | T3: GID | U3: Категория ЖК | V3: тип города | W3: скидка по категории | X3: стоимость с учетом скидки
A4: Республика Башкортостан | B4: Уфа | C4: ЖК Видинеевский | D4: =IFERROR(__xludf.DUMMYFUNCTION("IFERROR(sum(filter('Основной эфир'!$AA:$AA, 'Основной эфир'!$B:$B=$A4,'Основной эфир'!$C:$C=$B4,'Основной эфир'!$I:$I=$C4)), 0) "),2880.0) -> 2880 | E4: =IFERROR(__xludf.DUMMYFUNCTION("IFERROR(sum(filter('Основной эфир'!$AC:$AC, 'Основной эфир'!$B:$B=$A4,'Основной эфир'!$C:$C=$B4,'Основной эфир'!$I:$I=$C4)), 0) "),214272.0) -> 214272 | F4: =IFERROR(__xludf.DUMMYFUNCTION("IFERROR(sum(filter('Основной эфир'!$O:$O, 'Основной эфир'!$B:$B=$A4,'Основной эфир'!$C:$C=$B4,'Основной эфир'!$I:$I=$C4)), 0) "),1339.0) -> 1339 | G4: =IFERROR(__xludf.DUMMYFUNCTION("IFERROR(sum(filter('Основной эфир'!$Q:$Q, 'Основной эфир'!$B:$B=$A4,'Основной эфир'!$C:$C=$B4,'Основной эфир'!$I:$I=$C4)), 0) "),12.0) -> 12 | H4: =IFERROR(__xludf.DUMMYFUNCTION("IFERROR(AVERAGE(filter('Основной эфир'!$Y:$Y, 'Основной эфир'!$B:$B=$A4,'Основной эфир'!$C:$C=$B4,'Основной эфир'!$I:$I=$C4)), 0) "),10.0) -> 10 | I4: =IFERROR(__xludf.DUMMYFUNCTION("IFERROR(AVERAGE(filter('Основной эфир'!$AE:$AE, 'Основной эфир'!$B:$B=$A4,'Основной эфир'!$C:$C=$B4,'Основной эфир'!$I:$I=$C4)), 0) "),11882.302755555556) -> 11882.303 | J4: =IFERROR(__xludf.DUMMYFUNCTION("IFERROR(SUM(filter('Основной эфир'!$AL:$AL, 'Основной эфир'!$B:$B=$A4,'Основной эфир'!$C:$C=$B4,'Основной эфир'!$I:$I=$C4)), 0) "),48000.0) -> 48000 | K4: =IFERROR(__xludf.DUMMYFUNCTION("IFERROR(REGEXREPLACE(unique(filter('Основной эфир'!$A:$A, 'Основной эфир'!$B:$B=$A4,'Основной эфир'!$C:$C=$B4,'Основной эфир'!$I:$I=$C4)), ""\d+"", """"),"""")"),"U") -> U | L4: =IFERROR(__xludf.DUMMYFUNCTION("IFERROR(unique(filter('Основной эфир'!$F:$F, 'Основной эфир'!$B:$B=$A4,'Основной эфир'!$C:$C=$B4,'Основной эфир'!$I:$I=$C4)),"""")"),"А") -> А | M4: =if(C4<>"",if(or(lower(K4)="u",lower(K4)="nn",lower(K4)="kzn"),"миллионник",if(lower(K4)="msc","мск","остальное")),"") -> миллионник | N4: =IFERROR(__xludf.DUMMYFUNCTION("IFERROR(SWITCH(lower(join("" "",L4:M4)),""а миллионник"", 62.5,""б миллионник"", 75,""а мск"", 50, ""б мск"", 62.5, ""a остальное"", 70, ""б остальное"", 80)/100,0)"),0.625) -> 0.625 | O4: =IFERROR(J4-J4*N4,0) -> 18000 | P4: =IFERROR(__xludf.DUMMYFUNCTION("IFERROR(sum(filter('Генеральный баннер'!$O:$O, 'Генеральный баннер'!$B:$B=$A4,'Генеральный баннер'!$C:$C=$B4,'Генеральный баннер'!$I:$I=$C4)), 0) "),1339.0) -> 1339 | Q4: =IFERROR(__xludf.DUMMYFUNCTION("IFERROR(sum(filter('Генеральный баннер'!$Q:$Q, 'Генеральный баннер'!$B:$B=$A4,'Генеральный баннер'!$C:$C=$B4,'Генеральный баннер'!$I:$I=$C4)), 0) "),12.0) -> 12 | R4: =IFERROR(__xludf.DUMMYFUNCTION("IFERROR(AVERAGE(filter('Генеральный баннер'!$AA:$AA, 'Генеральный баннер'!$B:$B=$A4,'Генеральный баннер'!$C:$C=$B4,'Генеральный баннер'!$I:$I=$C4)), 0) "),23805.478666666666) -> 23805.479 | S4: =IFERROR(__xludf.DUMMYFUNCTION("IFERROR(SUM(filter('Генеральный баннер'!$AH:$AH, 'Генеральный баннер'!$B:$B=$A4,'Генеральный баннер'!$C:$C=$B4,'Генеральный баннер'!$I:$I=$C4)), 0) "),96000.0) -> 96000 | T4: =IFERROR(__xludf.DUMMYFUNCTION("IFERROR(REGEXREPLACE(unique(filter('Генеральный баннер'!$A:$A, 'Генеральный баннер'!$B:$B=$A4,'Генеральный баннер'!$C:$C=$B4,'Генеральный баннер'!$I:$I=$C4)), ""\d+"", """"),"""")"),"U") -> U | U4: =IFERROR(__xludf.DUMMYFUNCTION("IFERROR(unique(filter('Генеральный баннер'!$F:$F, 'Генеральный баннер'!$B:$B=$A4,'Генеральный баннер'!$C:$C=$B4,'Генеральный баннер'!$I:$I=$C4)),"""")"),"А") -> А | V4: =if(L4<>"",if(or(lower(T4)="u",lower(T4)="nn",lower(T4)="kzn"),"миллионник",if(lower(T4)="msc","мск","остальное")),"") -> миллионник | W4: =IFERROR(__xludf.DUMMYFUNCTION("IFERROR(SWITCH(lower(join("" "",U4:V4)),""а миллионник"", 62.5,""б миллионник"", 75,""а мск"", 50, ""б мск"", 62.5, ""a остальное"", 70, ""б остальное"", 80)/100,0)"),0.625) -> 0.625 | X4: =IFERROR(S4-S4*W4,0) -> 36000
A5: Республика Башкортостан | B5: Уфа | C5: ЖК Южный | D5: =IFERROR(__xludf.DUMMYFUNCTION("IFERROR(sum(filter('Основной эфир'!$AA:$AA, 'Основной эфир'!$B:$B=$A5,'Основной эфир'!$C:$C=$B5,'Основной эфир'!$I:$I=$C5)), 0) "),576.0) -> 576 | E5: =IFERROR(__xludf.DUMMYFUNCTION("IFERROR(sum(filter('Основной эфир'!$AC:$AC, 'Основной эфир'!$B:$B=$A5,'Основной эфир'!$C:$C=$B5,'Основной эфир'!$I:$I=$C5)), 0) "),53568.0) -> 53568 | F5: =IFERROR(__xludf.DUMMYFUNCTION("IFERROR(sum(filter('Основной эфир'!$O:$O, 'Основной эфир'!$B:$B=$A5,'Основной эфир'!$C:$C=$B5,'Основной эфир'!$I:$I=$C5)), 0) "),301.0) -> 301 | G5: =IFERROR(__xludf.DUMMYFUNCTION("IFERROR(sum(filter('Основной эфир'!$Q:$Q, 'Основной эфир'!$B:$B=$A5,'Основной эфир'!$C:$C=$B5,'Основной эфир'!$I:$I=$C5)), 0) "),3.0) -> 3 | H5: =IFERROR(__xludf.DUMMYFUNCTION("IFERROR(AVERAGE(filter('Основной эфир'!$Y:$Y, 'Основной эфир'!$B:$B=$A5,'Основной эфир'!$C:$C=$B5,'Основной эфир'!$I:$I=$C5)), 0) "),10.0) -> 10 | I5: =IFERROR(__xludf.DUMMYFUNCTION("IFERROR(AVERAGE(filter('Основной эфир'!$AE:$AE, 'Основной эфир'!$B:$B=$A5,'Основной эфир'!$C:$C=$B5,'Основной эфир'!$I:$I=$C5)), 0) "),19473.174933333332) -> 19473.175 | J5: =IFERROR(__xludf.DUMMYFUNCTION("IFERROR(SUM(filter('Основной эфир'!$AL:$AL, 'Основной эфир'!$B:$B=$A5,'Основной эфир'!$C:$C=$B5,'Основной эфир'!$I:$I=$C5)), 0) "),11999.999999999998) -> 12000 | K5: =IFERROR(__xludf.DUMMYFUNCTION("IFERROR(REGEXREPLACE(unique(filter('Основной эфир'!$A:$A, 'Основной эфир'!$B:$B=$A5,'Основной эфир'!$C:$C=$B5,'Основной эфир'!$I:$I=$C5)), ""\d+"", """"),"""")"),"U") -> U | L5: =IFERROR(__xludf.DUMMYFUNCTION("IFERROR(unique(filter('Основной эфир'!$F:$F, 'Основной эфир'!$B:$B=$A5,'Основной эфир'!$C:$C=$B5,'Основной эфир'!$I:$I=$C5)),"""")"),"Б") -> Б | M5: =if(C5<>"",if(or(lower(K5)="u",lower(K5)="nn",lower(K5)="kzn"),"миллионник",if(lower(K5)="msc","мск","остальное")),"") -> миллионник | N5: =IFERROR(__xludf.DUMMYFUNCTION("IFERROR(SWITCH(lower(join("" "",L5:M5)),""а миллионник"", 62.5,""б миллионник"", 75,""а мск"", 50, ""б мск"", 62.5, ""a остальное"", 70, ""б остальное"", 80)/100,0)"),0.75) -> 0.75 | O5: =IFERROR(J5-J5*N5,0) -> 3000 | P5: =IFERROR(__xludf.DUMMYFUNCTION("IFERROR(sum(filter('Генеральный баннер'!$O:$O, 'Генеральный баннер'!$B:$B=$A5,'Генеральный баннер'!$C:$C=$B5,'Генеральный баннер'!$I:$I=$C5)), 0) "),301.0) -> 301 | Q5: =IFERROR(__xludf.DUMMYFUNCTION("IFERROR(sum(filter('Генеральный баннер'!$Q:$Q, 'Генеральный баннер'!$B:$B=$A5,'Генеральный баннер'!$C:$C=$B5,'Генеральный баннер'!$I:$I=$C5)), 0) "),3.0) -> 3 | R5: =IFERROR(__xludf.DUMMYFUNCTION("IFERROR(AVERAGE(filter('Генеральный баннер'!$AA:$AA, 'Генеральный баннер'!$B:$B=$A5,'Генеральный баннер'!$C:$C=$B5,'Генеральный баннер'!$I:$I=$C5)), 0) "),33964.84) -> 33964.84 | S5: =IFERROR(__xludf.DUMMYFUNCTION("IFERROR(SUM(filter('Генеральный баннер'!$AH:$AH, 'Генеральный баннер'!$B:$B=$A5,'Генеральный баннер'!$C:$C=$B5,'Генеральный баннер'!$I:$I=$C5)), 0) "),23999.999999999996) -> 24000 | T5: =IFERROR(__xludf.DUMMYFUNCTION("IFERROR(REGEXREPLACE(unique(filter('Генеральный баннер'!$A:$A, 'Генеральный баннер'!$B:$B=$A5,'Генеральный баннер'!$C:$C=$B5,'Генеральный баннер'!$I:$I=$C5)), ""\d+"", """"),"""")"),"U") -> U | U5: =IFERROR(__xludf.DUMMYFUNCTION("IFERROR(unique(filter('Генеральный баннер'!$F:$F, 'Генеральный баннер'!$B:$B=$A5,'Генеральный баннер'!$C:$C=$B5,'Генеральный баннер'!$I:$I=$C5)),"""")"),"Б") -> Б | V5: =if(L5<>"",if(or(lower(T5)="u",lower(T5)="nn",lower(T5)="kzn"),"миллионник",if(lower(T5)="msc","мск","остальное")),"") -> миллионник | W5: =IFERROR(__xludf.DUMMYFUNCTION("IFERROR(SWITCH(lower(join("" "",U5:V5)),""а миллионник"", 62.5,""б миллионник"", 75,""а мск"", 50, ""б мск"", 62.5, ""a остальное"", 70, ""б остальное"", 80)/100,0)"),0.75) -> 0.75 | X5: =IFERROR(S5-S5*W5,0) -> 6000
A6: Московская область | B6: Внуково | C6: ЖК Новое Внуково 1 | D6: =IFERROR(__xludf.DUMMYFUNCTION("IFERROR(sum(filter('Основной эфир'!$AA:$AA, 'Основной эфир'!$B:$B=$A6,'Основной эфир'!$C:$C=$B6,'Основной эфир'!$I:$I=$C6)), 0) "),2304.0) -> 2304 | E6: =IFERROR(__xludf.DUMMYFUNCTION("IFERROR(sum(filter('Основной эфир'!$AC:$AC, 'Основной эфир'!$B:$B=$A6,'Основной эфир'!$C:$C=$B6,'Основной эфир'!$I:$I=$C6)), 0) "),124992.0) -> 124992 | F6: =IFERROR(__xludf.DUMMYFUNCTION("IFERROR(sum(filter('Основной эфир'!$O:$O, 'Основной эфир'!$B:$B=$A6,'Основной эфир'!$C:$C=$B6,'Основной эфир'!$I:$I=$C6)), 0) "),778.0) -> 778 | G6: =IFERROR(__xludf.DUMMYFUNCTION("IFERROR(sum(filter('Основной эфир'!$Q:$Q, 'Основной эфир'!$B:$B=$A6,'Основной эфир'!$C:$C=$B6,'Основной эфир'!$I:$I=$C6)), 0) "),7.0) -> 7 | H6: =IFERROR(__xludf.DUMMYFUNCTION("IFERROR(AVERAGE(filter('Основной эфир'!$Y:$Y, 'Основной эфир'!$B:$B=$A6,'Основной эфир'!$C:$C=$B6,'Основной эфир'!$I:$I=$C6)), 0) "),10.0) -> 10 | I6: =IFERROR(__xludf.DUMMYFUNCTION("IFERROR(AVERAGE(filter('Основной эфир'!$AE:$AE, 'Основной эфир'!$B:$B=$A6,'Основной эфир'!$C:$C=$B6,'Основной эфир'!$I:$I=$C6)), 0) "),2977.0953333333327) -> 2977.0953 | J6: =IFERROR(__xludf.DUMMYFUNCTION("IFERROR(SUM(filter('Основной эфир'!$AL:$AL, 'Основной эфир'!$B:$B=$A6,'Основной эфир'!$C:$C=$B6,'Основной эфир'!$I:$I=$C6)), 0) "),28000.0) -> 28000 | K6: =IFERROR(__xludf.DUMMYFUNCTION("IFERROR(REGEXREPLACE(unique(filter('Основной эфир'!$A:$A, 'Основной эфир'!$B:$B=$A6,'Основной эфир'!$C:$C=$B6,'Основной эфир'!$I:$I=$C6)), ""\d+"", """"),"""")"),"MSC") -> MSC | L6: =IFERROR(__xludf.DUMMYFUNCTION("IFERROR(unique(filter('Основной эфир'!$F:$F, 'Основной эфир'!$B:$B=$A6,'Основной эфир'!$C:$C=$B6,'Основной эфир'!$I:$I=$C6)),"""")"),"А") -> А | M6: =if(C6<>"",if(or(lower(K6)="u",lower(K6)="nn",lower(K6)="kzn"),"миллионник",if(lower(K6)="msc","мск","остальное")),"") -> мск | N6: =IFERROR(__xludf.DUMMYFUNCTION("IFERROR(SWITCH(lower(join("" "",L6:M6)),""а миллионник"", 62.5,""б миллионник"", 75,""а мск"", 50, ""б мск"", 62.5, ""a остальное"", 70, ""б остальное"", 80)/100,0)"),0.5) -> 0.5 | O6: =IFERROR(J6-J6*N6,0) -> 14000 | P6: =IFERROR(__xludf.DUMMYFUNCTION("IFERROR(sum(filter('Генеральный баннер'!$O:$O, 'Генеральный баннер'!$B:$B=$A6,'Генеральный баннер'!$C:$C=$B6,'Генеральный баннер'!$I:$I=$C6)), 0) "),778.0) -> 778 | Q6: =IFERROR(__xludf.DUMMYFUNCTION("IFERROR(sum(filter('Генеральный баннер'!$Q:$Q, 'Генеральный баннер'!$B:$B=$A6,'Генеральный баннер'!$C:$C=$B6,'Генеральный баннер'!$I:$I=$C6)), 0) "),7.0) -> 7 | R6: =IFERROR(__xludf.DUMMYFUNCTION("IFERROR(AVERAGE(filter('Генеральный баннер'!$AA:$AA, 'Генеральный баннер'!$B:$B=$A6,'Генеральный баннер'!$C:$C=$B6,'Генеральный баннер'!$I:$I=$C6)), 0) "),7442.738333333333) -> 7442.7383 | S6: =IFERROR(__xludf.DUMMYFUNCTION("IFERROR(SUM(filter('Генеральный баннер'!$AH:$AH, 'Генеральный баннер'!$B:$B=$A6,'Генеральный баннер'!$C:$C=$B6,'Генеральный баннер'!$I:$I=$C6)), 0) "),56000.0) -> 56000 | T6: =IFERROR(__xludf.DUMMYFUNCTION("IFERROR(REGEXREPLACE(unique(filter('Генеральный баннер'!$A:$A, 'Генеральный баннер'!$B:$B=$A6,'Генеральный баннер'!$C:$C=$B6,'Генеральный баннер'!$I:$I=$C6)), ""\d+"", """"),"""")"),"MSC") -> MSC | U6: =IFERROR(__xludf.DUMMYFUNCTION("IFERROR(unique(filter('Генеральный баннер'!$F:$F, 'Генеральный баннер'!$B:$B=$A6,'Генеральный баннер'!$C:$C=$B6,'Генеральный баннер'!$I:$I=$C6)),"""")"),"А") -> А | V6: =if(L6<>"",if(or(lower(T6)="u",lower(T6)="nn",lower(T6)="kzn"),"миллионник",if(lower(T6)="msc","мск","остальное")),"") -> мск | W6: =IFERROR(__xludf.DUMMYFUNCTION("IFERROR(SWITCH(lower(join("" "",U6:V6)),""а миллионник"", 62.5,""б миллионник"", 75,""а мск"", 50, ""б мск"", 62.5, ""a остальное"", 70, ""б остальное"", 80)/100,0)"),0.5) -> 0.5 | X6: =IFERROR(S6-S6*W6,0) -> 28000
A7: Республика Татарстан | B7: Усады | C7: ЖК Счастливый | D7: =IFERROR(__xludf.DUMMYFUNCTION("IFERROR(sum(filter('Основной эфир'!$AA:$AA, 'Основной эфир'!$B:$B=$A7,'Основной эфир'!$C:$C=$B7,'Основной эфир'!$I:$I=$C7)), 0) "),4032.0) -> 4032 | E7: =IFERROR(__xludf.DUMMYFUNCTION("IFERROR(sum(filter('Основной эфир'!$AC:$AC, 'Основной эфир'!$B:$B=$A7,'Основной эфир'!$C:$C=$B7,'Основной эфир'!$I:$I=$C7)), 0) "),214272.0) -> 214272 | F7: =IFERROR(__xludf.DUMMYFUNCTION("IFERROR(sum(filter('Основной эфир'!$O:$O, 'Основной эфир'!$B:$B=$A7,'Основной эфир'!$C:$C=$B7,'Основной эфир'!$I:$I=$C7)), 0) "),1069.0) -> 1069 | G7: =IFERROR(__xludf.DUMMYFUNCTION("IFERROR(sum(filter('Основной эфир'!$Q:$Q, 'Основной эфир'!$B:$B=$A7,'Основной эфир'!$C:$C=$B7,'Основной эфир'!$I:$I=$C7)), 0) "),12.0) -> 12 | H7: =IFERROR(__xludf.DUMMYFUNCTION("IFERROR(AVERAGE(filter('Основной эфир'!$Y:$Y, 'Основной эфир'!$B:$B=$A7,'Основной эфир'!$C:$C=$B7,'Основной эфир'!$I:$I=$C7)), 0) "),10.0) -> 10 | I7: =IFERROR(__xludf.DUMMYFUNCTION("IFERROR(AVERAGE(filter('Основной эфир'!$AE:$AE, 'Основной эфир'!$B:$B=$A7,'Основной эфир'!$C:$C=$B7,'Основной эфир'!$I:$I=$C7)), 0) "),3446.4560000000006) -> 3446.456 | J7: =IFERROR(__xludf.DUMMYFUNCTION("IFERROR(SUM(filter('Основной эфир'!$AL:$AL, 'Основной эфир'!$B:$B=$A7,'Основной эфир'!$C:$C=$B7,'Основной эфир'!$I:$I=$C7)), 0) "),48000.0) -> 48000 | K7: =IFERROR(__xludf.DUMMYFUNCTION("IFERROR(REGEXREPLACE(unique(filter('Основной эфир'!$A:$A, 'Основной эфир'!$B:$B=$A7,'Основной эфир'!$C:$C=$B7,'Основной эфир'!$I:$I=$C7)), ""\d+"", """"),"""")"),"KZN") -> KZN | L7: =IFERROR(__xludf.DUMMYFUNCTION("IFERROR(unique(filter('Основной эфир'!$F:$F, 'Основной эфир'!$B:$B=$A7,'Основной эфир'!$C:$C=$B7,'Основной эфир'!$I:$I=$C7)),"""")"),"Б") -> Б | M7: =if(C7<>"",if(or(lower(K7)="u",lower(K7)="nn",lower(K7)="kzn"),"миллионник",if(lower(K7)="msc","мск","остальное")),"") -> миллионник | N7: =IFERROR(__xludf.DUMMYFUNCTION("IFERROR(SWITCH(lower(join("" "",L7:M7)),""а миллионник"", 62.5,""б миллионник"", 75,""а мск"", 50, ""б мск"", 62.5, ""a остальное"", 70, ""б остальное"", 80)/100,0)"),0.75) -> 0.75 | O7: =IFERROR(J7-J7*N7,0) -> 12000 | P7: =IFERROR(__xludf.DUMMYFUNCTION("IFERROR(sum(filter('Генеральный баннер'!$O:$O, 'Генеральный баннер'!$B:$B=$A7,'Генеральный баннер'!$C:$C=$B7,'Генеральный баннер'!$I:$I=$C7)), 0) "),1069.0) -> 1069 | Q7: =IFERROR(__xludf.DUMMYFUNCTION("IFERROR(sum(filter('Генеральный баннер'!$Q:$Q, 'Генеральный баннер'!$B:$B=$A7,'Генеральный баннер'!$C:$C=$B7,'Генеральный баннер'!$I:$I=$C7)), 0) "),12.0) -> 12 | R7: =IFERROR(__xludf.DUMMYFUNCTION("IFERROR(AVERAGE(filter('Генеральный баннер'!$AA:$AA, 'Генеральный баннер'!$B:$B=$A7,'Генеральный баннер'!$C:$C=$B7,'Генеральный баннер'!$I:$I=$C7)), 0) "),8616.14) -> 8616.14 | S7: =IFERROR(__xludf.DUMMYFUNCTION("IFERROR(SUM(filter('Генеральный баннер'!$AH:$AH, 'Генеральный баннер'!$B:$B=$A7,'Генеральный баннер'!$C:$C=$B7,'Генеральный баннер'!$I:$I=$C7)), 0) "),96000.0) -> 96000 | T7: =IFERROR(__xludf.DUMMYFUNCTION("IFERROR(REGEXREPLACE(unique(filter('Генеральный баннер'!$A:$A, 'Генеральный баннер'!$B:$B=$A7,'Генеральный баннер'!$C:$C=$B7,'Генеральный баннер'!$I:$I=$C7)), ""\d+"", """"),"""")"),"KZN") -> KZN | U7: =IFERROR(__xludf.DUMMYFUNCTION("IFERROR(unique(filter('Генеральный баннер'!$F:$F, 'Генеральный баннер'!$B:$B=$A7,'Генеральный баннер'!$C:$C=$B7,'Генеральный баннер'!$I:$I=$C7)),"""")"),"Б") -> Б | V7: =if(L7<>"",if(or(lower(T7)="u",lower(T7)="nn",lower(T7)="kzn"),"миллионник",if(lower(T7)="msc","мск","остальное")),"") -> миллионник | W7: =IFERROR(__xludf.DUMMYFUNCTION("IFERROR(SWITCH(lower(join("" "",U7:V7)),""а миллионник"", 62.5,""б миллионник"", 75,""а мск"", 50, ""б мск"", 62.5, ""a остальное"", 70, ""б остальное"", 80)/100,0)"),0.75) -> 0.75 | X7: =IFERROR(S7-S7*W7,0) -> 24000
D8: =IFERROR(__xludf.DUMMYFUNCTION("IFERROR(sum(filter('Основной эфир'!$AA:$AA, 'Основной эфир'!$B:$B=$A8,'Основной эфир'!$C:$C=$B8,'Основной эфир'!$I:$I=$C8)), 0) "),0.0) -> 0 | E8: =IFERROR(__xludf.DUMMYFUNCTION("IFERROR(sum(filter('Основной эфир'!$AC:$AC, 'Основной эфир'!$B:$B=$A8,'Основной эфир'!$C:$C=$B8,'Основной эфир'!$I:$I=$C8)), 0) "),0.0) -> 0 | F8: =IFERROR(__xludf.DUMMYFUNCTION("IFERROR(sum(filter('Основной эфир'!$O:$O, 'Основной эфир'!$B:$B=$A8,'Основной эфир'!$C:$C=$B8,'Основной эфир'!$I:$I=$C8)), 0) "),0.0) -> 0 | G8: =IFERROR(__xludf.DUMMYFUNCTION("IFERROR(sum(filter('Основной эфир'!$Q:$Q, 'Основной эфир'!$B:$B=$A8,'Основной эфир'!$C:$C=$B8,'Основной эфир'!$I:$I=$C8)), 0) "),0.0) -> 0 | H8: =IFERROR(__xludf.DUMMYFUNCTION("IFERROR(AVERAGE(filter('Основной эфир'!$Y:$Y, 'Основной эфир'!$B:$B=$A8,'Основной эфир'!$C:$C=$B8,'Основной эфир'!$I:$I=$C8)), 0) "),0.0) -> 0 | I8: =IFERROR(__xludf.DUMMYFUNCTION("IFERROR(AVERAGE(filter('Основной эфир'!$AE:$AE, 'Основной эфир'!$B:$B=$A8,'Основной эфир'!$C:$C=$B8,'Основной эфир'!$I:$I=$C8)), 0) "),0.0) -> 0 | J8: =IFERROR(__xludf.DUMMYFUNCTION("IFERROR(SUM(filter('Основной эфир'!$AL:$AL, 'Основной эфир'!$B:$B=$A8,'Основной эфир'!$C:$C=$B8,'Основной эфир'!$I:$I=$C8)), 0) "),0.0) -> 0 | K8: =IFERROR(__xludf.DUMMYFUNCTION("IFERROR(REGEXREPLACE(unique(filter('Основной эфир'!$A:$A, 'Основной эфир'!$B:$B=$A8,'Основной эфир'!$C:$C=$B8,'Основной эфир'!$I:$I=$C8)), ""\d+"", """"),"""")"),"") | L8: =IFERROR(__xludf.DUMMYFUNCTION("IFERROR(unique(filter('Основной эфир'!$F:$F, 'Основной эфир'!$B:$B=$A8,'Основной эфир'!$C:$C=$B8,'Основной эфир'!$I:$I=$C8)),"""")"),"") | M8: =if(C8<>"",if(or(lower(K8)="u",lower(K8)="nn",lower(K8)="kzn"),"миллионник",if(lower(K8)="msc","мск","остальное")),"") | N8: =IFERROR(__xludf.DUMMYFUNCTION("IFERROR(SWITCH(lower(join("" "",L8:M8)),""а миллионник"", 62.5,""б миллионник"", 75,""а мск"", 50, ""б мск"", 62.5, ""a остальное"", 70, ""б остальное"", 80)/100,0)"),0.0) -> 0 | O8: =IFERROR(J8-J8*N8,0) -> 0 | P8: =IFERROR(__xludf.DUMMYFUNCTION("IFERROR(sum(filter('Генеральный баннер'!$O:$O, 'Генеральный баннер'!$B:$B=$A8,'Генеральный баннер'!$C:$C=$B8,'Генеральный баннер'!$I:$I=$C8)), 0) "),0.0) -> 0 | Q8: =IFERROR(__xludf.DUMMYFUNCTION("IFERROR(sum(filter('Генеральный баннер'!$Q:$Q, 'Генеральный баннер'!$B:$B=$A8,'Генеральный баннер'!$C:$C=$B8,'Генеральный баннер'!$I:$I=$C8)), 0) "),0.0) -> 0 | R8: =IFERROR(__xludf.DUMMYFUNCTION("IFERROR(AVERAGE(filter('Генеральный баннер'!$AA:$AA, 'Генеральный баннер'!$B:$B=$A8,'Генеральный баннер'!$C:$C=$B8,'Генеральный баннер'!$I:$I=$C8)), 0) "),0.0) -> 0 | S8: =IFERROR(__xludf.DUMMYFUNCTION("IFERROR(SUM(filter('Генеральный баннер'!$AH:$AH, 'Генеральный баннер'!$B:$B=$A8,'Генеральный баннер'!$C:$C=$B8,'Генеральный баннер'!$I:$I=$C8)), 0) "),0.0) -> 0 | T8: =IFERROR(__xludf.DUMMYFUNCTION("IFERROR(REGEXREPLACE(unique(filter('Генеральный баннер'!$A:$A, 'Генеральный баннер'!$B:$B=$A8,'Генеральный баннер'!$C:$C=$B8,'Генеральный баннер'!$I:$I=$C8)), ""\d+"", """"),"""")"),"") | U8: =IFERROR(__xludf.DUMMYFUNCTION("IFERROR(unique(filter('Генеральный баннер'!$F:$F, 'Генеральный баннер'!$B:$B=$A8,'Генеральный баннер'!$C:$C=$B8,'Генеральный баннер'!$I:$I=$C8)),"""")"),"") | V8: =if(L8<>"",if(or(lower(T8)="u",lower(T8)="nn",lower(T8)="kzn"),"миллионник",if(lower(T8)="msc","мск","остальное")),"") | W8: =IFERROR(__xludf.DUMMYFUNCTION("IFERROR(SWITCH(lower(join("" "",U8:V8)),""а миллионник"", 62.5,""б миллионник"", 75,""а мск"", 50, ""б мск"", 62.5, ""a остальное"", 70, ""б остальное"", 80)/100,0)"),0.0) -> 0 | X8: =IFERROR(S8-S8*W8,0) -> 0
D9: =IFERROR(__xludf.DUMMYFUNCTION("IFERROR(sum(filter('Основной эфир'!$AA:$AA, 'Основной эфир'!$B:$B=$A9,'Основной эфир'!$C:$C=$B9,'Основной эфир'!$I:$I=$C9)), 0) "),0.0) -> 0 | E9: =IFERROR(__xludf.DUMMYFUNCTION("IFERROR(sum(filter('Основной эфир'!$AC:$AC, 'Основной эфир'!$B:$B=$A9,'Основной эфир'!$C:$C=$B9,'Основной эфир'!$I:$I=$C9)), 0) "),0.0) -> 0 | F9: =IFERROR(__xludf.DUMMYFUNCTION("IFERROR(sum(filter('Основной эфир'!$O:$O, 'Основной эфир'!$B:$B=$A9,'Основной эфир'!$C:$C=$B9,'Основной эфир'!$I:$I=$C9)), 0) "),0.0) -> 0 | G9: =IFERROR(__xludf.DUMMYFUNCTION("IFERROR(sum(filter('Основной эфир'!$Q:$Q, 'Основной эфир'!$B:$B=$A9,'Основной эфир'!$C:$C=$B9,'Основной эфир'!$I:$I=$C9)), 0) "),0.0) -> 0 | H9: =IFERROR(__xludf.DUMMYFUNCTION("IFERROR(AVERAGE(filter('Основной эфир'!$Y:$Y, 'Основной эфир'!$B:$B=$A9,'Основной эфир'!$C:$C=$B9,'Основной эфир'!$I:$I=$C9)), 0) "),0.0) -> 0 | I9: =IFERROR(__xludf.DUMMYFUNCTION("IFERROR(AVERAGE(filter('Основной эфир'!$AE:$AE, 'Основной эфир'!$B:$B=$A9,'Основной эфир'!$C:$C=$B9,'Основной эфир'!$I:$I=$C9)), 0) "),0.0) -> 0 | J9: =IFERROR(__xludf.DUMMYFUNCTION("IFERROR(SUM(filter('Основной эфир'!$AL:$AL, 'Основной эфир'!$B:$B=$A9,'Основной эфир'!$C:$C=$B9,'Основной эфир'!$I:$I=$C9)), 0) "),0.0) -> 0 | K9: =IFERROR(__xludf.DUMMYFUNCTION("IFERROR(REGEXREPLACE(unique(filter('Основной эфир'!$A:$A, 'Основной эфир'!$B:$B=$A9,'Основной эфир'!$C:$C=$B9,'Основной эфир'!$I:$I=$C9)), ""\d+"", """"),"""")"),"") | L9: =IFERROR(__xludf.DUMMYFUNCTION("IFERROR(unique(filter('Основной эфир'!$F:$F, 'Основной эфир'!$B:$B=$A9,'Основной эфир'!$C:$C=$B9,'Основной эфир'!$I:$I=$C9)),"""")"),"") | M9: =if(C9<>"",if(or(lower(K9)="u",lower(K9)="nn",lower(K9)="kzn"),"миллионник",if(lower(K9)="msc","мск","остальное")),"") | N9: =IFERROR(__xludf.DUMMYFUNCTION("IFERROR(SWITCH(lower(join("" "",L9:M9)),""а миллионник"", 62.5,""б миллионник"", 75,""а мск"", 50, ""б мск"", 62.5, ""a остальное"", 70, ""б остальное"", 80)/100,0)"),0.0) -> 0 | O9: =IFERROR(J9-J9*N9,0) -> 0 | P9: =IFERROR(__xludf.DUMMYFUNCTION("IFERROR(sum(filter('Генеральный баннер'!$O:$O, 'Генеральный баннер'!$B:$B=$A9,'Генеральный баннер'!$C:$C=$B9,'Генеральный баннер'!$I:$I=$C9)), 0) "),0.0) -> 0 | Q9: =IFERROR(__xludf.DUMMYFUNCTION("IFERROR(sum(filter('Генеральный баннер'!$Q:$Q, 'Генеральный баннер'!$B:$B=$A9,'Генеральный баннер'!$C:$C=$B9,'Генеральный баннер'!$I:$I=$C9)), 0) "),0.0) -> 0 | R9: =IFERROR(__xludf.DUMMYFUNCTION("IFERROR(AVERAGE(filter('Генеральный баннер'!$AA:$AA, 'Генеральный баннер'!$B:$B=$A9,'Генеральный баннер'!$C:$C=$B9,'Генеральный баннер'!$I:$I=$C9)), 0) "),0.0) -> 0 | S9: =IFERROR(__xludf.DUMMYFUNCTION("IFERROR(SUM(filter('Генеральный баннер'!$AH:$AH, 'Генеральный баннер'!$B:$B=$A9,'Генеральный баннер'!$C:$C=$B9,'Генеральный баннер'!$I:$I=$C9)), 0) "),0.0) -> 0 | T9: =IFERROR(__xludf.DUMMYFUNCTION("IFERROR(REGEXREPLACE(unique(filter('Генеральный баннер'!$A:$A, 'Генеральный баннер'!$B:$B=$A9,'Генеральный баннер'!$C:$C=$B9,'Генеральный баннер'!$I:$I=$C9)), ""\d+"", """"),"""")"),"") | U9: =IFERROR(__xludf.DUMMYFUNCTION("IFERROR(unique(filter('Генеральный баннер'!$F:$F, 'Генеральный баннер'!$B:$B=$A9,'Генеральный баннер'!$C:$C=$B9,'Генеральный баннер'!$I:$I=$C9)),"""")"),"") | V9: =if(L9<>"",if(or(lower(T9)="u",lower(T9)="nn",lower(T9)="kzn"),"миллионник",if(lower(T9)="msc","мск","остальное")),"") | W9: =IFERROR(__xludf.DUMMYFUNCTION("IFERROR(SWITCH(lower(join("" "",U9:V9)),""а миллионник"", 62.5,""б миллионник"", 75,""а мск"", 50, ""б мск"", 62.5, ""a остальное"", 70, ""б остальное"", 80)/100,0)"),0.0) -> 0 | X9: =IFERROR(S9-S9*W9,0) -> 0
D10: =IFERROR(__xludf.DUMMYFUNCTION("IFERROR(sum(filter('Основной эфир'!$AA:$AA, 'Основной эфир'!$B:$B=$A10,'Основной эфир'!$C:$C=$B10,'Основной эфир'!$I:$I=$C10)), 0) "),0.0) -> 0 | E10: =IFERROR(__xludf.DUMMYFUNCTION("IFERROR(sum(filter('Основной эфир'!$AC:$AC, 'Основной эфир'!$B:$B=$A10,'Основной эфир'!$C:$C=$B10,'Основной эфир'!$I:$I=$C10)), 0) "),0.0) -> 0 | F10: =IFERROR(__xludf.DUMMYFUNCTION("IFERROR(sum(filter('Основной эфир'!$O:$O, 'Основной эфир'!$B:$B=$A10,'Основной эфир'!$C:$C=$B10,'Основной эфир'!$I:$I=$C10)), 0) "),0.0) -> 0 | G10: =IFERROR(__xludf.DUMMYFUNCTION("IFERROR(sum(filter('Основной эфир'!$Q:$Q, 'Основной эфир'!$B:$B=$A10,'Основной эфир'!$C:$C=$B10,'Основной эфир'!$I:$I=$C10)), 0) "),0.0) -> 0 | H10: =IFERROR(__xludf.DUMMYFUNCTION("IFERROR(AVERAGE(filter('Основной эфир'!$Y:$Y, 'Основной эфир'!$B:$B=$A10,'Основной эфир'!$C:$C=$B10,'Основной эфир'!$I:$I=$C10)), 0) "),0.0) -> 0 | I10: =IFERROR(__xludf.DUMMYFUNCTION("IFERROR(AVERAGE(filter('Основной эфир'!$AE:$AE, 'Основной эфир'!$B:$B=$A10,'Основной эфир'!$C:$C=$B10,'Основной эфир'!$I:$I=$C10)), 0) "),0.0) -> 0 | J10: =IFERROR(__xludf.DUMMYFUNCTION("IFERROR(SUM(filter('Основной эфир'!$AL:$AL, 'Основной эфир'!$B:$B=$A10,'Основной эфир'!$C:$C=$B10,'Основной эфир'!$I:$I=$C10)), 0) "),0.0) -> 0 | K10: =IFERROR(__xludf.DUMMYFUNCTION("IFERROR(REGEXREPLACE(unique(filter('Основной эфир'!$A:$A, 'Основной эфир'!$B:$B=$A10,'Основной эфир'!$C:$C=$B10,'Основной эфир'!$I:$I=$C10)), ""\d+"", """"),"""")"),"") | L10: =IFERROR(__xludf.DUMMYFUNCTION("IFERROR(unique(filter('Основной эфир'!$F:$F, 'Основной эфир'!$B:$B=$A10,'Основной эфир'!$C:$C=$B10,'Основной эфир'!$I:$I=$C10)),"""")"),"") | M10: =if(C10<>"",if(or(lower(K10)="u",lower(K10)="nn",lower(K10)="kzn"),"миллионник",if(lower(K10)="msc","мск","остальное")),"") | N10: =IFERROR(__xludf.DUMMYFUNCTION("IFERROR(SWITCH(lower(join("" "",L10:M10)),""а миллионник"", 62.5,""б миллионник"", 75,""а мск"", 50, ""б мск"", 62.5, ""a остальное"", 70, ""б остальное"", 80)/100,0)"),0.0) -> 0 | O10: =IFERROR(J10-J10*N10,0) -> 0 | P10: =IFERROR(__xludf.DUMMYFUNCTION("IFERROR(sum(filter('Генеральный баннер'!$O:$O, 'Генеральный баннер'!$B:$B=$A10,'Генеральный баннер'!$C:$C=$B10,'Генеральный баннер'!$I:$I=$C10)), 0) "),0.0) -> 0 | Q10: =IFERROR(__xludf.DUMMYFUNCTION("IFERROR(sum(filter('Генеральный баннер'!$Q:$Q, 'Генеральный баннер'!$B:$B=$A10,'Генеральный баннер'!$C:$C=$B10,'Генеральный баннер'!$I:$I=$C10)), 0) "),0.0) -> 0 | R10: =IFERROR(__xludf.DUMMYFUNCTION("IFERROR(AVERAGE(filter('Генеральный баннер'!$AA:$AA, 'Генеральный баннер'!$B:$B=$A10,'Генеральный баннер'!$C:$C=$B10,'Генеральный баннер'!$I:$I=$C10)), 0) "),0.0) -> 0 | S10: =IFERROR(__xludf.DUMMYFUNCTION("IFERROR(SUM(filter('Генеральный баннер'!$AH:$AH, 'Генеральный баннер'!$B:$B=$A10,'Генеральный баннер'!$C:$C=$B10,'Генеральный баннер'!$I:$I=$C10)), 0) "),0.0) -> 0 | T10: =IFERROR(__xludf.DUMMYFUNCTION("IFERROR(REGEXREPLACE(unique(filter('Генеральный баннер'!$A:$A, 'Генеральный баннер'!$B:$B=$A10,'Генеральный баннер'!$C:$C=$B10,'Генеральный баннер'!$I:$I=$C10)), ""\d+"", """"),"""")"),"") | U10: =IFERROR(__xludf.DUMMYFUNCTION("IFERROR(unique(filter('Генеральный баннер'!$F:$F, 'Генеральный баннер'!$B:$B=$A10,'Генеральный баннер'!$C:$C=$B10,'Генеральный баннер'!$I:$I=$C10)),"""")"),"") | V10: =if(L10<>"",if(or(lower(T10)="u",lower(T10)="nn",lower(T10)="kzn"),"миллионник",if(lower(T10)="msc","мск","остальное")),"") | W10: =IFERROR(__xludf.DUMMYFUNCTION("IFERROR(SWITCH(lower(join("" "",U10:V10)),""а миллионник"", 62.5,""б миллионник"", 75,""а мск"", 50, ""б мск"", 62.5, ""a остальное"", 70, ""б остальное"", 80)/100,0)"),0.0) -> 0 | X10: =IFERROR(S10-S10*W10,0) -> 0
D11: =IFERROR(__xludf.DUMMYFUNCTION("IFERROR(sum(filter('Основной эфир'!$AA:$AA, 'Основной эфир'!$B:$B=$A11,'Основной эфир'!$C:$C=$B11,'Основной эфир'!$I:$I=$C11)), 0) "),0.0) -> 0 | E11: =IFERROR(__xludf.DUMMYFUNCTION("IFERROR(sum(filter('Основной эфир'!$AC:$AC, 'Основной эфир'!$B:$B=$A11,'Основной эфир'!$C:$C=$B11,'Основной эфир'!$I:$I=$C11)), 0) "),0.0) -> 0 | F11: =IFERROR(__xludf.DUMMYFUNCTION("IFERROR(sum(filter('Основной эфир'!$O:$O, 'Основной эфир'!$B:$B=$A11,'Основной эфир'!$C:$C=$B11,'Основной эфир'!$I:$I=$C11)), 0) "),0.0) -> 0 | G11: =IFERROR(__xludf.DUMMYFUNCTION("IFERROR(sum(filter('Основной эфир'!$Q:$Q, 'Основной эфир'!$B:$B=$A11,'Основной эфир'!$C:$C=$B11,'Основной эфир'!$I:$I=$C11)), 0) "),0.0) -> 0 | H11: =IFERROR(__xludf.DUMMYFUNCTION("IFERROR(AVERAGE(filter('Основной эфир'!$Y:$Y, 'Основной эфир'!$B:$B=$A11,'Основной эфир'!$C:$C=$B11,'Основной эфир'!$I:$I=$C11)), 0) "),0.0) -> 0 | I11: =IFERROR(__xludf.DUMMYFUNCTION("IFERROR(AVERAGE(filter('Основной эфир'!$AE:$AE, 'Основной эфир'!$B:$B=$A11,'Основной эфир'!$C:$C=$B11,'Основной эфир'!$I:$I=$C11)), 0) "),0.0) -> 0 | J11: =IFERROR(__xludf.DUMMYFUNCTION("IFERROR(SUM(filter('Основной эфир'!$AL:$AL, 'Основной эфир'!$B:$B=$A11,'Основной эфир'!$C:$C=$B11,'Основной эфир'!$I:$I=$C11)), 0) "),0.0) -> 0 | K11: =IFERROR(__xludf.DUMMYFUNCTION("IFERROR(REGEXREPLACE(unique(filter('Основной эфир'!$A:$A, 'Основной эфир'!$B:$B=$A11,'Основной эфир'!$C:$C=$B11,'Основной эфир'!$I:$I=$C11)), ""\d+"", """"),"""")"),"") | L11: =IFERROR(__xludf.DUMMYFUNCTION("IFERROR(unique(filter('Основной эфир'!$F:$F, 'Основной эфир'!$B:$B=$A11,'Основной эфир'!$C:$C=$B11,'Основной эфир'!$I:$I=$C11)),"""")"),"") | M11: =if(C11<>"",if(or(lower(K11)="u",lower(K11)="nn",lower(K11)="kzn"),"миллионник",if(lower(K11)="msc","мск","остальное")),"") | N11: =IFERROR(__xludf.DUMMYFUNCTION("IFERROR(SWITCH(lower(join("" "",L11:M11)),""а миллионник"", 62.5,""б миллионник"", 75,""а мск"", 50, ""б мск"", 62.5, ""a остальное"", 70, ""б остальное"", 80)/100,0)"),0.0) -> 0 | O11: =IFERROR(J11-J11*N11,0) -> 0 | P11: =IFERROR(__xludf.DUMMYFUNCTION("IFERROR(sum(filter('Генеральный баннер'!$O:$O, 'Генеральный баннер'!$B:$B=$A11,'Генеральный баннер'!$C:$C=$B11,'Генеральный баннер'!$I:$I=$C11)), 0) "),0.0) -> 0 | Q11: =IFERROR(__xludf.DUMMYFUNCTION("IFERROR(sum(filter('Генеральный баннер'!$Q:$Q, 'Генеральный баннер'!$B:$B=$A11,'Генеральный баннер'!$C:$C=$B11,'Генеральный баннер'!$I:$I=$C11)), 0) "),0.0) -> 0 | R11: =IFERROR(__xludf.DUMMYFUNCTION("IFERROR(AVERAGE(filter('Генеральный баннер'!$AA:$AA, 'Генеральный баннер'!$B:$B=$A11,'Генеральный баннер'!$C:$C=$B11,'Генеральный баннер'!$I:$I=$C11)), 0) "),0.0) -> 0 | S11: =IFERROR(__xludf.DUMMYFUNCTION("IFERROR(SUM(filter('Генеральный баннер'!$AH:$AH, 'Генеральный баннер'!$B:$B=$A11,'Генеральный баннер'!$C:$C=$B11,'Генеральный баннер'!$I:$I=$C11)), 0) "),0.0) -> 0 | T11: =IFERROR(__xludf.DUMMYFUNCTION("IFERROR(REGEXREPLACE(unique(filter('Генеральный баннер'!$A:$A, 'Генеральный баннер'!$B:$B=$A11,'Генеральный баннер'!$C:$C=$B11,'Генеральный баннер'!$I:$I=$C11)), ""\d+"", """"),"""")"),"") | U11: =IFERROR(__xludf.DUMMYFUNCTION("IFERROR(unique(filter('Генеральный баннер'!$F:$F, 'Генеральный баннер'!$B:$B=$A11,'Генеральный баннер'!$C:$C=$B11,'Генеральный баннер'!$I:$I=$C11)),"""")"),"") | V11: =if(L11<>"",if(or(lower(T11)="u",lower(T11)="nn",lower(T11)="kzn"),"миллионник",if(lower(T11)="msc","мск","остальное")),"") | W11: =IFERROR(__xludf.DUMMYFUNCTION("IFERROR(SWITCH(lower(join("" "",U11:V11)),""а миллионник"", 62.5,""б миллионник"", 75,""а мск"", 50, ""б мск"", 62.5, ""a остальное"", 70, ""б остальное"", 80)/100,0)"),0.0) -> 0 | X11: =IFERROR(S11-S11*W11,0) -> 0
